Workbook
Name billion: About!$A$71
Name Diesel_FE_2024: '[1]Fuel Economy Stds'!$F$54
Name Eno_TM: '[2]1997 Table 1a Modified'!#REF!
Name Eno_TM: '[2]1997 Table 1a Modified'!#REF!
Name Eno_TM: '[2]1997 Table 1a Modified'!#REF!
Name Eno_Tons: '[2]1997 Table 1a Modified'!#REF!
Name Eno_Tons: '[2]1997 Table 1a Modified'!#REF!
Name Eno_Tons: '[2]1997 Table 1a Modified'!#REF!
Name EV_FE_2024: '[1]Fuel Economy Stds'!$F$51
Name Gasoline_FE_2024: '[1]Fuel Economy Stds'!#REF!
Name Hydg_FE_2024: '[1]Fuel Economy Stds'!$F$57
Name LPG_FE_2024: '[1]Fuel Economy Stds'!$F$56
Name NG_FE_2024: '[1]Fuel Economy Stds'!$F$52
Name NTS_YR: [3]About!$B$136
Name PHEV_FE_2024: '[1]Fuel Economy Stds'!$F$55
Name Sum_T2: '[2]1997 Table 1a Modified'!#REF!
Name Sum_T2: '[2]1997 Table 1a Modified'!#REF!
Name Sum_T2: '[2]1997 Table 1a Modified'!#REF!
Name Sum_TTM: '[2]1997 Table 1a Modified'!#REF!
Name Sum_TTM: '[2]1997 Table 1a Modified'!#REF!
Name Sum_TTM: '[2]1997 Table 1a Modified'!#REF!
Name ti_tbl_50: #REF!
Name ti_tbl_50: #REF!
Name ti_tbl_50: #REF!
Name ti_tbl_69: #REF!
Name ti_tbl_69: #REF!
Name ti_tbl_69: #REF!
Name trillion: About!$A$72

Sheet About
A1: SYFAFE Start Year Fleet Avg Fuel Economy | B1: Arkansas | C1: 44944 | F1: State | G1: State
B2: =LOOKUP(B1,F2:G51,G2:G51) -> AR | F2: Alabama | G2: AL
A3: Sources: | B3: See Notes section for which vehicle types use which sources | F3: Alaska | G3: AK
B4: EIA | F4: Arizona | G4: AZ
B5: 2020 | F5: Arkansas | G5: AR
B6: Annual Energy Outlook 2020 | F6: California | G6: CA
B7: https://www.eia.gov/outlooks/aeo/tables_ref.cfm | F7: Colorado | G7: CO
B8: Tables 7, 25, 36, 37, 38, 40, 41, 43, 46, 47, 48, 49 | F8: Connecticut | G8: CT
C9: Passenger Rail Scaling | F9: Delaware | G9: DE
B10: Bureau of Transportation Statistics | C10: American Public Transit Association | F10: Florida | G10: FL
B11: 2018 | C11: 2020 | F11: Georgia | G11: GA
B12: National Transportation Statistics | C12: National Transit Database 2019 | F12: Hawaii | G12: HI
B13: https://www.bts.gov/content/us-passenger-miles | C13: https://www.apta.com/research-technical-resources/transit-statistics/ntd-data-tables/ | F13: Idaho | G13: ID
B14: Table 1-40 | C14: Service_Statistic and Fuel and Energy_Statistic | F14: Illinois | G14: IL
F15: Indiana | G15: IN
B16: U.S. Coast Guard | F16: Iowa | G16: IA
B17: 2013 | F17: Kansas | G17: KS
B18: National Recreational Boating Survey 2012 | F18: Kentucky | G18: KY
B19: http://www.uscgboating.org/library/recreational-boating-servey/2012survey%20report.pdf | F19: Louisiana | G19: LA
B20: Page 63, Table 40 | F20: Maine | G20: ME
F21: Maryland | G21: MD
B22: U.S. Department of Energy | F22: Massachusetts | G22: MA
B23: 2015 | F23: Michigan | G23: MI
B24: Fuel Cells Fact Sheet | F24: Minnesota | G24: MN
B25: https://www.energy.gov/sites/prod/files/2015/11/f27/fcto_fuel_cells_fact_sheet.pdf | F25: Mississippi | G25: MS
F26: Missouri | G26: MO
B27: Others as noted on "Calculations Etc" tab | F27: Montana | G27: MT
F28: Nebraska | G28: NE
A29: Notes | F29: Nevada | G29: NV
A30: This variable gives fleet-wide fuel economy in units of cargo distance per BTU. | F30: New Hampshire | G30: NH
F31: New Jersey | G31: NJ
A32: passenger LDVs, freight LDVs and HDVs | F32: New Mexico | G32: NM
A33: Sources: AEO 37, 41, 43, 36, 49 | F33: New York | G33: NY
A34: Vehicle distance traveled and energy consumption by vehicle technology is available for passenger LDVs, commercial light trucks and HDVs. | F34: North Carolina | G34: NC
A35: We sum vehicle distance traveled by technology, divide by energy consumption of that technology, and multiply by the vehicle loading values used in the | F35: North Dakota | G35: ND
A36: EPS to convert from miles/BTU to thing-miles/BTU. The AEO shows 0 energy consumption by battery electric and plug-in hybrid commercial freight | F36: Ohio | G36: OH
A37: trucks in 2019. Therefore, we use 2020 data for those two technologies. | F37: Oklahoma | G37: OK
F38: Oregon | G38: OR
A39: freight rail | F39: Pennsylvania | G39: PA
A40: Sources: AEO 7 | F40: Rhode Island | G40: RI
A41: Freight rail efficiency is available directly from AEO 7. | F41: South Carolina | G41: SC
F42: South Dakota | G42: SD
A43: passenger rail | F43: Tennessee | G43: TN
A44: Sources: AEO 7, 36, and others as noted on "Calculations Etc" tab | F44: Texas | G44: TX
A45: Energy demand by fuel type is available from AEO 36. We adjust the energy demand for diesel and electricity by an efficiency factor for electric rail | F45: Utah | G45: UT
A46: technologies to find the share of travel demand from each vehicle technology, then apply those shares to the passenger-miles reported in AEO 7. | F46: Vermont | G46: VT
A47: We divide the passenger-miles for each technology by the energy demand for the respective technologies. | F47: Virginia | G47: VA
F48: Washington | G48: WA
A49: freight ships | F49: West Virginia | G49: WV
A50: Sources: AEO 7, AEO 48, AEO 49 | F50: Wisconsin | G50: WI
A51: Freight ship efficiency (for domestic shipping) is available directly from AEO 7. We | F51: Wyoming | G51: WY
A52: use this value to represent all freight shipping.
A54: other vehicle types
A55: Sources: EPS files BAADTbVT, AVLo, SYVbT, AEO 7 and 36, and other sources as noted in Calcualtions tab
A56: We classify AEO's light commercial trucks category as well as light-medium and medium duty vehicles
A57: in "freight LDVs" and heavy duty vehicles in "freight HDVs."
A59: Although vehicle distance traveled is available for some of these vehicle types in the AEO, vehicle distance travled varies by technology type, and the EPS assigns a
A60: constant average distance traveled across technologies. To ensure energy consumption is calculated correctly, we therefore divide cargo distance in the EPS
A61: (BAADTbVT * AVLo * SYVbT) by energy consumption from AEO to find fuel economy.
A63: freight motorbikes
A64: This vehicle type is not used in the U.S. model.
A66: Calibration Adjustments
A67: This variable may need calibration after all other data are in place. See the notes on the
... A69: calibration and how to perform it.
A71: =10^9 -> 1000000000
A72: =10^12 -> 1000000000000

Sheet AEO 7
B1: highogs.d112619a | C1: 2019 | D1: 2020 | E1: 2021 | F1: 2022 | G1: 2023 | H1: 2024 | I1: 2025 | J1: 2026 | K1: 2027 | L1: 2028 | M1: 2029 | N1: 2030 | O1: 2031 | P1: 2032 | Q1: 2033 | R1: 2034 | S1: 2035 | T1: 2036 | U1: 2037 | V1: 2038 | W1: 2039 | X1: 2040 | Y1: 2041 | Z1: 2042 | AA1: 2043 | AB1: 2044 | AC1: 2045 | AD1: 2046 | AE1: 2047 | AF1: 2048 | AG1: 2049 | AH1: 2050
C3: Report | D3: Annual Energy Outlook 2020
C4: Scenario | D4: highogs | G4: High oil and gas supply
C5: Datekey | D5: d112619a
C6: Release Date | E6: January 2020
A10: TKI000 | B10: 7. Transportation Sector Key Indicators and Delivered Energy Consumption
AI12: 2019-
B13: Key Indicators and Consumption | C13: 2019 | D13: 2020 | E13: 2021 | F13: 2022 | G13: 2023 | H13: 2024 | I13: 2025 | J13: 2026 | K13: 2027 | L13: 2028 | M13: 2029 | N13: 2030 | O13: 2031 | P13: 2032 | Q13: 2033 | R13: 2034 | S13: 2035 | T13: 2036 | U13: 2037 | V13: 2038 | W13: 2039 | X13: 2040 | Y13: 2041 | Z13: 2042 | AA13: 2043 | AB13: 2044 | AC13: 2045 | AD13: 2046 | AE13: 2047 | AF13: 2048 | AG13: 2049 | AH13: 2050 | AI13: 2050
B15: Key Indicators
B16: Travel Indicators
B17: (billion vehicle miles traveled)
A18: TKI000:ba_Light-DutyVeh | B18: Light-Duty Vehicles less than 8,501 pounds | C18: 2917.2534 | D18: 2975.1255 | E18: 3025.3584 | F18: 3062.7468 | G18: 3083.9775 | H18: 3096.5911 | I18: 3105.9812 | J18: 3125.592 | K18: 3146.8806 | L18: 3167.6331 | M18: 3188.2371 | N18: 3209.8457 | O18: 3233.3459 | P18: 3252.6282 | Q18: 3271.1394 | R18: 3285.1404 | S18: 3295.6909 | T18: 3311.9399 | U18: 3327.9958 | V18: 3344.2627 | W18: 3361.5449 | X18: 3379.7544 | Y18: 3396.2571 | Z18: 3413.8406 | AA18: 3432.0298 | AB18: 3451.1577 | AC18: 3472.0923 | AD18: 3496.9058 | AE18: 3524.3184 | AF18: 3555.4368 | AG18: 3588.8325 | AH18: 3624.4036 | AI18: 0.007026
A19: TKI000:ba_CommercialLig | B19: Commercial Light Trucks 1/ | C19: 99.321114 | D19: 100.61537 | E19: 102.27555 | F19: 103.79449 | G19: 104.99791 | H19: 105.84502 | I19: 106.78965 | J19: 107.83586 | K19: 109.08619 | L19: 110.31479 | M19: 111.61692 | N19: 112.77087 | O19: 114.26243 | P19: 115.52301 | Q19: 116.87927 | R19: 118.14617 | S19: 119.40303 | T19: 120.80527 | U19: 122.15245 | V19: 123.49687 | W19: 124.85643 | X19: 126.2754 | Y19: 127.71654 | Z19: 129.18462 | AA19: 130.707 | AB19: 132.37408 | AC19: 134.19019 | AD19: 136.27534 | AE19: 138.1423 | AF19: 140.20346 | AG19: 142.3405 | AH19: 144.47952 | AI19: 0.012163
A20: TKI000:ba_FreightTrucks | B20: Freight Trucks greater than 10,000 pounds | C20: 299.98956 | D20: 302.9967 | E20: 307.86118 | F20: 312.26749 | G20: 316.85519 | H20: 319.63693 | I20: 322.73798 | J20: 325.80005 | K20: 329.40594 | L20: 332.56686 | M20: 335.87531 | N20: 338.36066 | O20: 342.56183 | P20: 345.99631 | Q20: 349.88959 | R20: 353.1503 | S20: 356.89838 | T20: 360.95453 | U20: 364.40631 | V20: 367.98541 | W20: 371.4613 | X20: 375.17526 | Y20: 378.96576 | Z20: 382.97611 | AA20: 386.86951 | AB20: 391.47946 | AC20: 396.5683 | AD20: 402.70737 | AE20: 407.39862 | AF20: 413.09305 | AG20: 419.04983 | AH20: 425.07648 | AI20: 0.011306
B21: (billion passenger miles traveled)
A22: TKI000:buspassmiles | B22: Bus Transportation | C22: 210.1385 | D22: 211.1262 | E22: 212.11616 | F22: 213.08595 | G22: 214.01353 | H22: 214.96095 | I22: 215.98413 | J22: 216.98978 | K22: 217.98006 | L22: 218.98109 | M22: 219.96805 | N22: 220.90674 | O22: 221.80705 | P22: 222.67883 | Q22: 223.45596 | R22: 224.19052 | S22: 224.88495 | T22: 225.5426 | U22: 226.16771 | V22: 226.76289 | W22: 227.33022 | X22: 227.87238 | Y22: 228.39172 | Z22: 228.89146 | AA22: 229.37672 | AB22: 229.85208 | AC22: 230.32323 | AD22: 230.79691 | AE22: 231.28061 | AF22: 231.78067 | AG22: 232.30583 | AH22: 232.85057 | AI22: 0.003316
A23: TKI000:railpassmiles | B23: Passenger Rail | C23: 41.270718 | D23: 41.874931 | E23: 42.455513 | F23: 42.941441 | G23: 43.403492 | H23: 43.866783 | I23: 44.310471 | J23: 44.75193 | K23: 45.177658 | L23: 45.617382 | M23: 46.05724 | N23: 46.402245 | O23: 46.841446 | P23: 47.267838 | Q23: 47.680485 | R23: 48.055225 | S23: 48.435219 | T23: 48.803921 | U23: 49.166313 | V23: 49.530781 | W23: 49.890511 | X23: 50.244217 | Y23: 50.573273 | Z23: 50.897018 | AA23: 51.222713 | AB23: 51.549355 | AC23: 51.873222 | AD23: 52.227497 | AE23: 52.585468 | AF23: 52.972961 | AG23: 53.355492 | AH23: 53.757782 | AI23: 0.008563
B24: (billion seat miles available)
A25: TKI000:ba_Air | B25: Air | C25: 1222.9934 | D25: 1245.385 | E25: 1270.2579 | F25: 1290.4578 | G25: 1307.1332 | H25: 1325.8835 | I25: 1346.3998 | J25: 1366.3947 | K25: 1386.9773 | L25: 1409.3759 | M25: 1434.0159 | N25: 1459.4762 | O25: 1485.5172 | P25: 1512.3081 | Q25: 1538.871 | R25: 1563.6233 | S25: 1587.829 | T25: 1613.7333 | U25: 1640.1089 | V25: 1667.4398 | W25: 1695.8134 | X25: 1724.8636 | Y25: 1752.9756 | Z25: 1781.3413 | AA25: 1810.3131 | AB25: 1840.631 | AC25: 1874.0067 | AD25: 1909.9596 | AE25: 1947.4512 | AF25: 1987.4026 | AG25: 2028.574 | AH25: 2071.0894 | AI25: 0.017138
B26: (billion ton miles traveled)
A27: TKI000:ba_Rail | B27: Rail | C27: 1807.9623 | D27: 1730.8405 | E27: 1660.0334 | F27: 1651.2594 | G27: 1652.7242 | H27: 1638.4692 | I27: 1604.7769 | J27: 1643.9995 | K27: 1652.7871 | L27: 1662.7437 | M27: 1655.604 | N27: 1648.3021 | O27: 1654.8008 | P27: 1663.8508 | Q27: 1673.921 | R27: 1684.4979 | S27: 1686.808 | T27: 1698.2738 | U27: 1704.6904 | V27: 1701.2555 | W27: 1711.9681 | X27: 1715.1283 | Y27: 1722.2583 | Z27: 1735.2404 | AA27: 1747.2886 | AB27: 1760.9611 | AC27: 1777.2797 | AD27: 1802.0692 | AE27: 1818.0815 | AF27: 1839.249 | AG27: 1861.9969 | AH27: 1888.5421 | AI27: 0.001408
A28: TKI000:ba_DomesticShipp | B28: Domestic Shipping | C28: 416.68076 | D28: 409.15491 | E28: 404.52988 | F28: 396.47797 | G28: 388.98981 | H28: 379.45697 | I28: 370.07324 | J28: 361.44611 | K28: 352.76407 | L28: 343.56067 | M28: 333.81879 | N28: 323.79498 | O28: 320.25205 | P28: 316.14533 | Q28: 312.6521 | R28: 308.38547 | S28: 304.23715 | T28: 300.63773 | U28: 296.55325 | V28: 292.41882 | W28: 288.76395 | X28: 284.95685 | Y28: 283.66168 | Z28: 282.64859 | AA28: 281.33289 | AB28: 280.51184 | AC28: 279.8728 | AD28: 280.18787 | AE28: 279.40164 | AF28: 279.35028 | AG28: 279.69217 | AH28: 280.25092 | AI28: -0.012713
B30: Energy Efficiency Indicators
B31: (miles per gallon)
A32: TKI000:ca_AvgCAFEStand | B32: New Light-Duty Vehicle CAFE Standard 2/ | C32: 34.359936 | D32: 35.284824 | E32: 36.831001 | F32: 38.399506 | G32: 40.110416 | H32: 41.695168 | I32: 43.801582 | J32: 43.785816 | K32: 43.851311 | L32: 43.92421 | M32: 44.014652 | N32: 44.196796 | O32: 44.303349 | P32: 44.390171 | Q32: 44.493732 | R32: 44.60854 | S32: 44.698715 | T32: 44.789574 | U32: 44.882374 | V32: 44.963428 | W32: 45.039089 | X32: 45.11404 | Y32: 45.19231 | Z32: 45.25729 | AA32: 45.303879 | AB32: 45.340485 | AC32: 45.390274 | AD32: 45.422104 | AE32: 45.456978 | AF32: 45.47982 | AG32: 45.506924 | AH32: 45.514236 | AI32: 0.00911
A33: TKI000:ca_CarCAFEStand | B33: New Car 2/ | C33: 40.551155 | D33: 42.338371 | E33: 44.294533 | F33: 46.414017 | G33: 48.711933 | H33: 50.082985 | I33: 52.773457 | J33: 52.773731 | K33: 52.786339 | L33: 52.786339 | M33: 52.798622 | N33: 52.841564 | O33: 52.841564 | P33: 52.841564 | Q33: 52.841564 | R33: 52.841564 | S33: 52.841564 | T33: 52.841564 | U33: 52.841564 | V33: 52.841564 | W33: 52.841564 | X33: 52.842728 | Y33: 52.844788 | Z33: 52.844788 | AA33: 52.844788 | AB33: 52.844788 | AC33: 52.84753 | AD33: 52.84753 | AE33: 52.848724 | AF33: 52.848724 | AG33: 52.84988 | AH33: 52.84988 | AI33: 0.008582
A34: TKI000:ca_TwukCAFEStand | B34: New Light Truck 2/ | C34: 30.2997 | D34: 30.889185 | E34: 32.380001 | F34: 33.7799 | G34: 35.309071 | H34: 36.976479 | I34: 38.765255 | J34: 38.772991 | K34: 38.772991 | L34: 38.772991 | M34: 38.772991 | N34: 38.772991 | O34: 38.772991 | P34: 38.772991 | Q34: 38.772991 | R34: 38.772991 | S34: 38.772991 | T34: 38.772991 | U34: 38.772991 | V34: 38.772991 | W34: 38.772991 | X34: 38.772991 | Y34: 38.772991 | Z34: 38.772991 | AA34: 38.772991 | AB34: 38.772991 | AC34: 38.772991 | AD34: 38.772991 | AE34: 38.772991 | AF34: 38.772991 | AG34: 38.772991 | AH34: 38.773014 | AI34: 0.007986
A35: TKI000:ca_NewVehCred | B35: Compliance New Light-Duty Vehicle 3/ | C35: 35.348213 | D35: 36.238525 | E35: 37.596539 | F35: 39.37933 | G35: 40.901978 | H35: 42.360344 | I35: 44.567291 | J35: 44.831284 | K35: 44.934002 | L35: 45.040806 | M35: 45.183762 | N35: 45.495754 | O35: 45.787571 | P35: 46.034676 | Q35: 46.317448 | R35: 46.60257 | S35: 46.849384 | T35: 47.060444 | U35: 47.280041 | V35: 47.481697 | W35: 47.659729 | X35: 47.83065 | Y35: 47.980515 | Z35: 48.108444 | AA35: 48.197189 | AB35: 48.262737 | AC35: 48.3549 | AD35: 48.425739 | AE35: 48.504185 | AF35: 48.562855 | AG35: 48.634819 | AH35: 48.674248 | AI35: 0.010373
A36: TKI000:ca_NewCarCred | B36: New Car 3/ | C36: 42.356316 | D36: 43.482601 | E36: 45.545635 | F36: 47.835651 | G36: 49.962463 | H36: 51.477432 | I36: 54.131187 | J36: 54.288181 | K36: 54.274036 | L36: 54.345482 | M36: 54.476521 | N36: 54.755726 | O36: 55.19865 | P36: 55.546597 | Q36: 55.91061 | R36: 56.268238 | S36: 56.616009 | T36: 56.875309 | U36: 57.153564 | V36: 57.42186 | W36: 57.643833 | X36: 57.841148 | Y36: 57.984364 | Z36: 58.118862 | AA36: 58.223202 | AB36: 58.303883 | AC36: 58.397022 | AD36: 58.51268 | AE36: 58.621887 | AF36: 58.738182 | AG36: 58.859608 | AH36: 58.987617 | AI36: 0.010741
A37: TKI000:ca_NewTwukCred | B37: New Light Truck 3/ | C37: 30.865908 | D37: 31.724129 | E37: 32.910633 | F37: 34.543072 | G37: 35.889904 | H37: 37.32349 | I37: 39.26572 | J37: 39.595291 | K37: 39.653728 | L37: 39.666462 | M37: 39.683132 | N37: 39.748066 | O37: 39.797894 | P37: 39.852974 | Q37: 39.920296 | R37: 39.970135 | S37: 40.005047 | T37: 40.02647 | U37: 40.043442 | V37: 40.056137 | W37: 40.064693 | X37: 40.075218 | Y37: 40.075615 | Z37: 40.069695 | AA37: 40.055481 | AB37: 40.038029 | AC37: 40.029408 | AD37: 40.008018 | AE37: 39.996075 | AF37: 39.972542 | AG37: 39.958122 | AH37: 39.929474 | AI37: 0.00834
A38: TKI000:ca_TestedNewVeh | B38: Tested New Light-Duty Vehicle 4/ | C38: 34.962322 | D38: 35.991081 | E38: 37.288235 | F38: 39.051094 | G38: 40.553646 | H38: 41.976017 | I38: 44.120575 | J38: 44.336227 | K38: 44.414066 | L38: 44.500385 | M38: 44.615799 | N38: 44.876507 | O38: 45.111603 | P38: 45.306648 | Q38: 45.531082 | R38: 45.75457 | S38: 45.942371 | T38: 46.09964 | U38: 46.263412 | V38: 46.41185 | W38: 46.541386 | X38: 46.666012 | Y38: 46.777721 | Z38: 46.871037 | AA38: 46.931049 | AB38: 46.971848 | AC38: 47.034363 | AD38: 47.077263 | AE38: 47.126358 | AF38: 47.158012 | AG38: 47.200371 | AH38: 47.214767 | AI38: 0.009739
A39: TKI000:ca_TestedNewCar | B39: New Car 4/ | C39: 41.715885 | D39: 42.872379 | E39: 44.733494 | F39: 46.957069 | G39: 49.003487 | H39: 50.41568 | I39: 52.908669 | J39: 53.035347 | K39: 53.002815 | L39: 53.031281 | M39: 53.101597 | N39: 53.283951 | O39: 53.59354 | P39: 53.82737 | Q39: 54.068119 | R39: 54.300163 | S39: 54.521736 | T39: 54.675041 | U39: 54.843937 | V39: 55.006741 | W39: 55.136219 | X39: 55.248566 | Y39: 55.326115 | Z39: 55.397579 | AA39: 55.445976 | AB39: 55.477283 | AC39: 55.516716 | AD39: 55.571735 | AE39: 55.621513 | AF39: 55.67548 | AG39: 55.732971 | AH39: 55.794552 | AI39: 0.009425
A40: TKI000:ca_TestedNewTwuk | B40: New Light Truck 4/ | C40: 30.612513 | D40: 31.651661 | E40: 32.830524 | F40: 34.456524 | G40: 35.799854 | H40: 37.22747 | I40: 39.151051 | J40: 39.426971 | K40: 39.465645 | L40: 39.475208 | M40: 39.488102 | N40: 39.541683 | O40: 39.581787 | P40: 39.624954 | Q40: 39.679688 | R40: 39.716709 | S40: 39.740402 | T40: 39.750675 | U40: 39.756599 | V40: 39.759041 | W40: 39.758137 | X40: 39.759655 | Y40: 39.75499 | Z40: 39.745636 | AA40: 39.729229 | AB40: 39.710049 | AC40: 39.698334 | AD40: 39.675388 | AE40: 39.66048 | AF40: 39.635681 | AG40: 39.61845 | AH40: 39.589142 | AI40: 0.00833
A41: TKI000:ca_OnRoadNewVeh | B41: On-Road New Light-Duty Vehicle 5/ | C41: 28.524006 | D41: 29.363092 | E41: 30.420794 | F41: 31.858644 | G41: 33.084072 | H41: 34.244457 | I41: 35.994076 | J41: 36.169979 | K41: 36.233746 | L41: 36.304462 | M41: 36.398952 | N41: 36.612297 | O41: 36.804462 | P41: 36.963898 | Q41: 37.147385 | R41: 37.330143 | S41: 37.483685 | T41: 37.612339 | U41: 37.7463 | V41: 37.867699 | W41: 37.973671 | X41: 38.075638 | Y41: 38.16708 | Z41: 38.243473 | AA41: 38.292618 | AB41: 38.326035 | AC41: 38.377235 | AD41: 38.412346 | AE41: 38.45253 | AF41: 38.478436 | AG41: 38.513092 | AH41: 38.524834 | AI41: 0.009742
A42: TKI000:ca_OnRoadNewCar | B42: New Car 5/ | C42: 34.065807 | D42: 35.010216 | E42: 36.530029 | F42: 38.345837 | G42: 40.016972 | H42: 41.170189 | I42: 43.205997 | J42: 43.309448 | K42: 43.282879 | L42: 43.306126 | M42: 43.363548 | N42: 43.512459 | O42: 43.765274 | P42: 43.956223 | Q42: 44.152824 | R42: 44.342316 | S42: 44.523254 | T42: 44.648445 | U42: 44.786369 | V42: 44.919315 | W42: 45.025051 | X42: 45.116795 | Y42: 45.180122 | Z42: 45.23848 | AA42: 45.278004 | AB42: 45.303566 | AC42: 45.33577 | AD42: 45.380699 | AE42: 45.421349 | AF42: 45.46542 | AG42: 45.512367 | AH42: 45.562653 | AI42: 0.009425
A43: TKI000:ca_OnRoadNewTwuk | B43: New Light Truck 5/ | C43: 24.960157 | D43: 25.807436 | E43: 26.768633 | F43: 28.094404 | G43: 29.189699 | H43: 30.353718 | I43: 31.922125 | J43: 32.147099 | K43: 32.178631 | L43: 32.186428 | M43: 32.196941 | N43: 32.240631 | O43: 32.273327 | P43: 32.308525 | Q43: 32.353153 | R43: 32.383339 | S43: 32.402657 | T43: 32.411034 | U43: 32.415863 | V43: 32.417854 | W43: 32.417118 | X43: 32.418354 | Y43: 32.414551 | Z43: 32.406925 | AA43: 32.393547 | AB43: 32.377907 | AC43: 32.368355 | AD43: 32.349648 | AE43: 32.33749 | AF43: 32.317272 | AG43: 32.303223 | AH43: 32.279324 | AI43: 0.00833
... A47: TKI000:ca_FreightTruck | B47: Freight Truck | C47: 7.119165 | D47: 7.17094 | E47: 7.235986 | F47: 7.3073 | G47: 7.388516 | H47: 7.48128 | I47: 7.586367 | J47: 7.703835 | K47: 7.834221 | L47: 7.967885 | M47: 8.108215 | N47: 8.251791 | O47: 8.396469 | P47: 8.537745 | Q47: 8.669586 | R47: 8.791187 | S47: 8.902438 | T47: 9.004374 | U47: 9.096915 | V47: 9.181 | W47: 9.258368 | X47: 9.327685 | Y47: 9.391495 | Z47: 9.448672 | AA47: 9.500283 | AB47: 9.547491 | AC47: 9.591628 | AD47: 9.634123 | AE47: 9.675597 | AF47: 9.716289 | AG47: 9.756433 | AH47: 9.797481 | AI47: 0.010354
B48: (seat miles per gallon)
A49: TKI000:ca_Aircraft | B49: Aircraft | C49: 69.061409 | D49: 69.384445 | E49: 69.706734 | F49: 70.035477 | G49: 70.376755 | H49: 70.734436 | I49: 71.082642 | J49: 71.464615 | K49: 71.895363 | L49: 72.350365 | M49: 72.824806 | N49: 73.293343 | O49: 73.757736 | P49: 74.234024 | Q49: 74.700493 | R49: 75.177055 | S49: 75.653641 | T49: 76.137352 | U49: 76.621902 | V49: 77.107964 | W49: 77.601532 | X49: 78.09996 | Y49: 78.56591 | Z49: 79.031158 | AA49: 79.489037 | AB49: 79.918777 | AC49: 80.345123 | AD49: 80.761703 | AE49: 81.17762 | AF49: 81.591446 | AG49: 81.990547 | AH49: 82.372414 | AI49: 0.005702
B50: (ton miles/thousand Btu)
A51: TKI000:ca_Rail | B51: Rail | C51: 3.466884 | D51: 3.489371 | E51: 3.512003 | F51: 3.534782 | G51: 3.55771 | H51: 3.580785 | I51: 3.60401 | J51: 3.627386 | K51: 3.650914 | L51: 3.674594 | M51: 3.698428 | N51: 3.722416 | O51: 3.74656 | P51: 3.77086 | Q51: 3.795318 | R51: 3.819935 | S51: 3.844712 | T51: 3.869649 | U51: 3.894748 | V51: 3.920009 | W51: 3.945435 | X51: 3.971025 | Y51: 3.996782 | Z51: 4.022705 | AA51: 4.048797 | AB51: 4.075058 | AC51: 4.101489 | AD51: 4.128091 | AE51: 4.154866 | AF51: 4.181815 | AG51: 4.208939 | AH51: 4.236238 | AI51: 0.006486
A52: TKI000:ca_DomesticShipp | B52: Domestic Shipping | C52: 4.813365 | D52: 4.84196 | E52: 4.870726 | F52: 4.899663 | G52: 4.928772 | H52: 4.958054 | I52: 4.987509 | J52: 5.01714 | K52: 5.046947 | L52: 5.076931 | M52: 5.107092 | N52: 5.137434 | O52: 5.167955 | P52: 5.198658 | Q52: 5.229543 | R52: 5.260611 | S52: 5.291864 | T52: 5.323303 | U52: 5.354929 | V52: 5.386742 | W52: 5.418745 | X52: 5.450938 | Y52: 5.483322 | Z52: 5.515898 | AA52: 5.548667 | AB52: 5.581632 | AC52: 5.614792 | AD52: 5.64815 | AE52: 5.681705 | AF52: 5.71546 | AG52: 5.749416 | AH52: 5.783573 | AI52: 0.005941
B54: Energy Use by Mode
B55: (quadrillion Btu)
A56: TKI000:da_Light-DutyVeh | B56: Light-Duty Vehicles | C56: 15.312445 | D56: 15.30714 | E56: 15.236718 | F56: 15.068806 | G56: 14.804813 | H56: 14.499307 | I56: 14.167157 | J56: 13.909196 | K56: 13.685458 | L56: 13.482776 | M56: 13.299863 | N56: 13.139069 | O56: 13.002687 | P56: 12.863337 | Q56: 12.735183 | R56: 12.602709 | S56: 12.470579 | T56: 12.372916 | U56: 12.287333 | V56: 12.215109 | W56: 12.15875 | X56: 12.118073 | Y56: 12.081137 | Z56: 12.057517 | AA56: 12.045367 | AB56: 12.044356 | AC56: 12.055041 | AD56: 12.085419 | AE56: 12.129275 | AF56: 12.190246 | AG56: 12.262823 | AH56: 12.346762 | AI56: -0.00692
A57: TKI000:da_CommercialLig | B57: Commercial Light Trucks 1/ | C57: 0.891028 | D57: 0.891903 | E57: 0.895889 | F57: 0.89787 | G57: 0.89709 | H57: 0.89318 | I57: 0.892636 | J57: 0.892015 | K57: 0.892606 | L57: 0.893648 | M57: 0.895486 | N57: 0.896713 | O57: 0.901317 | P57: 0.904846 | Q57: 0.909857 | R57: 0.914968 | S57: 0.920246 | T57: 0.927079 | U57: 0.934283 | V57: 0.94158 | W57: 0.949261 | X57: 0.957789 | Y57: 0.966845 | Z57: 0.975906 | AA57: 0.98611 | AB57: 0.997791 | AC57: 1.010687 | AD57: 1.027074 | AE57: 1.040264 | AF57: 1.054572 | AG57: 1.069246 | AH57: 1.083799 | AI57: 0.006338
A58: TKI000:da_BusTransporta | B58: Bus Transportation | C58: 0.238531 | D58: 0.23989 | E58: 0.241259 | F58: 0.242609 | G58: 0.243913 | H58: 0.245252 | I58: 0.246684 | J58: 0.248104 | K58: 0.249516 | L58: 0.250953 | M58: 0.252383 | N58: 0.253717 | O58: 0.25501 | P58: 0.256269 | Q58: 0.257406 | R58: 0.258486 | S58: 0.259508 | T58: 0.26047 | U58: 0.261377 | V58: 0.262223 | W58: 0.263003 | X58: 0.263714 | Y58: 0.264353 | Z58: 0.264925 | AA58: 0.265439 | AB58: 0.265904 | AC58: 0.266333 | AD58: 0.266748 | AE58: 0.267177 | AF58: 0.267648 | AG58: 0.268208 | AH58: 0.268877 | AI58: 0.00387
A59: TKI000:da_FreightTrucks | B59: Freight Trucks | C59: 5.880958 | D59: 5.904005 | E59: 5.951757 | F59: 5.983958 | G59: 6.010647 | H59: 5.993482 | I59: 5.972905 | J59: 5.942755 | K59: 5.913831 | L59: 5.875737 | M59: 5.836956 | N59: 5.783237 | O59: 5.760028 | P59: 5.727354 | Q59: 5.709549 | R59: 5.688765 | S59: 5.682989 | T59: 5.688041 | U59: 5.689445 | V59: 5.697817 | W59: 5.709255 | X59: 5.729411 | Y59: 5.754163 | Z59: 5.786846 | AA59: 5.821076 | AB59: 5.869198 | AC59: 5.927293 | AD59: 6.001935 | AE59: 6.05612 | AF59: 6.125846 | AG59: 6.200032 | AH59: 6.275017 | AI59: 0.002094
A60: TKI000:da_Rail,Passenge | B60: Rail, Passenger | C60: 0.049125 | D60: 0.050002 | E60: 0.050829 | F60: 0.051513 | G60: 0.052173 | H60: 0.05283 | I60: 0.053461 | J60: 0.054088 | K60: 0.054688 | L60: 0.055315 | M60: 0.05594 | N60: 0.056411 | O60: 0.057057 | P60: 0.057683 | Q60: 0.058288 | R60: 0.058841 | S60: 0.059417 | T60: 0.059977 | U60: 0.060532 | V60: 0.061099 | W60: 0.061667 | X60: 0.062234 | Y60: 0.062772 | Z60: 0.063311 | AA60: 0.063864 | AB60: 0.064422 | AC60: 0.064971 | AD60: 0.065568 | AE60: 0.066151 | AF60: 0.066765 | AG60: 0.067348 | AH60: 0.067945 | AI60: 0.010517
A61: TKI000:da_Rail,Freight | B61: Rail, Freight | C61: 0.521495 | D61: 0.496032 | E61: 0.472674 | F61: 0.467146 | G61: 0.464547 | H61: 0.457573 | I61: 0.445275 | J61: 0.453219 | K61: 0.452705 | L61: 0.452497 | M61: 0.447651 | N61: 0.442804 | O61: 0.441685 | P61: 0.441239 | Q61: 0.441049 | R61: 0.440976 | S61: 0.438735 | T61: 0.43887 | U61: 0.43769 | V61: 0.433993 | W61: 0.433911 | X61: 0.431911 | Y61: 0.430911 | Z61: 0.431362 | AA61: 0.431558 | AB61: 0.432132 | AC61: 0.433326 | AD61: 0.436538 | AE61: 0.437579 | AF61: 0.439821 | AG61: 0.442391 | AH61: 0.445806 | AI61: -0.005046
A62: TKI000:da_Shipping,Dome | B62: Shipping, Domestic | C62: 0.089409 | D62: 0.087947 | E62: 0.085825 | F62: 0.083144 | G62: 0.081043 | H62: 0.07854 | I62: 0.076103 | J62: 0.073851 | K62: 0.071606 | L62: 0.069278 | M62: 0.066865 | N62: 0.064421 | O62: 0.063281 | P62: 0.062044 | Q62: 0.060933 | R62: 0.059681 | S62: 0.058471 | T62: 0.057385 | U62: 0.056209 | V62: 0.055025 | W62: 0.053933 | X62: 0.052831 | Y62: 0.052283 | Z62: 0.051792 | AA62: 0.051248 | AB62: 0.050799 | AC62: 0.050387 | AD62: 0.050149 | AE62: 0.049715 | AF62: 0.049415 | AG62: 0.049187 | AH62: 0.048997 | AI62: -0.019215
A63: TKI000:da_Shipping,Inte | B63: Shipping, International | C63: 0.927327 | D63: 1.008838 | E63: 0.971116 | F63: 0.886972 | G63: 0.891949 | H63: 0.875923 | I63: 0.889297 | J63: 0.864365 | K63: 0.875667 | L63: 0.876735 | M63: 0.862752 | N63: 0.876611 | O63: 0.877461 | P63: 0.865944 | Q63: 0.876064 | R63: 0.876109 | S63: 0.872912 | T63: 0.862727 | U63: 0.869371 | V63: 0.858956 | W63: 0.858436 | X63: 0.864699 | Y63: 0.853751 | Z63: 0.852309 | AA63: 0.849807 | AB63: 0.846604 | AC63: 0.844515 | AD63: 0.843746 | AE63: 0.841557 | AF63: 0.840549 | AG63: 0.839989 | AH63: 0.840091 | AI63: -0.003182
A64: TKI000:da_RecreationalB | B64: Recreational Boats | C64: 0.245487 | D64: 0.246247 | E64: 0.246891 | F64: 0.247228 | G64: 0.247401 | H64: 0.247561 | I64: 0.247747 | J64: 0.247872 | K64: 0.247948 | L64: 0.248034 | M64: 0.248119 | N64: 0.248128 | O64: 0.248119 | P64: 0.248079 | Q64: 0.247943 | R64: 0.247704 | S64: 0.247382 | T64: 0.247051 | U64: 0.246672 | V64: 0.246271 | W64: 0.245845 | X64: 0.245364 | Y64: 0.244837 | Z64: 0.244243 | AA64: 0.243636 | AB64: 0.243037 | AC64: 0.242467 | AD64: 0.241926 | AE64: 0.241387 | AF64: 0.240858 | AG64: 0.240316 | AH64: 0.23976 | AI64: -0.000761
A65: TKI000:da_Air | B65: Air | C65: 2.640944 | D65: 2.673067 | E65: 2.70635 | F65: 2.732191 | G65: 2.752433 | H65: 2.776094 | I65: 2.803131 | J65: 2.82868 | K65: 2.853517 | L65: 2.879811 | M65: 2.908522 | N65: 2.937199 | O65: 2.967398 | P65: 2.997719 | Q65: 3.0276 | R65: 3.053208 | S65: 3.077652 | T65: 3.104426 | U65: 3.132126 | V65: 3.160325 | W65: 3.189834 | X65: 3.220148 | Y65: 3.250173 | Z65: 3.279953 | AA65: 3.310731 | AB65: 3.34457 | AC65: 3.383125 | AD65: 3.426044 | AE65: 3.471181 | AF65: 3.520372 | AG65: 3.571743 | AH65: 3.624813 | AI65: 0.010267
A66: TKI000:da_MilitaryUse | B66: Military Use | C66: 0.512501 | D66: 0.526369 | E66: 0.515977 | F66: 0.504054 | G66: 0.488973 | H66: 0.47893 | I66: 0.47706 | J66: 0.475186 | K66: 0.474613 | L66: 0.477166 | M66: 0.476099 | N66: 0.47539 | O66: 0.475478 | P66: 0.475588 | Q66: 0.475726 | R66: 0.475885 | S66: 0.476065 | T66: 0.476268 | U66: 0.476499 | V66: 0.476747 | W66: 0.477015 | X66: 0.477302 | Y66: 0.4776 | Z66: 0.477913 | AA66: 0.478237 | AB66: 0.478571 | AC66: 0.478915 | AD66: 0.479268 | AE66: 0.479627 | AF66: 0.479993 | AG66: 0.480364 | AH66: 0.480741 | AI66: -0.002062
A67: TKI000:da_Lubricants | B67: Lubricants | C67: 0.131469 | D67: 0.130998 | E67: 0.130617 | F67: 0.130166 | G67: 0.129716 | H67: 0.129236 | I67: 0.128717 | J67: 0.12821 | K67: 0.127738 | L67: 0.127329 | M67: 0.126997 | N67: 0.126676 | O67: 0.126395 | P67: 0.126142 | Q67: 0.125896 | R67: 0.125704 | S67: 0.12555 | T67: 0.12549 | U67: 0.125464 | V67: 0.125469 | W67: 0.125512 | X67: 0.125529 | Y67: 0.125533 | Z67: 0.125612 | AA67: 0.125667 | AB67: 0.125765 | AC67: 0.12594 | AD67: 0.126144 | AE67: 0.126361 | AF67: 0.126627 | AG67: 0.126863 | AH67: 0.127078 | AI67: -0.001095
... A69: TKI000:da_Total | B69: Total | C69: 28.112638 | D69: 28.229656 | E69: 28.207281 | F69: 28.00946 | G69: 27.785589 | H69: 27.463036 | I69: 27.152018 | J69: 26.878296 | K69: 26.655809 | L69: 26.445753 | M69: 26.240934 | N69: 26.065762 | O69: 25.948496 | P69: 25.80217 | Q69: 25.701551 | R69: 25.580608 | S69: 25.470058 | T69: 25.412188 | U69: 25.37376 | V69: 25.339329 | W69: 25.342278 | X69: 25.372105 | Y69: 25.393759 | Z69: 25.455908 | AA69: 25.525803 | AB69: 25.624594 | AC69: 25.752531 | AD69: 25.930012 | AE69: 26.094328 | AF69: 26.300638 | AG69: 26.523647 | AH69: 26.762129 | AI69: -0.001587
B71: (million barrels per day oil equivalent)
A72: TKI000:ea_Light-DutyVeh | B72: Light-Duty Vehicles | C72: 8.299458 | D72: 8.297431 | E72: 8.258867 | F72: 8.167576 | G72: 8.024354 | H72: 7.858614 | I72: 7.680162 | J72: 7.54128 | K72: 7.420378 | L72: 7.311098 | M72: 7.21259 | N72: 7.126847 | O72: 7.05311 | P72: 6.977902 | Q72: 6.908753 | R72: 6.837132 | S72: 6.765776 | T72: 6.712733 | U72: 6.666179 | V72: 6.626825 | W72: 6.595639 | X72: 6.572973 | Y72: 6.552473 | Z72: 6.538953 | AA72: 6.532093 | AB72: 6.531311 | AC72: 6.536314 | AD72: 6.552357 | AE72: 6.575637 | AF72: 6.60852 | AG72: 6.647728 | AH72: 6.693235 | AI72: -0.006914
A73: TKI000:ea_CommercialLig | B73: Commercial Light Trucks 1/ | C73: 0.463645 | D73: 0.463938 | E73: 0.465786 | F73: 0.466659 | G73: 0.466108 | H73: 0.464014 | I73: 0.463842 | J73: 0.463561 | K73: 0.463877 | L73: 0.46449 | M73: 0.465553 | N73: 0.466452 | O73: 0.468995 | P73: 0.470979 | Q73: 0.473754 | R73: 0.476574 | S73: 0.479564 | T73: 0.483356 | U73: 0.487438 | V73: 0.491518 | W73: 0.495649 | X73: 0.500162 | Y73: 0.505092 | Z73: 0.509883 | AA73: 0.515413 | AB73: 0.521692 | AC73: 0.528346 | AD73: 0.53696 | AE73: 0.543866 | AF73: 0.551526 | AG73: 0.559404 | AH73: 0.567315 | AI73: 0.006531
A74: TKI000:ea_BusTransporta | B74: Bus Transportation | C74: 0.115227 | D74: 0.115901 | E74: 0.116581 | F74: 0.117251 | G74: 0.117882 | H74: 0.118551 | I74: 0.11926 | J74: 0.11995 | K74: 0.120641 | L74: 0.12134 | M74: 0.122028 | N74: 0.122645 | O74: 0.12329 | P74: 0.123892 | Q74: 0.124421 | R74: 0.124924 | S74: 0.125429 | T74: 0.125889 | U74: 0.126375 | V74: 0.126791 | W74: 0.127173 | X74: 0.127473 | Y74: 0.127798 | Z74: 0.128063 | AA74: 0.128311 | AB74: 0.128539 | AC74: 0.128753 | AD74: 0.128956 | AE74: 0.12916 | AF74: 0.129386 | AG74: 0.129657 | AH74: 0.129983 | AI74: 0.003895
A75: TKI000:ea_FreightTrucks | B75: Freight Trucks | C75: 2.827296 | D75: 2.838177 | E75: 2.861533 | F75: 2.877479 | G75: 2.89041 | H75: 2.883003 | I75: 2.873901 | J75: 2.859937 | K75: 2.846777 | L75: 2.829164 | M75: 2.811116 | N75: 2.785219 | O75: 2.775341 | P75: 2.760258 | Q75: 2.752032 | R75: 2.742399 | S75: 2.740685 | T75: 2.743816 | U75: 2.746544 | V75: 2.751515 | W75: 2.757982 | X75: 2.767448 | Y75: 2.780638 | Z75: 2.797015 | AA75: 2.814377 | AB75: 2.838605 | AC75: 2.867797 | AD75: 2.904866 | AE75: 2.931931 | AF75: 2.966593 | AG75: 3.003496 | AH75: 3.040895 | AI75: 0.002352
A76: TKI000:ea_Rail,Passenge | B76: Rail, Passenger | C76: 0.023255 | D76: 0.023671 | E76: 0.024065 | F76: 0.02439 | G76: 0.024703 | H76: 0.025016 | I76: 0.025317 | J76: 0.025614 | K76: 0.025899 | L76: 0.026196 | M76: 0.026491 | N76: 0.026709 | O76: 0.027018 | P76: 0.027313 | Q76: 0.027597 | R76: 0.027856 | S76: 0.02813 | T76: 0.028393 | U76: 0.028663 | V76: 0.028932 | W76: 0.029202 | X76: 0.029463 | Y76: 0.02972 | Z76: 0.029973 | AA76: 0.030235 | AB76: 0.030499 | AC76: 0.030761 | AD76: 0.031043 | AE76: 0.031319 | AF76: 0.031609 | AG76: 0.031885 | AH76: 0.032168 | AI76: 0.010521
A77: TKI000:ea_Rail,Freight | B77: Rail, Freight | C77: 0.247425 | D77: 0.235349 | E77: 0.224294 | F77: 0.221703 | G77: 0.220458 | H77: 0.217186 | I77: 0.211368 | J77: 0.215123 | K77: 0.214871 | L77: 0.214751 | M77: 0.212415 | N77: 0.21003 | O77: 0.209515 | P77: 0.209267 | Q77: 0.209119 | R77: 0.209029 | S77: 0.207961 | T77: 0.207993 | U77: 0.207494 | V77: 0.205728 | W77: 0.205676 | X77: 0.20464 | Y77: 0.204172 | Z77: 0.204352 | AA77: 0.204426 | AB77: 0.204688 | AC77: 0.205248 | AD77: 0.206758 | AE77: 0.207232 | AF77: 0.208277 | AG77: 0.209481 | AH77: 0.211086 | AI77: -0.005111
A78: TKI000:ea_Shipping,Dome | B78: Shipping, Domestic | C78: 0.042333 | D78: 0.041603 | E78: 0.040635 | F78: 0.0394 | G78: 0.038405 | H78: 0.037229 | I78: 0.03608 | J78: 0.035014 | K78: 0.033953 | L78: 0.032851 | M78: 0.031707 | N78: 0.030539 | O78: 0.030006 | P78: 0.029419 | Q78: 0.028888 | R78: 0.02829 | S78: 0.02772 | T78: 0.027204 | U78: 0.02666 | V78: 0.026101 | W78: 0.025585 | X78: 0.025052 | Y78: 0.024795 | Z78: 0.024559 | AA78: 0.0243 | AB78: 0.024088 | AC78: 0.023893 | AD78: 0.023781 | AE78: 0.023574 | AF78: 0.02343 | AG78: 0.023322 | AH78: 0.023231 | AI78: -0.019171
A79: TKI000:ea_Shipping,Inte | B79: Shipping, International | C79: 0.419044 | D79: 0.459324 | E79: 0.440255 | F79: 0.398147 | G79: 0.4 | H79: 0.394394 | I79: 0.399222 | J79: 0.390425 | K79: 0.394511 | L79: 0.39495 | M79: 0.390033 | N79: 0.394978 | O79: 0.395364 | P79: 0.391307 | Q79: 0.394931 | R79: 0.394969 | S79: 0.393888 | T79: 0.390292 | U79: 0.392778 | V79: 0.389117 | W79: 0.38898 | X79: 0.391189 | Y79: 0.387353 | Z79: 0.386861 | AA79: 0.386008 | AB79: 0.384915 | AC79: 0.384226 | AD79: 0.384005 | AE79: 0.383269 | AF79: 0.382965 | AG79: 0.382823 | AH79: 0.382909 | AI79: -0.002905
A80: TKI000:ea_RecreationalB | B80: Recreational Boats | C80: 0.13308 | D80: 0.1335 | E80: 0.133858 | F80: 0.134049 | G80: 0.134152 | H80: 0.134247 | I80: 0.134378 | J80: 0.134477 | K80: 0.134548 | L80: 0.134625 | M80: 0.134701 | N80: 0.134737 | O80: 0.134762 | P80: 0.134771 | Q80: 0.134727 | R80: 0.134629 | S80: 0.134484 | T80: 0.134326 | U80: 0.134143 | V80: 0.133947 | W80: 0.133738 | X80: 0.133498 | Y80: 0.13323 | Z80: 0.132925 | AA80: 0.132613 | AB80: 0.132305 | AC80: 0.132013 | AD80: 0.131737 | AE80: 0.131461 | AF80: 0.131191 | AG80: 0.130914 | AH80: 0.130629 | AI80: -0.0006
A81: TKI000:ea_Air | B81: Air | C81: 1.277419 | D81: 1.292941 | E81: 1.309023 | F81: 1.321509 | G81: 1.33129 | H81: 1.342723 | I81: 1.35579 | J81: 1.368137 | K81: 1.380141 | L81: 1.392848 | M81: 1.406724 | N81: 1.420583 | O81: 1.435178 | P81: 1.449832 | Q81: 1.464272 | R81: 1.476649 | S81: 1.488463 | T81: 1.501402 | U81: 1.514789 | V81: 1.528416 | W81: 1.542677 | X81: 1.557327 | Y81: 1.571836 | Z81: 1.586228 | AA81: 1.601101 | AB81: 1.617454 | AC81: 1.636085 | AD81: 1.656825 | AE81: 1.678637 | AF81: 1.702407 | AG81: 1.727231 | AH81: 1.752876 | AI81: 0.010259
A82: TKI000:ea_MilitaryUse | B82: Military Use | C82: 0.245757 | D82: 0.251956 | E82: 0.247274 | F82: 0.241855 | G82: 0.234618 | H82: 0.229808 | I82: 0.228918 | J82: 0.228018 | K82: 0.227745 | L82: 0.22897 | M82: 0.228454 | N82: 0.228098 | O82: 0.228149 | P82: 0.228197 | Q82: 0.228253 | R82: 0.228318 | S82: 0.228408 | T82: 0.228501 | U82: 0.228635 | V82: 0.228755 | W82: 0.228885 | X82: 0.228999 | Y82: 0.229148 | Z82: 0.229291 | AA82: 0.229445 | AB82: 0.229607 | AC82: 0.229775 | AD82: 0.229945 | AE82: 0.230114 | AF82: 0.230288 | AG82: 0.230466 | AH82: 0.230647 | AI82: -0.002045
A83: TKI000:ea_Lubricants | B83: Lubricants | C83: 0.062101 | D83: 0.061879 | E83: 0.061699 | F83: 0.061486 | G83: 0.061273 | H83: 0.061047 | I83: 0.060801 | J83: 0.060562 | K83: 0.060339 | L83: 0.060146 | M83: 0.059989 | N83: 0.059838 | O83: 0.059705 | P83: 0.059585 | Q83: 0.059469 | R83: 0.059378 | S83: 0.059306 | T83: 0.059277 | U83: 0.059265 | V83: 0.059268 | W83: 0.059288 | X83: 0.059296 | Y83: 0.059298 | Z83: 0.059335 | AA83: 0.059361 | AB83: 0.059407 | AC83: 0.05949 | AD83: 0.059586 | AE83: 0.059688 | AF83: 0.059814 | AG83: 0.059926 | AH83: 0.060027 | AI83: -0.001095
... A85: TKI000:ea_Total | B85: Total | C85: 14.473433 | D85: 14.53084 | E85: 14.515177 | F85: 14.408682 | G85: 14.284176 | H85: 14.113085 | I85: 13.944188 | J85: 13.801455 | K85: 13.680749 | L85: 13.568763 | M85: 13.462358 | N85: 13.368217 | O85: 13.305375 | P85: 13.229243 | Q85: 13.172801 | R85: 13.107446 | S85: 13.048519 | T85: 13.017055 | U85: 12.995325 | V85: 12.977034 | W85: 12.975856 | X85: 12.986323 | Y85: 12.997333 | Z85: 13.026218 | AA85: 13.060641 | AB85: 13.110025 | AC85: 13.173438 | AD85: 13.26224 | AE85: 13.34532 | AF85: 13.450161 | AG85: 13.563889 | AH85: 13.686009 | AI85: -0.001803
B87: 1/ Commercial trucks 8,501 to 10,000 pounds gross vehicle weight rating.
B88: 2/ CAFE standard based on projected new vehicle sales.
B89: 3/ Includes CAFE credits for alternative fueled vehicle sales and credit banking.
B90: 4/ Environmental Protection Agency rated miles per gallon.
B91: 5/ Tested new vehicle efficiency revised for on-road performance.
B92: 6/ Combined "on-the-road" estimate for all cars and light trucks.
B93: CAFE = Corporate average fuel economy.
B94: Btu = British thermal unit.
B95: Note: Totals may not equal sum of components due to independent rounding.
B96: Sources: 2019: U.S. Energy Information Administration (EIA), Short-Term Energy Outlook, October 2019 and EIA, AEO2020 National
B97: Energy Modeling System run highogs.d112619a. Projections: EIA, AEO2020 National Energy Modeling System run highogs.d112619a.

Sheet AEO 35
E1: 2019 | F1: 2020 | G1: 2021 | H1: 2022 | I1: 2023 | J1: 2024 | K1: 2025 | L1: 2026 | M1: 2027 | N1: 2028 | O1: 2029 | P1: 2030 | Q1: 2031 | R1: 2032 | S1: 2033 | T1: 2034 | U1: 2035 | V1: 2036 | W1: 2037 | X1: 2038 | Y1: 2039 | Z1: 2040 | AA1: 2041 | AB1: 2042 | AC1: 2043 | AD1: 2044 | AE1: 2045 | AF1: 2046 | AG1: 2047 | AH1: 2048 | AI1: 2049 | AJ1: 2050 | AK1: Growth (2019-2050)
A10: Table 35. Transportation Sector Energy Use by Mode and Type
A11: https://www.eia.gov/outlooks/aeo/data/browser/#/?id=45-AEO2020&cases=highogs&sourcekey=0
A12: Tue Mar 09 2021 09:44:26 GMT-0800 (Pacific Standard Time)
A13: Source: U.S. Energy Information Administration
B14: full name | C14: api key | D14: units | E14: 2019 | F14: 2020 | G14: 2021 | H14: 2022 | I14: 2023 | J14: 2024 | K14: 2025 | L14: 2026 | M14: 2027 | N14: 2028 | O14: 2029 | P14: 2030 | Q14: 2031 | R14: 2032 | S14: 2033 | T14: 2034 | U14: 2035 | V14: 2036 | W14: 2037 | X14: 2038 | Y14: 2039 | Z14: 2040 | AA14: 2041 | AB14: 2042 | AC14: 2043 | AD14: 2044 | AE14: 2045 | AF14: 2046 | AG14: 2047 | AH14: 2048 | AI14: 2049 | AJ14: 2050 | AK14: Growth (2019-2050)
A15: Energy Use by Mode | C15: 45-AEO2020.2.
A16: Highway | C16: 45-AEO2020.3.
A17: Light-Duty Vehicles | B17: Transportation Energy Use: Highway: Light-Duty Vehicles: High oil and gas supply | C17: 45-AEO2020.4.highogs-d112619a | D17: trillion Btu | E17: 15312.443 | F17: 15307.141 | G17: 15236.72 | H17: 15068.805 | I17: 14804.814 | J17: 14499.308 | K17: 14167.156 | L17: 13909.197 | M17: 13685.46 | N17: 13482.776 | O17: 13299.865 | P17: 13139.07 | Q17: 13002.688 | R17: 12863.338 | S17: 12735.186 | T17: 12602.711 | U17: 12470.581 | V17: 12372.919 | W17: 12287.335 | X17: 12215.112 | Y17: 12158.751 | Z17: 12118.077 | AA17: 12081.139 | AB17: 12057.521 | AC17: 12045.37 | AD17: 12044.358 | AE17: 12055.047 | AF17: 12085.423 | AG17: 12129.279 | AH17: 12190.25 | AI17: 12262.828 | AJ17: 12346.766 | AK17: -0.007
A18: Automobiles | B18: Transportation Energy Use: Highway: Light-Duty Vehicles: Automobiles: High oil and gas supply | C18: 45-AEO2020.5.highogs-d112619a | D18: trillion Btu | E18: 6604.9644 | F18: 6553.7881 | G18: 6462.5918 | H18: 6325.7974 | I18: 6141.5596 | J18: 5945.4087 | K18: 5745.1323 | L18: 5578.6621 | M18: 5431.4175 | N18: 5297.522 | O18: 5177.7271 | P18: 5078.146 | Q18: 4995.5908 | R18: 4919.3291 | S18: 4856.0435 | T18: 4801.0728 | U18: 4754.9814 | V18: 4730.7998 | W18: 4719.7905 | X18: 4721.6392 | Y18: 4736.0396 | Z18: 4762.6094 | AA18: 4794.8496 | AB18: 4835.4375 | AC18: 4882.0771 | AD18: 4933.0811 | AE18: 4988.8521 | AF18: 5051.8193 | AG18: 5119.1323 | AH18: 5191.9043 | AI18: 5267.8442 | AJ18: 5345.6309 | AK18: -0.007
A19: Light Trucks | B19: Transportation Energy Use: Highway: Light-Duty Vehicles: Light Trucks: High oil and gas supply | C19: 45-AEO2020.6.highogs-d112619a | D19: trillion Btu | E19: 8688.5088 | F19: 8734.5293 | G19: 8755.5664 | H19: 8724.8398 | I19: 8645.6162 | J19: 8536.8242 | K19: 8405.5244 | L19: 8314.5137 | M19: 8238.4434 | N19: 8170.0405 | O19: 8107.2686 | P19: 8046.3413 | Q19: 7992.7515 | R19: 7929.8823 | S19: 7865.1968 | T19: 7787.8506 | U19: 7701.9443 | V19: 7628.5342 | W19: 7553.9902 | X19: 7479.9131 | Y19: 7409.1113 | Z19: 7341.791 | AA19: 7272.52 | AB19: 7208.1963 | AC19: 7149.2725 | AD19: 7097.1104 | AE19: 7051.8662 | AF19: 7019.0952 | AG19: 6995.4448 | AH19: 6983.4336 | AI19: 6979.854 | AJ19: 6985.7817 | AK19: -0.007
A20: Motorcycles | B20: Transportation Energy Use: Highway: Light-Duty Vehicles: Motorcycles: High oil and gas supply | C20: 45-AEO2020.7.highogs-d112619a | D20: trillion Btu | E20: 18.970795 | F20: 18.823608 | G20: 18.561443 | H20: 18.168322 | I20: 17.63892 | J20: 17.075298 | K20: 16.499819 | L20: 16.021494 | M20: 15.598401 | N20: 15.213686 | O20: 14.869466 | P20: 14.583327 | Q20: 14.346129 | R20: 14.126972 | S20: 13.94516 | T20: 13.787245 | U20: 13.654823 | V20: 13.585337 | W20: 13.553765 | X20: 13.55909 | Y20: 13.600537 | Z20: 13.677015 | AA20: 13.769792 | AB20: 13.886584 | AC20: 14.020749 | AD20: 14.167451 | AE20: 14.327848 | AF20: 14.508926 | AG20: 14.702455 | AH20: 14.911672 | AI20: 15.129991 | AJ20: 15.353589 | AK20: -0.007
A21: Commercial Light Trucks | B21: Transportation Energy Use: Highway: Commercial Light Trucks: High oil and gas supply | C21: 45-AEO2020.8.highogs-d112619a | D21: trillion Btu | E21: 891.02838 | F21: 891.90326 | G21: 895.8894 | H21: 897.86987 | I21: 897.09033 | J21: 893.17987 | K21: 892.63629 | L21: 892.01526 | M21: 892.60571 | N21: 893.64764 | O21: 895.48633 | P21: 896.71252 | Q21: 901.31744 | R21: 904.84607 | S21: 909.85718 | T21: 914.96765 | U21: 920.24628 | V21: 927.07892 | W21: 934.28284 | X21: 941.58032 | Y21: 949.26141 | Z21: 957.78931 | AA21: 966.8446 | AB21: 975.90601 | AC21: 986.1098 | AD21: 997.79096 | AE21: 1010.6874 | AF21: 1027.0737 | AG21: 1040.2635 | AH21: 1054.5718 | AI21: 1069.2462 | AJ21: 1083.7993 | AK21: 0.006
A22: Buses | B22: Transportation Energy Use: Highway: Buses: High oil and gas supply | C22: 45-AEO2020.9.highogs-d112619a | D22: trillion Btu | E22: 238.53146 | F22: 239.89018 | G22: 241.25854 | H22: 242.60852 | I22: 243.91312 | J22: 245.2515 | K22: 246.68358 | L22: 248.10384 | M22: 249.51576 | N22: 250.95306 | O22: 252.38295 | P22: 253.71747 | Q22: 255.00951 | R22: 256.26871 | S22: 257.40616 | T22: 258.48618 | U22: 259.50766 | V22: 260.47018 | W22: 261.37662 | X22: 262.22324 | Y22: 263.00284 | Z22: 263.71384 | AA22: 264.35327 | AB22: 264.92453 | AC22: 265.43933 | AD22: 265.90439 | AE22: 266.33295 | AF22: 266.74771 | AG22: 267.1767 | AH22: 267.64749 | AI22: 268.20847 | AJ22: 268.87695 | AK22: 0.004
A23: Transit | B23: Transportation Energy Use: Highway: Buses: Transit: High oil and gas supply | C23: 45-AEO2020.10.highogs-d112619a | D23: trillion Btu | E23: 99.315071 | F23: 99.945122 | G23: 100.56989 | H23: 101.19645 | I23: 101.8311 | J23: 102.44681 | K23: 103.00167 | L23: 103.5542 | M23: 104.09944 | N23: 104.62385 | O23: 105.14225 | P23: 105.59572 | Q23: 106.02787 | R23: 106.43801 | S23: 106.85069 | T23: 107.24017 | U23: 107.60039 | V23: 107.92464 | W23: 108.20892 | X23: 108.4436 | Y23: 108.61575 | Z23: 108.71909 | AA23: 108.74683 | AB23: 108.69933 | AC23: 108.58459 | AD23: 108.40518 | AE23: 108.17055 | AF23: 107.90131 | AG23: 107.62363 | AH23: 107.36424 | AI23: 107.17227 | AJ23: 107.07778 | AK23: 0.002
A24: Intercity | B24: Transportation Energy Use: Highway: Buses: Intercity: High oil and gas supply | C24: 45-AEO2020.11.highogs-d112619a | D24: trillion Btu | E24: 34.017525 | F24: 34.295715 | G24: 34.571033 | H24: 34.845947 | I24: 35.122425 | J24: 35.390961 | K24: 35.642731 | L24: 35.891884 | M24: 36.136688 | N24: 36.372597 | O24: 36.604843 | P24: 36.834064 | Q24: 37.057114 | R24: 37.274578 | S24: 37.495804 | T24: 37.713417 | U24: 37.927135 | V24: 38.136677 | W24: 38.341736 | X24: 38.542122 | Y24: 38.737698 | Z24: 38.928463 | AA24: 39.114555 | AB24: 39.296169 | AC24: 39.473579 | AD24: 39.647072 | AE24: 39.817013 | AF24: 39.983807 | AG24: 40.147793 | AH24: 40.309471 | AI24: 40.469448 | AJ24: 40.627487 | AK24: 0.006
A25: School | B25: Transportation Energy Use: Highway: Buses: School: High oil and gas supply | C25: 45-AEO2020.12.highogs-d112619a | D25: trillion Btu | E25: 105.19891 | F25: 105.64934 | G25: 106.1176 | H25: 106.56614 | I25: 106.9596 | J25: 107.41371 | K25: 108.03915 | L25: 108.65778 | M25: 109.27963 | N25: 109.95661 | O25: 110.63587 | P25: 111.28769 | Q25: 111.9245 | R25: 112.55617 | S25: 113.05969 | T25: 113.53259 | U25: 113.98013 | V25: 114.40887 | W25: 114.82594 | X25: 115.2375 | Y25: 115.64941 | Z25: 116.06626 | AA25: 116.49187 | AB25: 116.92904 | AC25: 117.38118 | AD25: 117.85213 | AE25: 118.34538 | AF25: 118.86262 | AG25: 119.40527 | AH25: 119.97376 | AI25: 120.56672 | AJ25: 121.17171 | AK25: 0.005
A26: Freight Trucks | B26: Transportation Energy Use: Highway: Freight Trucks: High oil and gas supply | C26: 45-AEO2020.13.highogs-d112619a | D26: trillion Btu | E26: 5881.6938 | F26: 5905.2188 | G26: 5953.2412 | H26: 5985.7578 | I26: 6012.811 | J26: 5996.0127 | K26: 5975.9307 | L26: 5946.1875 | M26: 5917.5103 | N26: 5879.7197 | O26: 5841.2886 | P26: 5788.1685 | Q26: 5765.2397 | R26: 5732.8828 | S26: 5715.4565 | T26: 5694.999 | U26: 5689.6113 | V26: 5695.0806 | W26: 5696.8452 | X26: 5705.6021 | Y26: 5717.1274 | Z26: 5737.4014 | AA26: 5762.4326 | AB26: 5795.2007 | AC26: 5829.8892 | AD26: 5878.4766 | AE26: 5936.4565 | AF26: 6011.3896 | AG26: 6065.6465 | AH26: 6135.8477 | AI26: 6210.5356 | AJ26: 6286.1934 | AK26: 0.002
A27: Light Medium | B27: Transportation Energy Use: Highway: Freight Trucks: Light Medium: High oil and gas supply | C27: 45-AEO2020.14.highogs-d112619a | D27: trillion Btu | E27: 653.09912 | F27: 654.05658 | G27: 664.6781 | H27: 669.36182 | I27: 674.8158 | J27: 677.23505 | K27: 680.64838 | L27: 683.49329 | M27: 687.08698 | N27: 690.2002 | O27: 693.99316 | P27: 697.10449 | Q27: 704.64301 | R27: 711.11914 | S27: 719.18726 | T27: 726.89185 | U27: 736.56897 | V27: 746.99585 | W27: 755.67902 | X27: 764.26233 | Y27: 772.81659 | Z27: 781.92377 | AA27: 791.5379 | AB27: 801.55286 | AC27: 811.25696 | AD27: 822.5852 | AE27: 834.92804 | AF27: 849.58417 | AG27: 861.80377 | AH27: 876.91168 | AI27: 892.96716 | AJ27: 910.64691 | AK27: 0.011
A28: Medium | B28: Transportation Energy Use: Highway: Freight Trucks: Medium: High oil and gas supply | C28: 45-AEO2020.15.highogs-d112619a | D28: trillion Btu | E28: 910.4176 | F28: 904.67218 | G28: 906.67468 | H28: 910.82416 | I28: 916.18927 | J28: 916.7547 | K28: 917.79553 | L28: 919.64648 | M28: 923.70306 | N28: 928.14789 | O28: 932.71014 | P28: 934.43811 | Q28: 940.39081 | R28: 945.41644 | S28: 952.71179 | T28: 959.54273 | U28: 969.2384 | V28: 981.72199 | W28: 993.88721 | X28: 1007.3842 | Y28: 1021.9026 | Z28: 1038.1415 | AA28: 1055.7887 | AB28: 1075.1769 | AC28: 1096.2792 | AD28: 1121.1508 | AE28: 1148.5773 | AF28: 1180.0684 | AG28: 1208.2478 | AH28: 1240.3015 | AI28: 1274.1514 | AJ28: 1308.8241 | AK28: 0.012
A29: Large (> 26000 pounds) | B29: Transportation Energy Use: Highway: Freight Trucks: Large: High oil and gas supply | C29: 45-AEO2020.16.highogs-d112619a | D29: trillion Btu | E29: 4318.1768 | F29: 4346.4902 | G29: 4381.8887 | H29: 4405.5718 | I29: 4421.8057 | J29: 4402.0229 | K29: 4377.4868 | L29: 4343.0479 | M29: 4306.7202 | N29: 4261.3721 | O29: 4214.5854 | P29: 4156.6255 | Q29: 4120.2056 | R29: 4076.3474 | S29: 4043.5571 | T29: 4008.5645 | U29: 3983.8047 | V29: 3966.3625 | W29: 3947.2788 | X29: 3933.9556 | Y29: 3922.4082 | Z29: 3917.3357 | AA29: 3915.1064 | AB29: 3918.4707 | AC29: 3922.3528 | AD29: 3934.7407 | AE29: 3952.9514 | AF29: 3981.7366 | AG29: 3995.5945 | AH29: 4018.6345 | AI29: 4043.4175 | AJ29: 4066.7219 | AK29: -0.002
A30: Non-Highway | C30: 45-AEO2020.18.
A31: Air | B31: Transportation Energy Use: Non-Highway: Air: High oil and gas supply | C31: 45-AEO2020.19.highogs-d112619a | D31: trillion Btu | E31: 2640.9438 | F31: 2673.0667 | G31: 2706.3496 | H31: 2732.1909 | I31: 2752.4333 | J31: 2776.094 | K31: 2803.1313 | L31: 2828.6794 | M31: 2853.5171 | N31: 2879.8105 | O31: 2908.5222 | P31: 2937.1985 | Q31: 2967.3972 | R31: 2997.719 | S31: 3027.5989 | T31: 3053.2073 | U31: 3077.6519 | V31: 3104.4258 | W31: 3132.1252 | X31: 3160.3247 | Y31: 3189.8337 | Z31: 3220.1482 | AA31: 3250.1726 | AB31: 3279.9529 | AC31: 3310.7305 | AD31: 3344.5698 | AE31: 3383.1245 | AF31: 3426.0435 | AG31: 3471.1809 | AH31: 3520.3723 | AI31: 3571.7424 | AJ31: 3624.8132 | AK31: 0.01
A32: General Aviation | B32: Transportation Energy Use: Non-Highway: Air: General Aviation: High oil and gas supply | C32: 45-AEO2020.20.highogs-d112619a | D32: trillion Btu | E32: 147.15953 | F32: 148.67065 | G32: 150.24031 | H32: 151.45824 | I32: 152.41161 | J32: 153.52972 | K32: 154.81004 | L32: 156.02063 | M32: 157.19858 | N32: 158.44652 | O32: 159.81043 | P32: 161.17323 | Q32: 162.60881 | R32: 164.05092 | S32: 165.47211 | T32: 166.69023 | U32: 167.85316 | V32: 169.12738 | W32: 170.44545 | X32: 171.78783 | Y32: 173.19257 | Z32: 174.6355 | AA32: 176.06506 | AB32: 177.48273 | AC32: 178.94806 | AD32: 180.55942 | AE32: 182.39519 | AF32: 184.43875 | AG32: 186.58804 | AH32: 188.93048 | AI32: 191.37645 | AJ32: 193.90372 | AK32: 0.009
A33: Domestic Air Carriers | B33: Transportation Energy Use: Non-Highway: Air: Domestic Air Carriers: High oil and gas supply | C33: 45-AEO2020.21.highogs-d112619a | D33: trillion Btu | E33: 1635.2072 | F33: 1650.1774 | G33: 1668.0919 | H33: 1679.7188 | I33: 1686.4562 | J33: 1695.1627 | K33: 1706.0006 | L33: 1715.1434 | M33: 1723.5776 | N33: 1733.3123 | O33: 1744.8951 | P33: 1757.2142 | Q33: 1769.8943 | R33: 1782.7548 | S33: 1795.1801 | T33: 1804.9639 | U33: 1813.7872 | V33: 1823.9509 | W33: 1834.2209 | X33: 1845.1093 | Y33: 1856.511 | Z33: 1868.0806 | AA33: 1878.879 | AB33: 1889.5753 | AC33: 1900.677 | AD33: 1913.4052 | AE33: 1928.8691 | AF33: 1946.6647 | AG33: 1965.5006 | AH33: 1986.2723 | AI33: 2008.037 | AJ33: 2031.1687 | AK33: 0.007
A34: International Air Carriers | B34: Transportation Energy Use: Non-Highway: Air: International Air Carriers: High oil and gas supply | C34: 45-AEO2020.22.highogs-d112619a | D34: trillion Btu | E34: 714.12396 | F34: 730.10999 | G34: 747.56818 | H34: 762.11304 | I34: 774.37378 | J34: 787.69373 | K34: 802.18713 | L34: 815.99738 | M34: 829.63293 | N34: 844.11841 | O34: 859.7572 | P34: 875.99011 | Q34: 892.64008 | R34: 909.63281 | S34: 926.63452 | T34: 942.45721 | U34: 957.98291 | V34: 974.48108 | W34: 991.28644 | X34: 1008.6912 | Y34: 1026.6801 | Z34: 1045.0632 | AA34: 1063.4751 | AB34: 1082.0919 | AC34: 1101.2108 | AD34: 1121.5653 | AE34: 1143.8585 | AF34: 1167.8917 | AG34: 1192.9176 | AH34: 1219.5104 | AI34: 1247.116 | AJ34: 1275.6644 | AK34: 0.019
A35: Freight Carriers | B35: Transportation Energy Use: Non-Highway: Air: Freight Carriers: High oil and gas supply | C35: 45-AEO2020.23.highogs-d112619a | D35: trillion Btu | E35: 144.45309 | F35: 144.10854 | G35: 140.44926 | H35: 138.90096 | I35: 139.19157 | J35: 139.70784 | K35: 140.13348 | L35: 141.51813 | M35: 143.10794 | N35: 143.93337 | O35: 144.05933 | P35: 142.82098 | Q35: 142.25418 | R35: 141.28052 | S35: 140.31224 | T35: 139.09587 | U35: 138.02847 | V35: 136.8662 | W35: 136.17244 | X35: 134.73627 | Y35: 133.44994 | Z35: 132.36883 | AA35: 131.75345 | AB35: 130.80298 | AC35: 129.89465 | AD35: 129.03992 | AE35: 128.00151 | AF35: 127.04829 | AG35: 126.17458 | AH35: 125.65891 | AI35: 125.21304 | AJ35: 124.07639 | AK35: -0.005
A36: Water | B36: Transportation Energy Use: Non-Highway: Water: High oil and gas supply | C36: 45-AEO2020.24.highogs-d112619a | D36: trillion Btu | E36: 1262.223 | F36: 1343.0319 | G36: 1303.8322 | H36: 1217.3433 | I36: 1220.3928 | J36: 1202.0239 | K36: 1213.1461 | L36: 1186.0875 | M36: 1195.2208 | N36: 1194.0463 | O36: 1177.7366 | P36: 1189.1602 | Q36: 1188.8616 | R36: 1176.0665 | S36: 1184.9402 | T36: 1183.4945 | U36: 1178.7653 | V36: 1167.1626 | W36: 1172.2524 | X36: 1160.2507 | Y36: 1158.2136 | Z36: 1162.8938 | AA36: 1150.8705 | AB36: 1148.344 | AC36: 1144.6913 | AD36: 1140.4397 | AE36: 1137.3685 | AF36: 1135.8217 | AG36: 1132.6587 | AH36: 1130.8229 | AI36: 1129.4923 | AJ36: 1128.8481 | AK36: -0.004
A37: Freight | B37: Transportation Energy Use: Non-Highway: Water: Freight: High oil and gas supply | C37: 45-AEO2020.25.highogs-d112619a | D37: trillion Btu | E37: 1016.7357 | F37: 1096.7845 | G37: 1056.941 | H37: 970.11517 | I37: 972.99194 | J37: 954.46289 | K37: 965.3996 | L37: 938.21533 | M37: 947.27319 | N37: 946.01202 | O37: 929.61755 | P37: 941.0318 | Q37: 940.74268 | R37: 927.98798 | S37: 936.99731 | T37: 935.79016 | U37: 931.38336 | V37: 920.11212 | W37: 925.58014 | X37: 913.98023 | Y37: 912.36902 | Z37: 917.52997 | AA37: 906.03326 | AB37: 904.10101 | AC37: 901.05493 | AD37: 897.40314 | AE37: 894.90204 | AF37: 893.89569 | AG37: 891.2721 | AH37: 889.96435 | AI37: 889.17596 | AJ37: 889.08813 | AK37: -0.004
A38: Domestic Shipping | B38: Transportation Energy Use: Non-Highway: Water: Freight: Domestic Shipping: High oil and gas supply | C38: 45-AEO2020.26.highogs-d112619a | D38: trillion Btu | E38: 89.408684 | F38: 87.946663 | G38: 85.825142 | H38: 83.143684 | I38: 81.043098 | J38: 78.540054 | K38: 76.102608 | L38: 73.8507 | M38: 71.605797 | N38: 69.277527 | O38: 66.86528 | P38: 64.420662 | Q38: 63.281223 | R38: 62.043758 | S38: 60.933224 | T38: 59.681496 | U38: 58.471172 | V38: 57.385189 | W38: 56.208904 | X38: 55.024643 | Y38: 53.932945 | Z38: 52.831013 | AA38: 52.282791 | AB38: 51.791668 | AC38: 51.248352 | AD38: 50.799305 | AE38: 50.387039 | AF38: 50.149246 | AG38: 49.715466 | AH38: 49.415421 | AI38: 49.187336 | AJ38: 48.997417 | AK38: -0.019
A39: International Shipping | B39: Transportation Energy Use: Non-Highway: Water: Freight: International Shipping: High oil and gas supply | C39: 45-AEO2020.27.highogs-d112619a | D39: trillion Btu | E39: 927.32696 | F39: 1008.8378 | G39: 971.11591 | H39: 886.9715 | I39: 891.94885 | J39: 875.92285 | K39: 889.297 | L39: 864.36462 | M39: 875.66742 | N39: 876.7345 | O39: 862.75226 | P39: 876.61114 | Q39: 877.46143 | R39: 865.94421 | S39: 876.06409 | T39: 876.10864 | U39: 872.91217 | V39: 862.72693 | W39: 869.37122 | X39: 858.95557 | Y39: 858.4361 | Z39: 864.69898 | AA39: 853.75049 | AB39: 852.30933 | AC39: 849.80658 | AD39: 846.60382 | AE39: 844.51501 | AF39: 843.74646 | AG39: 841.55664 | AH39: 840.54895 | AI39: 839.98865 | AJ39: 840.0907 | AK39: -0.003
A40: Recreational Boats | B40: Transportation Energy Use: Non-Highway: Water: Recreational Boats: High oil and gas supply | C40: 45-AEO2020.28.highogs-d112619a | D40: trillion Btu | E40: 245.48737 | F40: 246.24731 | G40: 246.89113 | H40: 247.22803 | I40: 247.40088 | J40: 247.561 | K40: 247.74658 | L40: 247.87222 | M40: 247.94768 | N40: 248.03426 | O40: 248.11905 | P40: 248.12834 | Q40: 248.11883 | R40: 248.07858 | S40: 247.94284 | T40: 247.70436 | U40: 247.38197 | V40: 247.05051 | W40: 246.67229 | X40: 246.27057 | Y40: 245.84454 | Z40: 245.36371 | AA40: 244.83713 | AB40: 244.24297 | AC40: 243.63638 | AD40: 243.03659 | AE40: 242.46649 | AF40: 241.926 | AG40: 241.38654 | AH40: 240.85849 | AI40: 240.31628 | AJ40: 239.76006 | AK40: -0.001
A41: Rail | B41: Transportation Energy Use: Non-Highway: Rail: High oil and gas supply | C41: 45-AEO2020.29.highogs-d112619a | D41: trillion Btu | E41: 570.61951 | F41: 546.03455 | G41: 523.50366 | H41: 518.65912 | I41: 516.72046 | J41: 510.4024 | K41: 498.73596 | L41: 507.30695 | M41: 507.39301 | N41: 507.81271 | O41: 503.59045 | P41: 499.21533 | Q41: 498.74268 | R41: 498.92212 | S41: 499.33661 | T41: 499.81677 | U41: 498.15179 | V41: 498.84726 | W41: 498.22153 | X41: 495.09177 | Y41: 495.578 | Z41: 494.14456 | AA41: 493.68311 | AB41: 494.67279 | AC41: 495.42117 | AD41: 496.5531 | AE41: 498.297 | AF41: 502.10562 | AG41: 503.72974 | AH41: 506.58588 | AI41: 509.73932 | AJ41: 513.75122 | AK41: -0.003
A42: Freight | B42: Transportation Energy Use: Non-Highway: Rail: Freight: High oil and gas supply | C42: 45-AEO2020.30.highogs-d112619a | D42: trillion Btu | E42: 521.49481 | F42: 496.0322 | G42: 472.67419 | H42: 467.14597 | I42: 464.54727 | J42: 457.57266 | K42: 445.27527 | L42: 453.21878 | M42: 452.70502 | N42: 452.49731 | O42: 447.65079 | P42: 442.80438 | Q42: 441.68543 | R42: 441.23898 | S42: 441.04895 | T42: 440.97555 | U42: 438.7345 | V42: 438.8703 | W42: 437.68955 | X42: 433.99274 | Y42: 433.91113 | Z42: 431.91071 | AA42: 430.91129 | AB42: 431.36157 | AC42: 431.55756 | AD42: 432.13159 | AE42: 433.32553 | AF42: 436.53812 | AG42: 437.57886 | AH42: 439.82074 | AI42: 442.39105 | AJ42: 445.80643 | AK42: -0.005
... A53: Total | B53: Transportation Energy Use: Total: High oil and gas supply | C53: 45-AEO2020.43.highogs-d112619a | D53: trillion Btu | E53: 28113.373 | F53: 28230.869 | G53: 28208.764 | H53: 28011.26 | I53: 27787.75 | J53: 27465.568 | K53: 27155.045 | L53: 26881.73 | M53: 26659.488 | N53: 26449.74 | O53: 26245.27 | P53: 26070.695 | Q53: 25953.711 | R53: 25807.697 | S53: 25707.465 | T53: 25586.844 | U53: 25476.686 | V53: 25419.227 | W53: 25381.16 | X53: 25347.111 | Y53: 25350.15 | Z53: 25380.1 | AA53: 25402.027 | AB53: 25464.266 | AC53: 25534.621 | AD53: 25633.875 | AE53: 25761.697 | AF53: 25939.467 | AG53: 26103.859 | AH53: 26310.646 | AI53: 26534.156 | AJ53: 26773.309 | AK53: -0.002
A54: Energy Use by Type | C54: 45-AEO2020.45.
A55: Motor Gasoline excluding E85 | B55: Transportation Energy Use: Petroleum: Motor Gasoline: High oil and gas supply | C55: 45-AEO2020.46.highogs-d112619a | D55: trillion Btu | E55: 16549.932 | F55: 16522.381 | G55: 16441.443 | H55: 16259.478 | I55: 15982.112 | J55: 15662.639 | K55: 15317.657 | L55: 15050.626 | M55: 14823.722 | N55: 14617.606 | O55: 14432.009 | P55: 14261.387 | Q55: 14125.966 | R55: 13985.438 | S55: 13858.184 | T55: 13726.722 | U55: 13596.663 | V55: 13502.562 | W55: 13420.314 | X55: 13351.398 | Y55: 13301.795 | Z55: 13268.043 | AA55: 13238.325 | AB55: 13224.984 | AC55: 13219.75 | AD55: 13229.154 | AE55: 13257.222 | AF55: 13305.808 | AG55: 13364.965 | AH55: 13441.875 | AI55: 13531.795 | AJ55: 13633.456 | AK55: -0.006
A56: E85 | B56: Transportation Energy Use: E85: High oil and gas supply | C56: 45-AEO2020.47.highogs-d112619a | D56: trillion Btu | E56: 19.862495 | F56: 25.243965 | G56: 25.534731 | H56: 26.681034 | I56: 28.335787 | J56: 29.3298 | K56: 33.204823 | L56: 34.160919 | M56: 32.102829 | N56: 31.337315 | O56: 31.143978 | P56: 35.832336 | Q56: 34.118191 | R56: 33.44109 | S56: 33.061779 | T56: 32.209557 | U56: 32.014435 | V56: 32.282661 | W56: 32.174183 | X56: 32.11113 | Y56: 29.198238 | Z56: 26.767563 | AA56: 25.802158 | AB56: 22.979017 | AC56: 23.296274 | AD56: 23.40741 | AE56: 19.103216 | AF56: 17.506731 | AG56: 14.981414 | AH56: 14.800054 | AI56: 14.678515 | AJ56: 15.4762 | AK56: -0.008
A57: Diesel | B57: Transportation Energy Use: Petroleum: Diesel: High oil and gas supply | C57: 45-AEO2020.48.highogs-d112619a | D57: trillion Btu | E57: 6996.2236 | F57: 7122.9868 | G57: 7057.7153 | H57: 6959.8804 | I57: 6971.4199 | J57: 6968.647 | K57: 6908.6284 | L57: 6926.4014 | M57: 6869.417 | N57: 6819.3154 | O57: 6785.3198 | P57: 6695.3833 | Q57: 6654.563 | R57: 6623.9097 | S57: 6571.1802 | T57: 6531.3228 | U57: 6509.1025 | V57: 6508.6719 | W57: 6476.4233 | X57: 6475.1284 | Y57: 6463.6514 | Z57: 6448.1069 | AA57: 6461.8262 | AB57: 6467.6245 | AC57: 6478.2539 | AD57: 6502.7236 | AE57: 6534.0654 | AF57: 6580.793 | AG57: 6608.4395 | AH57: 6648.3291 | AI57: 6689.8101 | AJ57: 6730.1035 | AK57: -0.001
A58: Jet Fuel (kerosene & naphtha) | B58: Transportation Energy Use: Petroleum: Jet Fuel: High oil and gas supply | C58: 45-AEO2020.49.highogs-d112619a | D58: trillion Btu | E58: 3001.7886 | F58: 3036.5679 | G58: 3067.1274 | H58: 3089.0298 | I58: 3097.9346 | J58: 3114.0493 | K58: 3139.6846 | L58: 3163.8328 | M58: 3188.2424 | N58: 3216.4604 | O58: 3244.3743 | P58: 3272.5186 | Q58: 3302.7859 | R58: 3333.1934 | S58: 3363.177 | T58: 3388.9058 | U58: 3413.4873 | V58: 3440.4167 | W58: 3468.2896 | X58: 3496.677 | Y58: 3526.3887 | Z58: 3556.9182 | AA58: 3587.1692 | AB58: 3617.1851 | AC58: 3648.2073 | AD58: 3682.2991 | AE58: 3721.113 | AF58: 3764.2976 | AG58: 3809.7058 | AH58: 3859.1726 | AI58: 3910.8228 | AJ58: 3964.177 | AK58: 0.009
A59: Residual Fuel Oil | B59: Transportation Energy Use: Petroleum: Residual Fuel Oil: High oil and gas supply | C59: 45-AEO2020.50.highogs-d112619a | D59: trillion Btu | E59: 562.05536 | F59: 531.90418 | G59: 553.67804 | H59: 603.56909 | I59: 615.82465 | J59: 563.92096 | K59: 603.41009 | L59: 524.73645 | M59: 557.82379 | N59: 559.4696 | O59: 514.46368 | P59: 555.64471 | Q59: 556.54913 | R59: 519.41363 | S59: 549.07483 | T59: 547.64374 | U59: 536.33227 | V59: 503.48498 | W59: 522.3645 | X59: 488.84818 | Y59: 485.79688 | Z59: 503.60248 | AA59: 468.34439 | AB59: 462.50525 | AC59: 453.36588 | AD59: 442.09485 | AE59: 434.21487 | AF59: 430.32108 | AG59: 422.05041 | AH59: 417.2612 | AI59: 413.8425 | AJ59: 412.77423 | AK59: -0.01
A60: Aviation Gasoline | B60: Transportation Energy Use: Petroleum: Aviation Gasoline: High oil and gas supply | C60: 45-AEO2020.51.highogs-d112619a | D60: trillion Btu | E60: 22.470324 | F60: 22.450933 | G60: 22.434891 | H60: 22.421618 | I60: 22.410635 | J60: 22.401548 | K60: 22.394032 | L60: 22.387812 | M60: 22.382666 | N60: 22.378407 | O60: 22.374884 | P60: 22.371969 | Q60: 22.369558 | R60: 22.367563 | S60: 22.365911 | T60: 22.364546 | U60: 22.363417 | V60: 22.36248 | W60: 22.361708 | X60: 22.361067 | Y60: 22.360538 | Z60: 22.3601 | AA60: 22.359737 | AB60: 22.359438 | AC60: 22.35919 | AD60: 22.358984 | AE60: 22.358814 | AF60: 22.358673 | AG60: 22.358557 | AH60: 22.358461 | AI60: 22.358381 | AJ60: 22.358315 | AK60: 0
A61: Propane | B61: Transportation Energy Use: Petroleum: Propane: High oil and gas supply | C61: 45-AEO2020.52.highogs-d112619a | D61: trillion Btu | E61: 7.657276 | F61: 7.653785 | G61: 7.586419 | H61: 7.52744 | I61: 7.445743 | J61: 7.364764 | K61: 7.28232 | L61: 7.19181 | M61: 7.168025 | N61: 7.15703 | O61: 7.168547 | P61: 7.204074 | Q61: 7.216245 | R61: 7.260134 | S61: 7.334041 | T61: 7.431268 | U61: 7.530802 | V61: 7.661704 | W61: 7.806658 | X61: 7.966793 | Y61: 8.138635 | Z61: 8.324274 | AA61: 8.534259 | AB61: 8.756939 | AC61: 8.982894 | AD61: 9.23128 | AE61: 9.50943 | AF61: 9.812409 | AG61: 10.119851 | AH61: 10.454994 | AI61: 10.811787 | AJ61: 11.182622 | AK61: 0.012
A62: Lubricants | B62: Transportation Energy Use: Petroleum: Lubricants: High oil and gas supply | C62: 45-AEO2020.53.highogs-d112619a | D62: trillion Btu | E62: 131.4688 | F62: 130.9978 | G62: 130.61691 | H62: 130.16556 | I62: 129.71597 | J62: 129.23587 | K62: 128.71664 | L62: 128.21002 | M62: 127.73817 | N62: 127.32877 | O62: 126.99723 | P62: 126.67632 | Q62: 126.39497 | R62: 126.14228 | S62: 125.89642 | T62: 125.70426 | U62: 125.55006 | V62: 125.49034 | W62: 125.46355 | X62: 125.46944 | Y62: 125.51205 | Z62: 125.52898 | AA62: 125.53334 | AB62: 125.61249 | AC62: 125.6669 | AD62: 125.76542 | AE62: 125.93991 | AF62: 126.14378 | AG62: 126.36053 | AH62: 126.62708 | AI62: 126.86329 | AJ62: 127.07791 | AK62: -0.001
A63: Petroleum and Other Liquids Subtotal | B63: Transportation Energy Use: Petroleum Subtotal: High oil and gas supply | C63: 45-AEO2020.54.highogs-d112619a | D63: trillion Btu | E63: 27291.461 | F63: 27400.188 | G63: 27306.137 | H63: 27098.752 | I63: 26855.197 | J63: 26497.59 | K63: 26160.979 | L63: 25857.547 | M63: 25628.598 | N63: 25401.053 | O63: 25163.852 | P63: 24977.016 | Q63: 24829.963 | R63: 24651.166 | S63: 24530.273 | T63: 24382.307 | U63: 24243.045 | V63: 24142.934 | W63: 24075.197 | X63: 23999.961 | Y63: 23962.84 | Z63: 23959.65 | AA63: 23937.896 | AB63: 23952.01 | AC63: 23979.881 | AD63: 24037.037 | AE63: 24123.527 | AF63: 24257.041 | AG63: 24378.98 | AH63: 24540.879 | AI63: 24720.98 | AJ63: 24916.605 | AK63: -0.003
A64: M85 | B64: Transportation Energy Use: M85: High oil and gas supply | C64: 45-AEO2020.55.highogs-d112619a | D64: trillion Btu | E64: 0 | F64: 0 | G64: 0 | H64: 0 | I64: 0 | J64: 0 | K64: 0 | L64: 0 | M64: 0 | N64: 0 | O64: 0 | P64: 0 | Q64: 0 | R64: 0 | S64: 0 | T64: 0 | U64: 0 | V64: 0 | W64: 0 | X64: 0 | Y64: 0 | Z64: 0 | AA64: 0 | AB64: 0 | AC64: 0 | AD64: 0 | AE64: 0 | AF64: 0 | AG64: 0 | AH64: 0 | AI64: 0 | AJ64: 0 | AK64: - -
A65: Electricity | B65: Transportation Energy Use: Electricity: High oil and gas supply | C65: 45-AEO2020.56.highogs-d112619a | D65: trillion Btu | E65: 47.795029 | F65: 55.150471 | G65: 64.22538 | H65: 73.042702 | I65: 81.553291 | J65: 89.785378 | K65: 98.404716 | L65: 107.36632 | M65: 116.37162 | N65: 125.60815 | O65: 135.284 | P65: 145.77293 | Q65: 157.4238 | R65: 169.99832 | S65: 184.12589 | T65: 197.88741 | U65: 210.37291 | V65: 223.68597 | W65: 237.43968 | X65: 251.6152 | Y65: 266.16876 | Z65: 280.97986 | AA65: 295.66647 | AB65: 310.38831 | AC65: 325.11179 | AD65: 339.68912 | AE65: 354.16516 | AF65: 369.23172 | AG65: 384.06107 | AH65: 399.19025 | AI65: 414.48251 | AJ65: 429.89151 | AK65: 0.073
A66: Compressed/Liquefied Natural Gas | B66: Transportation Energy Use: Natural Gas: High oil and gas supply | C66: 45-AEO2020.57.highogs-d112619a | D66: trillion Btu | E66: 101.06208 | F66: 106.66568 | G66: 135.08421 | H66: 123.39756 | I66: 127.4782 | J66: 140.06422 | K66: 140.31729 | L66: 152.14859 | M66: 154.43762 | N66: 162.1174 | O66: 177.98422 | P66: 177.05515 | Q66: 187.97789 | R66: 204.50778 | S66: 210.49661 | T66: 222.22087 | U66: 235.43611 | V66: 253.39764 | W66: 263.63788 | X66: 282.27472 | Y66: 296.60358 | Z66: 307.51895 | AA66: 329.88119 | AB66: 348.32486 | AC66: 366.71652 | AD66: 385.34344 | AE66: 404.17032 | AF66: 423.08887 | AG66: 442.0921 | AH66: 461.32407 | AI66: 481.6655 | AJ66: 501.74286 | AK66: 0.053
A67: Hydrogen | B67: Transportation Energy Use: Hydrogen: High oil and gas supply | C67: 45-AEO2020.58.highogs-d112619a | D67: trillion Btu | E67: 0.274877 | F67: 0.300849 | G67: 0.31083 | H67: 0.314945 | I67: 0.316294 | J67: 0.316475 | K67: 0.317932 | L67: 0.322848 | M67: 0.330247 | N67: 0.339988 | O67: 0.352132 | P67: 0.366968 | Q67: 0.383826 | R67: 0.401677 | S67: 0.421015 | T67: 0.441648 | U67: 0.464972 | V67: 0.492086 | W67: 0.522663 | X67: 0.556304 | Y67: 0.59309 | Z67: 0.631984 | AA67: 0.681708 | AB67: 0.72897 | AC67: 0.778821 | AD67: 0.824748 | AE67: 0.870337 | AF67: 0.91691 | AG67: 0.964645 | AH67: 1.014005 | AI67: 1.064628 | AJ67: 1.116525 | AK67: 0.046
A68: Pipeline Fuel Natural Gas | B68: Transportation Energy Use: Pipeline Fuel Natural Gas: High oil and gas supply | C68: 45-AEO2020.59.highogs-d112619a | D68: trillion Btu | E68: 671.92114 | F68: 667.21631 | G68: 701.37659 | H68: 713.80554 | I68: 720.88531 | J68: 735.13074 | K68: 751.8468 | L68: 760.75671 | M68: 755.91388 | N68: 756.47766 | O68: 763.30188 | P68: 765.38464 | Q68: 772.58118 | R68: 775.92578 | S68: 776.05963 | T68: 777.57422 | U68: 780.55438 | V68: 791.487 | W68: 796.76007 | X68: 804.71332 | Y68: 815.8562 | Z68: 823.09863 | AA68: 829.39862 | AB68: 844.2193 | AC68: 853.06616 | AD68: 861.44495 | AE68: 869.52753 | AF68: 879.44995 | AG68: 887.93481 | AH68: 897.92761 | AI68: 905.13617 | AJ68: 912.4433 | AK68: 0.01
A69: Total Consumption | B69: Transportation: Total Energy Use: High oil and gas supply | C69: 45-AEO2020.61.highogs-d112619a | D69: trillion Btu | E69: 28112.516 | F69: 28229.521 | G69: 28207.133 | H69: 28009.312 | I69: 27785.43 | J69: 27462.887 | K69: 27151.865 | L69: 26878.141 | M69: 26655.65 | N69: 26445.596 | O69: 26240.773 | P69: 26065.596 | Q69: 25948.332 | R69: 25802 | S69: 25701.377 | T69: 25580.43 | U69: 25469.873 | V69: 25411.996 | W69: 25373.559 | X69: 25339.121 | Y69: 25342.061 | Z69: 25371.881 | AA69: 25393.523 | AB69: 25455.67 | AC69: 25525.555 | AD69: 25624.34 | AE69: 25752.262 | AF69: 25929.727 | AG69: 26094.033 | AH69: 26300.334 | AI69: 26523.33 | AJ69: 26761.799 | AK69: -0.002

Sheet AEO 36
F1: 2019 | G1: 2020 | H1: 2021 | I1: 2022 | J1: 2023 | K1: 2024 | L1: 2025 | M1: 2026 | N1: 2027 | O1: 2028 | P1: 2029 | Q1: 2030 | R1: 2031 | S1: 2032 | T1: 2033 | U1: 2034 | V1: 2035 | W1: 2036 | X1: 2037 | Y1: 2038 | Z1: 2039 | AA1: 2040 | AB1: 2041 | AC1: 2042 | AD1: 2043 | AE1: 2044 | AF1: 2045 | AG1: 2046 | AH1: 2047 | AI1: 2048 | AJ1: 2049 | AK1: 2050 | AL1: Growth (2019-2050)
B10: Table 36. Transportation Sector Energy Use by Fuel Type Within a Mode
B11: https://www.eia.gov/outlooks/aeo/data/browser/#/?id=46-AEO2020&cases=highogs&sourcekey=0
B12: Tue Mar 09 2021 09:59:28 GMT-0800 (Pacific Standard Time)
B13: Source: U.S. Energy Information Administration
C14: full name | D14: api key | E14: units | F14: 2019 | G14: 2020 | H14: 2021 | I14: 2022 | J14: 2023 | K14: 2024 | L14: 2025 | M14: 2026 | N14: 2027 | O14: 2028 | P14: 2029 | Q14: 2030 | R14: 2031 | S14: 2032 | T14: 2033 | U14: 2034 | V14: 2035 | W14: 2036 | X14: 2037 | Y14: 2038 | Z14: 2039 | AA14: 2040 | AB14: 2041 | AC14: 2042 | AD14: 2043 | AE14: 2044 | AF14: 2045 | AG14: 2046 | AH14: 2047 | AI14: 2048 | AJ14: 2049 | AK14: 2050 | AL14: Growth (2019-2050)
B15: Light-Duty Vehicle | C15: Transportation Energy Use: Light-Duty Vehicle: Total: High oil and gas supply | D15: 46-AEO2020.2.highogs-d112619a | E15: trillion Btu | F15: 15312.444 | G15: 15307.14 | H15: 15236.718 | I15: 15068.805 | J15: 14804.812 | K15: 14499.306 | L15: 14167.156 | M15: 13909.195 | N15: 13685.458 | O15: 13482.775 | P15: 13299.862 | Q15: 13139.068 | R15: 13002.686 | S15: 12863.336 | T15: 12735.183 | U15: 12602.708 | V15: 12470.578 | W15: 12372.916 | X15: 12287.332 | Y15: 12215.108 | Z15: 12158.749 | AA15: 12118.073 | AB15: 12081.136 | AC15: 12057.517 | AD15: 12045.366 | AE15: 12044.355 | AF15: 12055.041 | AG15: 12085.418 | AH15: 12129.274 | AI15: 12190.245 | AJ15: 12262.822 | AK15: 12346.761 | AL15: -0.007
B16: Motor Gasoline excluding E85 | C16: Transportation Energy Use: Light-Duty Vehicle: Motor Gasoline: High oil and gas supply | D16: 46-AEO2020.3.highogs-d112619a | E16: trillion Btu | F16: 15199.481 | G16: 15180.85 | H16: 15098.542 | I16: 14917.298 | J16: 14640.975 | K16: 14325.252 | L16: 13980.959 | M16: 13712.799 | N16: 13481.304 | O16: 13269.926 | P16: 13077.647 | Q16: 12903.024 | R16: 12756.388 | S16: 12605.884 | T16: 12465.86 | U16: 12321.55 | V16: 12177.008 | W16: 12065.656 | X16: 11966.21 | Y16: 11879.646 | Z16: 11810.42 | AA16: 11755.599 | AB16: 11704.455 | AC16: 11667.807 | AD16: 11640.296 | AE16: 11624.686 | AF16: 11623.285 | AG16: 11639.25 | AH16: 11669.203 | AI16: 11714.549 | AJ16: 11771.21 | AK16: 11838.642 | AL16: -0.008
B17: E85 | C17: Transportation Energy Use: Light-Duty Vehicle: Ethanol: High oil and gas supply | D17: 46-AEO2020.4.highogs-d112619a | E17: trillion Btu | F17: 17.035625 | G17: 21.426731 | H17: 21.436373 | I17: 22.207422 | J17: 23.357349 | K17: 23.953354 | L17: 26.829184 | M17: 27.316523 | N17: 25.384455 | O17: 24.480259 | P17: 24.010527 | Q17: 27.252335 | R17: 25.556938 | S17: 24.658401 | T17: 23.970201 | U17: 22.945911 | V17: 22.393032 | W17: 22.164173 | X17: 21.680609 | Y17: 21.23234 | Z17: 18.944868 | AA17: 17.040964 | AB17: 16.113234 | AC17: 14.075607 | AD17: 13.99791 | AE17: 13.793528 | AF17: 11.035002 | AG17: 9.906834 | AH17: 8.313334 | AI17: 8.051833 | AJ17: 7.830171 | AK17: 8.098272 | AL17: -0.024
B18: Distillate Fuel Oil (diesel) | C18: Transportation Energy Use: Light-Duty Vehicle: Distillate Fuel Oil: High oil and gas supply | D18: 46-AEO2020.5.highogs-d112619a | E18: trillion Btu | F18: 63.969234 | G18: 66.730286 | H18: 70.605339 | I18: 75.36026 | J18: 79.035683 | K18: 81.421143 | L18: 83.099983 | M18: 84.855759 | N18: 86.411316 | O18: 87.736122 | P18: 88.876724 | Q18: 90.110703 | R18: 91.861847 | S18: 93.189301 | T18: 94.418015 | U18: 95.519661 | V18: 96.34549 | W18: 97.257484 | X18: 98.127975 | Y18: 98.988495 | Z18: 99.829384 | AA18: 101.29481 | AB18: 101.90889 | AC18: 102.41099 | AD18: 103.26958 | AE18: 103.63173 | AF18: 104.11983 | AG18: 104.72976 | AH18: 105.52435 | AI18: 106.4286 | AJ18: 107.42856 | AK18: 108.44432 | AL18: 0.017
B19: Compressed/Liquefied Natural Gas | C19: Transportation Energy Use: Light-Duty Vehicle: Natural Gas: High oil and gas supply | D19: 46-AEO2020.6.highogs-d112619a | E19: trillion Btu | F19: 5.73929 | G19: 5.261131 | H19: 4.957932 | I19: 4.670878 | J19: 4.392184 | K19: 4.119547 | L19: 3.802957 | M19: 3.548156 | N19: 3.399066 | O19: 3.233215 | P19: 3.145408 | Q19: 3.013467 | R19: 2.894538 | S19: 2.803918 | T19: 2.725028 | U19: 2.674252 | V19: 2.632086 | W19: 2.603294 | X19: 2.582047 | Y19: 2.582973 | Z19: 2.570287 | AA19: 2.559894 | AB19: 2.561738 | AC19: 2.564096 | AD19: 2.571058 | AE19: 2.579886 | AF19: 2.591878 | AG19: 2.60693 | AH19: 2.624655 | AI19: 2.646219 | AJ19: 2.668769 | AK19: 2.692575 | AL19: -0.024
B20: Propane | C20: Transportation Energy Use: Light-Duty Vehicle: Propane: High oil and gas supply | D20: 46-AEO2020.7.highogs-d112619a | E20: trillion Btu | F20: 3.780961 | G20: 3.515011 | H20: 3.204999 | I20: 2.921944 | J20: 2.640429 | K20: 2.397087 | L20: 2.190106 | M20: 1.98849 | N20: 1.858488 | O20: 1.748247 | P20: 1.664872 | Q20: 1.616745 | R20: 1.528985 | S20: 1.477662 | T20: 1.43833 | U20: 1.415262 | V20: 1.385289 | W20: 1.372331 | X20: 1.367014 | Y20: 1.36366 | Z20: 1.36307 | AA20: 1.363592 | AB20: 1.377485 | AC20: 1.393089 | AD20: 1.405051 | AE20: 1.420997 | AF20: 1.447421 | AG20: 1.468693 | AH20: 1.499175 | AI20: 1.526954 | AJ20: 1.562022 | AK20: 1.589708 | AL20: -0.028
B21: Electricity | C21: Transportation Energy Use: Light-Duty Vehicle: Electricity: High oil and gas supply | D21: 46-AEO2020.8.highogs-d112619a | E21: trillion Btu | F21: 22.194469 | G21: 29.087179 | H21: 37.69017 | I21: 46.062927 | J21: 54.126274 | K21: 61.878109 | L21: 69.989319 | M21: 78.39698 | N21: 86.801628 | O21: 95.343201 | P21: 104.19643 | Q21: 113.71558 | R21: 124.10317 | S21: 134.95456 | T21: 146.38309 | U21: 158.19431 | V21: 170.38174 | W21: 183.40375 | X21: 196.8738 | Y21: 210.77278 | Z21: 225.06065 | AA21: 239.61594 | AB21: 254.06908 | AC21: 268.569 | AD21: 283.08017 | AE21: 297.4516 | AF21: 311.72357 | AG21: 326.57141 | AH21: 341.17658 | AI21: 356.05942 | AJ21: 371.08896 | AK21: 386.20929 | AL21: 0.097
B22: Hydrogen | C22: Transportation Energy Use: Light-Duty Vehicle: Hydrogen: High oil and gas supply | D22: 46-AEO2020.9.highogs-d112619a | E22: trillion Btu | F22: 0.244584 | G22: 0.270362 | H22: 0.28015 | I22: 0.284073 | J22: 0.28523 | K22: 0.285227 | L22: 0.286521 | M22: 0.291278 | N22: 0.29852 | O22: 0.308114 | P22: 0.320115 | Q22: 0.334829 | R22: 0.351576 | S22: 0.369324 | T22: 0.388562 | U22: 0.409105 | V22: 0.432351 | W22: 0.459401 | X22: 0.489928 | Y22: 0.523536 | Z22: 0.56031 | AA22: 0.599215 | AB22: 0.648974 | AC22: 0.696295 | AD22: 0.746228 | AE22: 0.792258 | AF22: 0.837969 | AG22: 0.884676 | AH22: 0.932552 | AI22: 0.982053 | AJ22: 1.032795 | AK22: 1.084782 | AL22: 0.049
B23: Commercial Light Trucks | C23: Transportation Energy Use: Commercial Light Trucks: Total: High oil and gas supply | D23: 46-AEO2020.29.highogs-d112619a | E23: trillion Btu | F23: 890.89917 | G23: 891.76575 | H23: 895.74506 | I23: 897.72205 | J23: 896.93951 | K23: 893.02771 | L23: 892.48267 | M23: 891.86066 | N23: 892.44971 | O23: 893.48975 | P23: 895.32581 | Q23: 896.54938 | R23: 901.15045 | S23: 904.67493 | T23: 909.68127 | U23: 914.78699 | V23: 920.06 | W23: 926.88635 | X23: 934.08356 | Y23: 941.37378 | Z23: 949.04761 | AA23: 957.56714 | AB23: 966.61407 | AC23: 975.66669 | AD23: 985.86127 | AE23: 997.53308 | AF23: 1010.4193 | AG23: 1026.7943 | AH23: 1039.973 | AI23: 1054.2693 | AJ23: 1068.9308 | AK23: 1083.4713 | AL23: 0.006
B24: Motor Gasoline excluding E85 | C24: Transportation Energy Use: Commercial Light Trucks: Motor Gasoline: High oil and gas supply | D24: 46-AEO2020.30.highogs-d112619a | E24: trillion Btu | F24: 595.89923 | G24: 590.37848 | H24: 588.03449 | I24: 584.95227 | J24: 580.21753 | K24: 574.47736 | L24: 571.12573 | M24: 568.71521 | N24: 568.39905 | O24: 568.5614 | P24: 569.49805 | Q24: 569.23401 | R24: 572.94452 | S24: 575.81103 | T24: 579.96906 | U24: 584.47821 | V24: 589.08411 | W24: 594.81274 | X24: 601.27228 | Y24: 608.02661 | Z24: 615.97882 | AA24: 624.44788 | AB24: 632.54114 | AC24: 641.46631 | AD24: 649.3819 | AE24: 658.06604 | AF24: 669.42169 | AG24: 681.92133 | AH24: 693.21137 | AI24: 704.52264 | AJ24: 716.33118 | AK24: 728.07343 | AL24: 0.006
B25: E85 | C25: Transportation Energy Use: Commercial Light Trucks: E85: High oil and gas supply | D25: 46-AEO2020.31.highogs-d112619a | E25: trillion Btu | F25: 2.821502 | G25: 3.811841 | H25: 4.092943 | I25: 4.468173 | J25: 4.972974 | K25: 5.370958 | L25: 6.37013 | M25: 6.83887 | N25: 6.712829 | O25: 6.851489 | P25: 7.127867 | Q25: 8.574407 | R25: 8.555639 | S25: 8.777064 | T25: 9.085947 | U25: 9.258004 | V25: 9.615754 | W25: 10.112835 | X25: 10.487921 | Y25: 10.873137 | Z25: 10.24772 | AA25: 9.720957 | AB25: 9.683296 | AC25: 8.897798 | AD25: 9.292772 | AE25: 9.608315 | AF25: 8.062674 | AG25: 7.594388 | AH25: 6.6626 | AI25: 6.742769 | AJ25: 6.842918 | AK25: 7.372523 | AL25: 0.031
B26: Distillate Fuel Oil (diesel) | C26: Transportation Energy Use: Commercial Light Trucks: Distillate Fuel Oil: High oil and gas supply | D26: 46-AEO2020.32.highogs-d112619a | E26: trillion Btu | F26: 290.96457 | G26: 296.35336 | H26: 302.31195 | I26: 306.91986 | J26: 310.25812 | K26: 311.58682 | L26: 313.32199 | M26: 314.57257 | N26: 315.55011 | O26: 316.23627 | P26: 316.80414 | Q26: 316.79217 | R26: 317.64154 | S26: 318.01819 | T26: 318.48956 | U26: 318.84314 | V26: 319.07819 | W26: 319.59921 | X26: 319.88031 | Y26: 319.94638 | Z26: 320.20547 | AA26: 320.68985 | AB26: 321.58499 | AC26: 322.39767 | AD26: 324.17795 | AE26: 326.7385 | AF26: 329.69339 | AG26: 333.90292 | AH26: 336.59091 | AI26: 339.34921 | AJ26: 341.94281 | AK26: 344.04034 | AL26: 0.005
... B28: Compressed/Liquefied Natural Gas | C28: Transportation Energy Use: Commercial Light Trucks: Natural Gas: High oil and gas supply | D28: 46-AEO2020.34.highogs-d112619a | E28: trillion Btu | F28: 1.032728 | G28: 0.892461 | H28: 0.834829 | I28: 0.77312 | J28: 0.755125 | K28: 0.736579 | L28: 0.714388 | M28: 0.692867 | N28: 0.672466 | O28: 0.652118 | P28: 0.633047 | Q28: 0.614338 | R28: 0.598108 | S28: 0.584005 | T28: 0.575195 | U28: 0.568726 | V28: 0.564531 | W28: 0.561669 | X28: 0.559763 | Y28: 0.558316 | Z28: 0.557915 | AA28: 0.558718 | AB28: 0.560485 | AC28: 0.563213 | AD28: 0.567338 | AE28: 0.573771 | AF28: 0.582667 | AG28: 0.594227 | AH28: 0.603862 | AI28: 0.618238 | AJ28: 0.637756 | AK28: 0.663077 | AL28: -0.014
B29: Electricity | C29: Transportation Energy Use: Commercial Light Trucks: Electricity: High oil and gas supply | D29: 46-AEO2020.35.highogs-d112619a | E29: trillion Btu | F29: 0 | G29: 0.062943 | H29: 0.122493 | I29: 0.179998 | J29: 0.233812 | K29: 0.284879 | L29: 0.333762 | M29: 0.381328 | N29: 0.413251 | O29: 0.444819 | P29: 0.476749 | Q29: 0.507622 | R29: 0.539985 | S29: 0.571189 | T29: 0.603402 | U29: 0.635684 | V29: 0.668439 | W29: 0.702819 | X29: 0.737713 | Y29: 0.773452 | Z29: 0.809864 | AA29: 0.847996 | AB29: 0.887194 | AC29: 0.927665 | AD29: 0.969063 | AE29: 1.012511 | AF29: 1.058829 | AG29: 1.109148 | AH29: 1.159517 | AI29: 1.213544 | AJ29: 1.270671 | AK29: 1.330036 | AL29: - -
B30: Hydrogen | C30: Transportation Energy Use: Commercial Light Trucks: Hydrogen: High oil and gas supply | D30: 46-AEO2020.36.highogs-d112619a | E30: trillion Btu | F30: 0 | G30: 0 | H30: 0 | I30: 0 | J30: 0 | K30: 0 | L30: 0 | M30: 0 | N30: 0 | O30: 0 | P30: 0 | Q30: 0 | R30: 0 | S30: 0 | T30: 0 | U30: 0 | V30: 0 | W30: 0 | X30: 0 | Y30: 0 | Z30: 0 | AA30: 0 | AB30: 0 | AC30: 0 | AD30: 0 | AE30: 0 | AF30: 0 | AG30: 0 | AH30: 0 | AI30: 0 | AJ30: 0 | AK30: 0 | AL30: - -
B31: Freight Trucks | C31: Transportation Energy Use: Freight Trucks: Total: High oil and gas supply | D31: 46-AEO2020.38.highogs-d112619a | E31: trillion Btu | F31: 5881.6943 | G31: 5905.2188 | H31: 5953.2422 | I31: 5985.7568 | J31: 6012.8101 | K31: 5996.0127 | L31: 5975.9302 | M31: 5946.187 | N31: 5917.5112 | O31: 5879.7192 | P31: 5841.2891 | Q31: 5788.1685 | R31: 5765.2388 | S31: 5732.8813 | T31: 5715.4561 | U31: 5695 | V31: 5689.6113 | W31: 5695.0796 | X31: 5696.8452 | Y31: 5705.6016 | Z31: 5717.1284 | AA31: 5737.4014 | AB31: 5762.4326 | AC31: 5795.2007 | AD31: 5829.8887 | AE31: 5878.4771 | AF31: 5936.4551 | AG31: 6011.3892 | AH31: 6065.646 | AI31: 6135.8477 | AJ31: 6210.5352 | AK31: 6286.1934 | AL31: 0.002
B32: Motor Gasoline | C32: Transportation Energy Use: Freight Trucks: Motor Gasoline: High oil and gas supply | D32: 46-AEO2020.39.highogs-d112619a | E32: trillion Btu | F32: 540.73395 | G32: 537.84741 | H32: 542.10693 | I32: 545.05066 | J32: 549.37195 | K32: 552.02496 | L32: 555.38165 | M32: 559.65637 | N32: 565.34204 | O32: 571.26288 | P32: 577.86774 | Q32: 583.05084 | R32: 591.53278 | S32: 599.66785 | T32: 609.36938 | U32: 618.84637 | V32: 629.91504 | W32: 642.67639 | X32: 654.70227 | Y32: 666.92889 | Z32: 679.97559 | AA32: 693.99664 | AB32: 708.79211 | AC32: 724.6748 | AD32: 740.57458 | AE32: 758.47546 | AF32: 778.18762 | AG32: 799.9342 | AH32: 819.49426 | AI32: 841.4057 | AJ32: 864.521 | AK32: 888.68237 | AL32: 0.016
B33: Distillate Fuel Oil (diesel) | C33: Transportation Energy Use: Freight Trucks: Distillate Fuel Oil: High oil and gas supply | D33: 46-AEO2020.40.highogs-d112619a | E33: trillion Btu | F33: 5283.1289 | G33: 5306.9424 | H33: 5349.1597 | I33: 5377.9526 | J33: 5400.4771 | K33: 5381.6416 | L33: 5358.9424 | M33: 5325.897 | N33: 5292.5874 | O33: 5249.8521 | P33: 5205.5933 | Q33: 5147.7773 | R33: 5116.6934 | S33: 5076.332 | T33: 5048.8105 | U33: 5018.2153 | V33: 5000.5215 | W33: 4991.415 | X33: 4978.9336 | Y33: 4972.6812 | Z33: 4968.2041 | AA33: 4970.9541 | AB33: 4976.9712 | AC33: 4989.2261 | AD33: 5002.5151 | AE33: 5026.9771 | AF33: 5058.8213 | AG33: 5104.1782 | AH33: 5130.8525 | AI33: 5169.6533 | AJ33: 5210.7144 | AK33: 5250.5322 | AL33: 0
B34: Compressed/Liquefied Natural Gas | C34: Transportation Energy Use: Freight Trucks: Natural Gas: High oil and gas supply | D34: 46-AEO2020.41.highogs-d112619a | E34: trillion Btu | F34: 55.134178 | G34: 57.093094 | H34: 58.223106 | I34: 58.559811 | J34: 58.292088 | K34: 57.231102 | L34: 55.931793 | M34: 54.498985 | N34: 53.148956 | O34: 51.826164 | P34: 50.658936 | Q34: 49.543758 | R34: 48.892788 | S34: 48.404388 | T34: 48.36216 | U34: 48.631775 | V34: 49.407616 | W34: 50.719105 | X34: 52.486225 | Y34: 54.779701 | Z34: 57.534088 | AA34: 60.793663 | AB34: 64.598251 | AC34: 68.99585 | AD34: 73.883759 | AE34: 79.473824 | AF34: 85.826004 | AG34: 93.153931 | AH34: 100.89922 | AI34: 109.68303 | AJ34: 119.4538 | AK34: 130.20404 | AL34: 0.028
B35: Propane | C35: Transportation Energy Use: Freight Trucks: Propane: High oil and gas supply | D35: 46-AEO2020.42.highogs-d112619a | E35: trillion Btu | F35: 1.960367 | G35: 2.1215 | H35: 2.266892 | I35: 2.395148 | J35: 2.505968 | K35: 2.583966 | L35: 2.648583 | M35: 2.702281 | N35: 2.752202 | O35: 2.795959 | P35: 2.834885 | Q35: 2.865149 | R35: 2.909102 | S35: 2.949782 | T35: 3.00678 | U35: 3.070877 | V35: 3.144099 | W35: 3.229989 | X35: 3.322527 | Y35: 3.427361 | Z35: 3.540749 | AA35: 3.665833 | AB35: 3.801986 | AC35: 3.948754 | AD35: 4.102226 | AE35: 4.272044 | AF35: 4.457664 | AG35: 4.667796 | AH35: 4.873384 | AI35: 5.103682 | AJ35: 5.342509 | AK35: 5.597682 | AL35: 0.034
B36: E85 | C36: Transportation Energy Use: Freight Trucks: E85: High oil and gas supply | D36: 46-AEO2020.43.highogs-d112619a | E36: trillion Btu | F36: 0.700699 | G36: 0.925426 | H36: 0.974728 | I36: 1.053808 | J36: 1.185472 | K36: 1.333321 | L36: 1.612093 | M36: 1.805291 | N36: 1.836704 | O36: 1.923446 | P36: 2.057781 | Q36: 2.445045 | R36: 2.502855 | S36: 2.601396 | T36: 2.756835 | U36: 2.863327 | V36: 3.019962 | W36: 3.194428 | X36: 3.311527 | Y36: 3.439568 | Z36: 3.27103 | AA36: 3.116567 | AB36: 3.110485 | AC36: 2.896846 | AD36: 3.046129 | AE36: 3.180807 | AF36: 2.711284 | AG36: 2.614661 | AH36: 2.304864 | AI36: 2.363302 | AJ36: 2.421665 | AK36: 2.627188 | AL36: 0.044
B37: Electricity | C37: Transportation Energy Use: Freight Trucks: Electricity: High oil and gas supply | D37: 46-AEO2020.44.highogs-d112619a | E37: trillion Btu | F37: 0.011563 | G37: 0.111948 | H37: 0.198932 | I37: 0.289752 | J37: 0.379985 | K37: 0.465577 | L37: 0.549008 | M37: 0.630298 | N37: 0.711034 | O37: 0.790491 | P37: 0.869031 | Q37: 0.94371 | R37: 1.022145 | S37: 1.098413 | T37: 1.177207 | U37: 1.255466 | V37: 1.337856 | W37: 1.42449 | X37: 1.512214 | Y37: 1.604873 | Z37: 1.698438 | AA37: 1.796811 | AB37: 1.899993 | AC37: 2.008631 | AD37: 2.118988 | AE37: 2.236684 | AF37: 2.361648 | AG37: 2.498656 | AH37: 2.632588 | AI37: 2.779589 | AJ37: 2.935927 | AK37: 3.101992 | AL37: 0.198
B38: Hydrogen | C38: Transportation Energy Use: Freight Trucks: Hydrogen: High oil and gas supply | D38: 46-AEO2020.45.highogs-d112619a | E38: trillion Btu | F38: 0.024469 | G38: 0.176735 | H38: 0.311558 | I38: 0.455412 | J38: 0.597673 | K38: 0.732324 | L38: 0.864866 | M38: 0.997107 | N38: 1.132654 | O38: 1.268626 | P38: 1.407123 | Q38: 1.5425 | R38: 1.686081 | S38: 1.827401 | T38: 1.973075 | U38: 2.116877 | V38: 2.265429 | W38: 2.420031 | X38: 2.576428 | Y38: 2.740173 | Z38: 2.904387 | AA38: 3.077651 | AB38: 3.258968 | AC38: 3.449954 | AD38: 3.64774 | AE38: 3.861133 | AF38: 4.08988 | AG38: 4.34175 | AH38: 4.589088 | AI38: 4.859178 | AJ38: 5.146183 | AK38: 5.447536 | AL38: 0.19
B39: Freight Rail | C39: Transportation Energy Use: Freight Rail: Total: High oil and gas supply | D39: 46-AEO2020.48.highogs-d112619a | E39: trillion Btu | F39: 521.49481 | G39: 496.0322 | H39: 472.67419 | I39: 467.14597 | J39: 464.54727 | K39: 457.57266 | L39: 445.27527 | M39: 453.21878 | N39: 452.70502 | O39: 452.49731 | P39: 447.65079 | Q39: 442.80438 | R39: 441.68543 | S39: 441.23898 | T39: 441.04895 | U39: 440.97555 | V39: 438.7345 | W39: 438.8703 | X39: 437.68955 | Y39: 433.99274 | Z39: 433.91113 | AA39: 431.91071 | AB39: 430.91129 | AC39: 431.36157 | AD39: 431.55756 | AE39: 432.13159 | AF39: 433.32553 | AG39: 436.53812 | AH39: 437.57886 | AI39: 439.82074 | AJ39: 442.39105 | AK39: 445.80643 | AL39: -0.005
B40: Distillate Fuel Oil (diesel) | C40: Transportation Energy Use: Freight Rail: Distillate Fuel Oil: High oil and gas supply | D40: 46-AEO2020.49.highogs-d112619a | E40: trillion Btu | F40: 521.49481 | G40: 495.50134 | H40: 471.15774 | I40: 464.15228 | J40: 459.59439 | K40: 450.27182 | L40: 434.29849 | M40: 436.59869 | N40: 429.20914 | O40: 420.73407 | P40: 406.74524 | Q40: 393.16223 | R40: 383.20844 | S40: 374.06174 | T40: 365.33307 | U40: 356.89035 | V40: 346.92865 | W40: 339.07257 | X40: 330.40054 | Y40: 320.09222 | Z40: 312.68826 | AA40: 304.10449 | AB40: 296.43866 | AC40: 289.9389 | AD40: 283.41437 | AE40: 277.27918 | AF40: 271.66495 | AG40: 267.39889 | AH40: 261.88574 | AI40: 257.18719 | AJ40: 252.75401 | AK40: 248.8606 | AL40: -0.024
B41: Residual Fuel Oil | C41: Transportation Energy Use: Freight Rail: Residual Fuel Oil: High oil and gas supply | D41: 46-AEO2020.50.highogs-d112619a | E41: trillion Btu | F41: 0 | G41: 0 | H41: 0 | I41: 0 | J41: 0 | K41: 0 | L41: 0 | M41: 0 | N41: 0 | O41: 0 | P41: 0 | Q41: 0 | R41: 0 | S41: 0 | T41: 0 | U41: 0 | V41: 0 | W41: 0 | X41: 0 | Y41: 0 | Z41: 0 | AA41: 0 | AB41: 0 | AC41: 0 | AD41: 0 | AE41: 0 | AF41: 0 | AG41: 0 | AH41: 0 | AI41: 0 | AJ41: 0 | AK41: 0 | AL41: - -
B42: Compressed Natural Gas | C42: Transportation Energy Use: Freight Rail: CNG: High oil and gas supply | D42: 46-AEO2020.51.highogs-d112619a | E42: trillion Btu | F42: 0 | G42: 0 | H42: 0 | I42: 0 | J42: 0 | K42: 0 | L42: 0 | M42: 0 | N42: 0 | O42: 0 | P42: 0 | Q42: 0 | R42: 0 | S42: 0 | T42: 0 | U42: 0 | V42: 0 | W42: 0 | X42: 0 | Y42: 0 | Z42: 0 | AA42: 0 | AB42: 0 | AC42: 0 | AD42: 0 | AE42: 0 | AF42: 0 | AG42: 0 | AH42: 0 | AI42: 0 | AJ42: 0 | AK42: 0 | AL42: - -
B43: Liquefied Natural Gas | C43: Transportation Energy Use: Freight Rail: LNG: High oil and gas supply | D43: 46-AEO2020.52.highogs-d112619a | E43: trillion Btu | F43: 0 | G43: 0.530842 | H43: 1.516452 | I43: 2.99369 | J43: 4.952883 | K43: 7.300835 | L43: 10.976789 | M43: 16.6201 | N43: 23.49588 | O43: 31.763241 | P43: 40.90556 | Q43: 49.642147 | R43: 58.476997 | S43: 67.177246 | T43: 75.715881 | U43: 84.085205 | V43: 91.805855 | W43: 99.797722 | X43: 107.289 | Y43: 113.90051 | Z43: 121.22288 | AA43: 127.80621 | AB43: 134.47263 | AC43: 141.42265 | AD43: 148.14317 | AE43: 154.85242 | AF43: 161.66058 | AG43: 169.13922 | AH43: 175.69312 | AI43: 182.63354 | AJ43: 189.63705 | AK43: 196.94583 | AL43: - -
B44: Domestic Shipping | C44: Transportation Energy Use: Domestic Shipping: Total: High oil and gas supply | D44: 46-AEO2020.54.highogs-d112619a | E44: trillion Btu | F44: 89.408684 | G44: 87.946663 | H44: 85.825142 | I44: 83.143684 | J44: 81.043098 | K44: 78.540054 | L44: 76.102608 | M44: 73.8507 | N44: 71.605797 | O44: 69.277527 | P44: 66.86528 | Q44: 64.420662 | R44: 63.281223 | S44: 62.043758 | T44: 60.933224 | U44: 59.681496 | V44: 58.471172 | W44: 57.385189 | X44: 56.208904 | Y44: 55.024643 | Z44: 53.932945 | AA44: 52.831013 | AB44: 52.282791 | AC44: 51.791668 | AD44: 51.248352 | AE44: 50.799305 | AF44: 50.387039 | AG44: 50.149246 | AH44: 49.715466 | AI44: 49.415421 | AJ44: 49.187336 | AK44: 48.997417 | AL44: -0.019
B45: Distillate Fuel Oil (diesel) | C45: Transportation Energy Use: Domestic Shipping: Distillate Fuel Oil: High oil and gas supply | D45: 46-AEO2020.55.highogs-d112619a | E45: trillion Btu | F45: 86.762909 | G45: 84.306114 | H45: 83.001831 | I45: 81.066429 | J45: 79.037163 | K45: 76.613297 | L45: 74.252258 | M45: 72.069481 | N45: 69.893257 | O45: 67.634338 | P45: 65.292313 | Q45: 62.918449 | R45: 61.819187 | S45: 60.623375 | T45: 59.551369 | U45: 58.340328 | V45: 57.16909 | W45: 56.117264 | X45: 54.977631 | Y45: 53.831322 | Z45: 52.775951 | AA45: 51.681522 | AB45: 51.084251 | AC45: 50.539864 | AD45: 49.941414 | AE45: 49.431511 | AF45: 48.953728 | AG45: 48.641235 | AH45: 48.134163 | AI45: 47.751972 | AJ45: 47.434082 | AK45: 47.147133 | AL45: -0.019
B46: Residual Oil | C46: Transportation Energy Use: Domestic Shipping: Residual Oil: High oil and gas supply | D46: 46-AEO2020.56.highogs-d112619a | E46: trillion Btu | F46: 2.235385 | G46: 3.185952 | H46: 2.322066 | I46: 1.536846 | J46: 1.430444 | K46: 1.323928 | L46: 1.223205 | M46: 1.135517 | N46: 1.048485 | O46: 0.964474 | P46: 0.883116 | Q46: 0.802012 | R46: 0.737509 | S46: 0.674934 | T46: 0.61419 | U46: 0.555478 | V46: 0.500224 | W46: 0.453879 | X46: 0.404642 | Y46: 0.351124 | Z46: 0.296574 | AA46: 0.248728 | AB46: 0.246076 | AC46: 0.243664 | AD46: 0.241051 | AE46: 0.238882 | AF46: 0.236868 | AG46: 0.235655 | AH46: 0.233567 | AI46: 0.232095 | AJ46: 0.230928 | AK46: 0.229971 | AL46: -0.071
B47: Compressed Natural Gas | C47: Transportation Energy Use: Domestic Shipping: CNG: High oil and gas supply | D47: 46-AEO2020.57.highogs-d112619a | E47: trillion Btu | F47: 0 | G47: 0 | H47: 0 | I47: 0 | J47: 0 | K47: 0 | L47: 0 | M47: 0 | N47: 0 | O47: 0 | P47: 0 | Q47: 0 | R47: 0 | S47: 0 | T47: 0 | U47: 0 | V47: 0 | W47: 0 | X47: 0 | Y47: 0 | Z47: 0 | AA47: 0 | AB47: 0 | AC47: 0 | AD47: 0 | AE47: 0 | AF47: 0 | AG47: 0 | AH47: 0 | AI47: 0 | AJ47: 0 | AK47: 0 | AL47: - -
B48: Liquefied Natural Gas | C48: Transportation Energy Use: Domestic Shipping: LNG: High oil and gas supply | D48: 46-AEO2020.58.highogs-d112619a | E48: trillion Btu | F48: 0.410393 | G48: 0.454601 | H48: 0.501242 | I48: 0.540412 | J48: 0.575496 | K48: 0.60283 | L48: 0.627143 | M48: 0.645708 | N48: 0.664057 | O48: 0.678715 | P48: 0.689847 | Q48: 0.700197 | R48: 0.724525 | S48: 0.745451 | T48: 0.767666 | U48: 0.785691 | V48: 0.801855 | W48: 0.814045 | X48: 0.826633 | Y48: 0.842197 | Z48: 0.860422 | AA48: 0.900761 | AB48: 0.952467 | AC48: 1.008142 | AD48: 1.065889 | AE48: 1.128912 | AF48: 1.196442 | AG48: 1.272354 | AH48: 1.347738 | AI48: 1.431353 | AJ48: 1.522328 | AK48: 1.620312 | AL48: 0.045
B49: International Shipping | C49: Transportation Energy Use: International Shipping: Total: High oil and gas supply | D49: 46-AEO2020.60.highogs-d112619a | E49: trillion Btu | F49: 927.32696 | G49: 1008.8378 | H49: 971.11591 | I49: 886.9715 | J49: 891.94885 | K49: 875.92285 | L49: 889.297 | M49: 864.36462 | N49: 875.66742 | O49: 876.7345 | P49: 862.75226 | Q49: 876.61114 | R49: 877.46143 | S49: 865.94421 | T49: 876.06409 | U49: 876.10864 | V49: 872.91217 | W49: 862.72693 | X49: 869.37122 | Y49: 858.95557 | Z49: 858.4361 | AA49: 864.69898 | AB49: 853.75049 | AC49: 852.30933 | AD49: 849.80658 | AE49: 846.60382 | AF49: 844.51501 | AG49: 843.74646 | AH49: 841.55664 | AI49: 840.54895 | AJ49: 839.98865 | AK49: 840.0907 | AL49: -0.003
B50: Distillate Fuel Oil (diesel) | C50: Transportation Energy Use: International Shipping: Distillate Fuel Oil: High oil and gas supply | D50: 46-AEO2020.61.highogs-d112619a | E50: trillion Btu | F50: 373.04852 | G50: 492.6366 | H50: 398.9743 | I50: 270.68814 | J50: 260.35339 | K50: 284.41614 | L50: 260.1181 | M50: 305.99264 | N50: 287.35303 | O50: 286.02362 | P50: 309.09839 | Q50: 290.22256 | R50: 287.38904 | S50: 304.67053 | T50: 287.64252 | U50: 286.05914 | V50: 289.48724 | W50: 303.53296 | X50: 290.35971 | Y50: 303.77838 | Z50: 302.08588 | AA50: 289.51819 | AB50: 302.03198 | AC50: 299.42145 | AD50: 299.35516 | AE50: 301.17114 | AF50: 301.36945 | AG50: 300.46417 | AH50: 301.91916 | AI50: 302.29303 | AJ50: 301.71484 | AK50: 301.03601 | AL50: -0.007
B51: Residual Oil | C51: Transportation Energy Use: International Shipping: Residual Oil: High oil and gas supply | D51: 46-AEO2020.62.highogs-d112619a | E51: trillion Btu | F51: 540.36908 | G51: 498.79111 | H51: 528.29767 | I51: 585.81372 | J51: 598.65875 | K51: 547.18671 | L51: 586.83374 | M51: 508.31253 | N51: 541.50269 | O51: 543.14996 | P51: 498.26242 | Q51: 539.54382 | R51: 540.50958 | S51: 503.43539 | T51: 533.15039 | U51: 531.77252 | V51: 520.51074 | W51: 487.70532 | X51: 506.62466 | Y51: 473.15625 | Z51: 470.15079 | AA51: 487.99304 | AB51: 452.73077 | AC51: 446.88406 | AD51: 437.73727 | AE51: 426.45844 | AF51: 418.56988 | AG51: 414.66602 | AH51: 406.38666 | AI51: 401.58768 | AJ51: 398.15857 | AK51: 397.07925 | AL51: -0.01
B52: Compressed Natural Gas | C52: Transportation Energy Use: International Shipping: CNG: High oil and gas supply | D52: 46-AEO2020.63.highogs-d112619a | E52: trillion Btu | F52: 0 | G52: 0 | H52: 0 | I52: 0 | J52: 0 | K52: 0 | L52: 0 | M52: 0 | N52: 0 | O52: 0 | P52: 0 | Q52: 0 | R52: 0 | S52: 0 | T52: 0 | U52: 0 | V52: 0 | W52: 0 | X52: 0 | Y52: 0 | Z52: 0 | AA52: 0 | AB52: 0 | AC52: 0 | AD52: 0 | AE52: 0 | AF52: 0 | AG52: 0 | AH52: 0 | AI52: 0 | AJ52: 0 | AK52: 0 | AL52: - -
B53: Liquefied Natural Gas | C53: Transportation Energy Use: International Shipping: LNG: High oil and gas supply | D53: 46-AEO2020.64.highogs-d112619a | E53: trillion Btu | F53: 13.90934 | G53: 17.410114 | H53: 43.843933 | I53: 30.469658 | J53: 32.936737 | K53: 44.320019 | L53: 42.345123 | M53: 50.059467 | N53: 46.811691 | O53: 47.560921 | P53: 55.391411 | Q53: 46.84478 | R53: 49.562832 | S53: 57.838287 | T53: 55.271194 | U53: 58.276951 | V53: 62.9142 | W53: 71.488655 | X53: 72.386871 | Y53: 82.02092 | Z53: 86.199387 | AA53: 87.187721 | AB53: 98.987724 | AC53: 106.00382 | AD53: 112.71416 | AE53: 118.97422 | AF53: 124.57568 | AG53: 128.61629 | AH53: 133.25089 | AI53: 136.66824 | AJ53: 140.11526 | AK53: 141.97546 | AL53: 0.078
B54: Air Transportation | C54: Transportation Energy Use: Air: Total: High oil and gas supply | D54: 46-AEO2020.66.highogs-d112619a | E54: trillion Btu | F54: 2640.9438 | G54: 2673.0671 | H54: 2706.3494 | I54: 2732.1907 | J54: 2752.4331 | K54: 2776.0942 | L54: 2803.1311 | M54: 2828.6794 | N54: 2853.5171 | O54: 2879.8105 | P54: 2908.5222 | Q54: 2937.199 | R54: 2967.3979 | S54: 2997.7192 | T54: 3027.5994 | U54: 3053.2075 | V54: 3077.6519 | W54: 3104.426 | X54: 3132.1257 | Y54: 3160.3245 | Z54: 3189.8337 | AA54: 3220.1482 | AB54: 3250.1729 | AC54: 3279.9529 | AD54: 3310.7305 | AE54: 3344.5701 | AF54: 3383.1245 | AG54: 3426.0437 | AH54: 3471.1812 | AI54: 3520.3723 | AJ54: 3571.7427 | AK54: 3624.8132 | AL54: 0.01
B55: Jet Fuel | C55: Transportation Energy Use: Air: Jet Fuel: High oil and gas supply | D55: 46-AEO2020.67.highogs-d112619a | E55: trillion Btu | F55: 2618.4736 | G55: 2650.6162 | H55: 2683.9146 | I55: 2709.769 | J55: 2730.0225 | K55: 2753.6926 | L55: 2780.7371 | M55: 2806.2917 | N55: 2831.1345 | O55: 2857.4321 | P55: 2886.1472 | Q55: 2914.8269 | R55: 2945.0283 | S55: 2975.3516 | T55: 3005.2334 | U55: 3030.843 | V55: 3055.2883 | W55: 3082.0635 | X55: 3109.7639 | Y55: 3137.9634 | Z55: 3167.4731 | AA55: 3197.7881 | AB55: 3227.8132 | AC55: 3257.5935 | AD55: 3288.3713 | AE55: 3322.2112 | AF55: 3360.7656 | AG55: 3403.6851 | AH55: 3448.8225 | AI55: 3498.0139 | AJ55: 3549.3843 | AK55: 3602.4548 | AL55: 0.01
B56: Aviation Gasoline | C56: Transportation Energy Use: Air: Aviation Gasoline: High oil and gas supply | D56: 46-AEO2020.68.highogs-d112619a | E56: trillion Btu | F56: 22.470324 | G56: 22.450933 | H56: 22.434891 | I56: 22.421618 | J56: 22.410635 | K56: 22.401548 | L56: 22.394032 | M56: 22.387812 | N56: 22.382666 | O56: 22.378407 | P56: 22.374884 | Q56: 22.371969 | R56: 22.369558 | S56: 22.367563 | T56: 22.365911 | U56: 22.364546 | V56: 22.363417 | W56: 22.36248 | X56: 22.361708 | Y56: 22.361067 | Z56: 22.360538 | AA56: 22.3601 | AB56: 22.359737 | AC56: 22.359438 | AD56: 22.35919 | AE56: 22.358984 | AF56: 22.358814 | AG56: 22.358673 | AH56: 22.358557 | AI56: 22.358461 | AJ56: 22.358381 | AK56: 22.358315 | AL56: 0
B57: Military Use | C57: Transportation Energy Use: Military: Total: High oil and gas supply | D57: 46-AEO2020.70.highogs-d112619a | E57: trillion Btu | F57: 512.50098 | G57: 526.36877 | H57: 515.97742 | I57: 504.05402 | J57: 488.97348 | K57: 478.92966 | L57: 477.05975 | M57: 475.18619 | N57: 474.61319 | O57: 477.16595 | P57: 476.09851 | Q57: 475.39038 | R57: 475.47815 | S57: 475.58762 | T57: 475.72589 | U57: 475.88477 | V57: 476.06509 | W57: 476.2684 | X57: 476.49933 | Y57: 476.74661 | Z57: 477.01523 | AA57: 477.30243 | AB57: 477.59964 | AC57: 477.91263 | AD57: 478.237 | AE57: 478.57141 | AF57: 478.91544 | AG57: 479.2681 | AH57: 479.62705 | AI57: 479.99258 | AJ57: 480.36383 | AK57: 480.74091 | AL57: -0.002
B58: Jet Fuel and Aviation Gasoline | C58: Transportation Energy Use: Military: Jet Fuel: High oil and gas supply | D58: 46-AEO2020.71.highogs-d112619a | E58: trillion Btu | F58: 383.31488 | G58: 385.95166 | H58: 383.21307 | I58: 379.26086 | J58: 367.91223 | K58: 360.35663 | L58: 358.94733 | M58: 357.54108 | N58: 357.10788 | O58: 359.02832 | P58: 358.22723 | Q58: 357.69171 | R58: 357.75745 | S58: 357.84161 | T58: 357.94373 | U58: 358.06293 | V58: 358.19885 | W58: 358.35339 | X58: 358.5256 | Y58: 358.7135 | Z58: 358.91553 | AA58: 359.13013 | AB58: 359.35586 | AC58: 359.59143 | AD58: 359.83582 | AE58: 360.08804 | AF58: 360.34729 | AG58: 360.61267 | AH58: 360.88336 | AI58: 361.15878 | AJ58: 361.43842 | AK58: 361.72223 | AL58: -0.002
B59: Residual Fuel Oil | C59: Transportation Energy Use: Military: Residual Fuel Oil: High oil and gas supply | D59: 46-AEO2020.72.highogs-d112619a | E59: trillion Btu | F59: 19.450865 | G59: 29.927103 | H59: 23.058311 | I59: 16.218527 | J59: 15.735498 | K59: 15.410321 | L59: 15.353174 | M59: 15.288407 | N59: 15.272653 | O59: 15.355188 | P59: 15.318134 | Q59: 15.298865 | R59: 15.302093 | S59: 15.30329 | T59: 15.310247 | U59: 15.315752 | V59: 15.32127 | W59: 15.325762 | X59: 15.335192 | Y59: 15.340797 | Z59: 15.349513 | AA59: 15.360726 | AB59: 15.367565 | AC59: 15.377542 | AD59: 15.387534 | AE59: 15.397519 | AF59: 15.408121 | AG59: 15.419409 | AH59: 15.430182 | AI59: 15.44144 | AJ59: 15.452998 | AK59: 15.465006 | AL59: -0.007
B60: Distillates and Diesel | C60: Transportation Energy Use: Military: Distillate Fuel Oil: High oil and gas supply | D60: 46-AEO2020.73.highogs-d112619a | E60: trillion Btu | F60: 109.7352 | G60: 110.49005 | H60: 109.70604 | I60: 108.57461 | J60: 105.32574 | K60: 103.16272 | L60: 102.75926 | M60: 102.35668 | N60: 102.23267 | O60: 102.78245 | P60: 102.55312 | Q60: 102.3998 | R60: 102.41863 | S60: 102.44272 | T60: 102.47194 | U60: 102.50607 | V60: 102.54498 | W60: 102.58923 | X60: 102.63853 | Y60: 102.69233 | Z60: 102.75017 | AA60: 102.8116 | AB60: 102.87622 | AC60: 102.94366 | AD60: 103.01363 | AE60: 103.08583 | AF60: 103.16004 | AG60: 103.23602 | AH60: 103.31351 | AI60: 103.39236 | AJ60: 103.47241 | AK60: 103.55366 | AL60: -0.002
B61: Bus Transportation | C61: Transportation Energy Use: Bus: High oil and gas supply | D61: 46-AEO2020.75.highogs-d112619a | E61: trillion Btu | F61: 237.91908 | G61: 239.20258 | H61: 240.47951 | I61: 241.71786 | J61: 242.88548 | K61: 244.05521 | L61: 245.27902 | M61: 246.43924 | N61: 247.52335 | O61: 248.54263 | P61: 249.42992 | Q61: 250.04468 | R61: 250.34396 | S61: 250.14467 | T61: 248.84425 | U61: 248.21402 | V61: 249.1734 | W61: 250.07764 | X61: 250.9297 | Y61: 251.72684 | Z61: 252.46313 | AA61: 253.13748 | AB61: 253.74773 | AC61: 254.29733 | AD61: 254.79733 | AE61: 255.25417 | AF61: 255.68042 | AG61: 256.09723 | AH61: 256.53055 | AI61: 257.00531 | AJ61: 257.56427 | AK61: 258.22113 | AL61: 0.003
B62: Transit Bus | C62: Transportation Energy Use: Bus: Transit Bus: High oil and gas supply | D62: 46-AEO2020.76.highogs-d112619a | E62: trillion Btu | F62: 99.315071 | G62: 99.945122 | H62: 100.56989 | I62: 101.19645 | J62: 101.8311 | K62: 102.44681 | L62: 103.00167 | M62: 103.5542 | N62: 104.09944 | O62: 104.62385 | P62: 105.14225 | Q62: 105.59572 | R62: 106.02787 | S62: 106.43801 | T62: 106.85069 | U62: 107.24017 | V62: 107.60039 | W62: 107.92464 | X62: 108.20892 | Y62: 108.4436 | Z62: 108.61575 | AA62: 108.71909 | AB62: 108.74683 | AC62: 108.69933 | AD62: 108.58459 | AE62: 108.40518 | AF62: 108.17055 | AG62: 107.90131 | AH62: 107.62363 | AI62: 107.36424 | AJ62: 107.17227 | AK62: 107.07778 | AL62: 0.002
A63: gasoline vehicle | B63: Motor Gasoline | C63: Transportation Energy Use: Bus: Transit Bus: Motor Gasoline: High oil and gas supply | D63: 46-AEO2020.77.highogs-d112619a | E63: trillion Btu | F63: 11.729362 | G63: 11.816158 | H63: 11.902537 | I63: 11.989355 | J63: 12.077346 | K63: 12.163309 | L63: 12.24227 | M63: 12.321168 | N63: 12.399398 | O63: 12.475354 | P63: 12.550812 | Q63: 12.618748 | R63: 12.684372 | S63: 12.747585 | T63: 12.811311 | U63: 12.872458 | V63: 12.930288 | W63: 12.983989 | X63: 13.033067 | Y63: 13.076353 | Z63: 13.112251 | AA63: 13.139974 | AB63: 13.158654 | AC63: 13.168315 | AD63: 13.16989 | AE63: 13.163657 | AF63: 13.15073 | AG63: 13.133533 | AH63: 13.115028 | AI63: 13.098603 | AJ63: 13.090434 | AK63: 13.094159 | AL63: 0.004
A64: gasoline vehicle | B64: E85 | C64: Transportation Energy Use: Bus: Transit Bus: E85: High oil and gas supply | D64: 46-AEO2020.78.highogs-d112619a | E64: trillion Btu | F64: 0.005368 | G64: 0.005391 | H64: 0.005415 | I64: 0.005439 | J64: 0.005464 | K64: 0.005488 | L64: 0.005508 | M64: 0.005528 | N64: 0.005548 | O64: 0.005566 | P64: 0.005584 | Q64: 0.005598 | R64: 0.00561 | S64: 0.005621 | T64: 0.005632 | U64: 0.005641 | V64: 0.005648 | W64: 0.005653 | X64: 0.005655 | Y64: 0.005654 | Z64: 0.00565 | AA64: 0.005642 | AB64: 0.005629 | AC64: 0.005612 | AD64: 0.005592 | AE64: 0.005568 | AF64: 0.00554 | AG64: 0.005511 | AH64: 0.005481 | AI64: 0.005451 | AJ64: 0.005425 | AK64: 0.005405 | AL64: 0
A65: diesel vehicle | B65: Distillate Fuel Oil (diesel) | C65: Transportation Energy Use: Bus: Transit Bus: Distillate Fuel Oil: High oil and gas supply | D65: 46-AEO2020.79.highogs-d112619a | E65: trillion Btu | F65: 61.387569 | G65: 61.672279 | H65: 61.939911 | I65: 62.190567 | J65: 62.422646 | K65: 62.612831 | L65: 62.726738 | M65: 62.788414 | N65: 62.778576 | O65: 62.666222 | P65: 62.425926 | Q65: 61.968517 | R65: 61.225372 | S65: 60.003315 | T65: 57.804356 | U65: 56.319401 | V65: 56.465099 | W65: 56.59269 | X65: 56.699474 | Y65: 56.780441 | Z65: 56.828808 | AA65: 56.841164 | AB65: 56.814117 | AC65: 56.748055 | AD65: 56.647324 | AE65: 56.513416 | AF65: 56.351532 | AG65: 56.173229 | AH65: 55.993633 | AI65: 55.826946 | AJ65: 55.697281 | AK65: 55.618725 | AL65: -0.003
A66: natural gas vehicle | B66: Compressed/Liquefied Natural Gas | C66: Transportation Energy Use: Bus: Transit Bus: Natural Gas: High oil and gas supply | D66: 46-AEO2020.80.highogs-d112619a | E66: trillion Btu | F66: 23.941086 | G66: 24.109018 | H66: 24.273115 | I66: 24.435379 | J66: 24.5977 | K66: 24.753761 | L66: 24.893671 | M66: 25.031811 | N66: 25.167294 | O66: 25.296886 | P66: 25.424404 | Q66: 25.535629 | R66: 25.640987 | S66: 25.740217 | T66: 25.839128 | U66: 25.931463 | V66: 26.015888 | W66: 26.091043 | X66: 26.156277 | Y66: 26.209276 | Z66: 26.246954 | AA66: 26.267929 | AB66: 26.270508 | AC66: 26.254749 | AD66: 26.222553 | AE66: 26.174509 | AF66: 26.112797 | AG66: 26.042229 | AH66: 25.968571 | AI66: 25.897781 | AJ66: 25.842039 | AK66: 25.809378 | AL66: 0.002
A67: LPG vehicle | B67: Propane | C67: Transportation Energy Use: Bus: Transit Bus: Propane: High oil and gas supply | D67: 46-AEO2020.81.highogs-d112619a | E67: trillion Btu | F67: 1.644644 | G67: 1.660068 | H67: 1.675301 | I67: 1.690487 | J67: 1.705746 | K67: 1.720629 | L67: 1.734441 | M67: 1.748175 | N67: 1.761762 | O67: 1.774971 | P67: 1.788064 | Q67: 1.800035 | R67: 1.811618 | S67: 1.822791 | T67: 1.83396 | U67: 1.844679 | V67: 1.854849 | W67: 1.864369 | X67: 1.873193 | Y67: 1.88115 | Z67: 1.888014 | AA67: 1.893678 | AB67: 1.89801 | AC67: 1.901005 | AD67: 1.902789 | AE67: 1.903395 | AF67: 1.902977 | AG67: 1.901822 | AH67: 1.900251 | AI67: 1.898759 | AJ67: 1.898358 | AK67: 1.899673 | AL67: 0.005
A68: battery electric vehicle | B68: Electricity | C68: Transportation Energy Use: Bus: Transit Bus: Electricity: High oil and gas supply | D68: 46-AEO2020.82.highogs-d112619a | E68: trillion Btu | F68: 0.576744 | G68: 0.651724 | H68: 0.742932 | I68: 0.854355 | J68: 0.991125 | K68: 1.159545 | L68: 1.36763 | M68: 1.627523 | N68: 1.955137 | O68: 2.372971 | P68: 2.915441 | Q68: 3.635056 | R68: 4.62767 | S68: 6.08612 | T68: 8.523853 | U68: 10.233985 | V68: 10.296 | W68: 10.354218 | X68: 10.408522 | Y68: 10.457965 | Z68: 10.501291 | AA68: 10.537944 | AB68: 10.56717 | AC68: 10.588911 | AD68: 10.603847 | AE68: 10.612144 | AF68: 10.614607 | AG68: 10.612758 | AH68: 10.608591 | AI68: 10.604752 | AJ68: 10.606899 | AK68: 10.6187 | AL68: 0.099
A69: hydrogen vehicle | B69: Hydrogen | C69: Transportation Energy Use: Bus: Transit Bus: Hydrogen: High oil and gas supply | D69: 46-AEO2020.83.highogs-d112619a | E69: trillion Btu | F69: 0.030293 | G69: 0.030488 | H69: 0.03068 | I69: 0.030871 | J69: 0.031064 | K69: 0.031248 | L69: 0.031411 | M69: 0.031571 | N69: 0.031727 | O69: 0.031874 | P69: 0.032018 | Q69: 0.032139 | R69: 0.03225 | S69: 0.032353 | T69: 0.032453 | U69: 0.032543 | V69: 0.032621 | W69: 0.032685 | X69: 0.032735 | Y69: 0.032768 | Z69: 0.03278 | AA69: 0.03277 | AB69: 0.032734 | AC69: 0.032675 | AD69: 0.032593 | AE69: 0.03249 | AF69: 0.032368 | AG69: 0.032234 | AH69: 0.032092 | AI69: 0.031953 | AJ69: 0.031833 | AK69: 0.031743 | AL69: 0.002
B70: Intercity Bus | C70: Transportation Energy Use: Bus: Intercity Bus: High oil and gas supply | D70: 46-AEO2020.84.highogs-d112619a | E70: trillion Btu | F70: 34.017525 | G70: 34.295715 | H70: 34.571033 | I70: 34.845947 | J70: 35.122425 | K70: 35.390961 | L70: 35.642731 | M70: 35.891884 | N70: 36.136688 | O70: 36.372597 | P70: 36.604843 | Q70: 36.834064 | R70: 37.057114 | S70: 37.274578 | T70: 37.495804 | U70: 37.713417 | V70: 37.927135 | W70: 38.136677 | X70: 38.341736 | Y70: 38.542122 | Z70: 38.737698 | AA70: 38.928463 | AB70: 39.114555 | AC70: 39.296169 | AD70: 39.473579 | AE70: 39.647072 | AF70: 39.817013 | AG70: 39.983807 | AH70: 40.147793 | AI70: 40.309471 | AJ70: 40.469448 | AK70: 40.627487 | AL70: 0.006
A71: gasoline vehicle | B71: Motor Gasoline | C71: Transportation Energy Use: Bus: Intercity Bus: Motor Gasoline: High oil and gas supply | D71: 46-AEO2020.85.highogs-d112619a | E71: trillion Btu | F71: 0 | G71: 0 | H71: 0 | I71: 0 | J71: 0 | K71: 0 | L71: 0 | M71: 0 | N71: 0 | O71: 0 | P71: 0 | Q71: 0 | R71: 0 | S71: 0 | T71: 0 | U71: 0 | V71: 0 | W71: 0 | X71: 0 | Y71: 0 | Z71: 0 | AA71: 0 | AB71: 0 | AC71: 0 | AD71: 0 | AE71: 0 | AF71: 0 | AG71: 0 | AH71: 0 | AI71: 0 | AJ71: 0 | AK71: 0 | AL71: - -
A72: gasoline vehicle | B72: E85 | C72: Transportation Energy Use: Bus: Intercity Bus: E85: High oil and gas supply | D72: 46-AEO2020.86.highogs-d112619a | E72: trillion Btu | F72: 0 | G72: 0 | H72: 0 | I72: 0 | J72: 0 | K72: 0 | L72: 0 | M72: 0 | N72: 0 | O72: 0 | P72: 0 | Q72: 0 | R72: 0 | S72: 0 | T72: 0 | U72: 0 | V72: 0 | W72: 0 | X72: 0 | Y72: 0 | Z72: 0 | AA72: 0 | AB72: 0 | AC72: 0 | AD72: 0 | AE72: 0 | AF72: 0 | AG72: 0 | AH72: 0 | AI72: 0 | AJ72: 0 | AK72: 0 | AL72: - -
A73: diesel vehicle | B73: Distillate Fuel Oil (diesel) | C73: Transportation Energy Use: Bus: Intercity Bus: Distillate Fuel Oil: High oil and gas supply | D73: 46-AEO2020.87.highogs-d112619a | E73: trillion Btu | F73: 34.017525 | G73: 34.295715 | H73: 34.571033 | I73: 34.845947 | J73: 35.122425 | K73: 35.390961 | L73: 35.642731 | M73: 35.891884 | N73: 36.136688 | O73: 36.372597 | P73: 36.604843 | Q73: 36.834064 | R73: 37.057114 | S73: 37.274578 | T73: 37.495804 | U73: 37.713417 | V73: 37.927135 | W73: 38.136677 | X73: 38.341736 | Y73: 38.542122 | Z73: 38.737698 | AA73: 38.928463 | AB73: 39.114555 | AC73: 39.296169 | AD73: 39.473579 | AE73: 39.647072 | AF73: 39.817013 | AG73: 39.983807 | AH73: 40.147793 | AI73: 40.309471 | AJ73: 40.469448 | AK73: 40.627487 | AL73: 0.006
A74: natural gas vehicle | B74: Compressed/Liquefied Natural Gas | C74: Transportation Energy Use: Bus: Intercity Bus: Natural Gas: High oil and gas supply | D74: 46-AEO2020.88.highogs-d112619a | E74: trillion Btu | F74: 0 | G74: 0 | H74: 0 | I74: 0 | J74: 0 | K74: 0 | L74: 0 | M74: 0 | N74: 0 | O74: 0 | P74: 0 | Q74: 0 | R74: 0 | S74: 0 | T74: 0 | U74: 0 | V74: 0 | W74: 0 | X74: 0 | Y74: 0 | Z74: 0 | AA74: 0 | AB74: 0 | AC74: 0 | AD74: 0 | AE74: 0 | AF74: 0 | AG74: 0 | AH74: 0 | AI74: 0 | AJ74: 0 | AK74: 0 | AL74: - -
A75: LPG vehicle | B75: Propane | C75: Transportation Energy Use: Bus: Intercity Bus: Propane: High oil and gas supply | D75: 46-AEO2020.89.highogs-d112619a | E75: trillion Btu | F75: 0 | G75: 0 | H75: 0 | I75: 0 | J75: 0 | K75: 0 | L75: 0 | M75: 0 | N75: 0 | O75: 0 | P75: 0 | Q75: 0 | R75: 0 | S75: 0 | T75: 0 | U75: 0 | V75: 0 | W75: 0 | X75: 0 | Y75: 0 | Z75: 0 | AA75: 0 | AB75: 0 | AC75: 0 | AD75: 0 | AE75: 0 | AF75: 0 | AG75: 0 | AH75: 0 | AI75: 0 | AJ75: 0 | AK75: 0 | AL75: - -
A76: battery electric vehicle | B76: Electricity | C76: Transportation Energy Use: Bus: Intercity Bus: Electricity: High oil and gas supply | D76: 46-AEO2020.90.highogs-d112619a | E76: trillion Btu | F76: 0 | G76: 0 | H76: 0 | I76: 0 | J76: 0 | K76: 0 | L76: 0 | M76: 0 | N76: 0 | O76: 0 | P76: 0 | Q76: 0 | R76: 0 | S76: 0 | T76: 0 | U76: 0 | V76: 0 | W76: 0 | X76: 0 | Y76: 0 | Z76: 0 | AA76: 0 | AB76: 0 | AC76: 0 | AD76: 0 | AE76: 0 | AF76: 0 | AG76: 0 | AH76: 0 | AI76: 0 | AJ76: 0 | AK76: 0 | AL76: - -
A77: hydrogen vehicle | B77: Hydrogen | C77: Transportation Energy Use: Bus: Intercity Bus: Hydrogen: High oil and gas supply | D77: 46-AEO2020.91.highogs-d112619a | E77: trillion Btu | F77: 0 | G77: 0 | H77: 0 | I77: 0 | J77: 0 | K77: 0 | L77: 0 | M77: 0 | N77: 0 | O77: 0 | P77: 0 | Q77: 0 | R77: 0 | S77: 0 | T77: 0 | U77: 0 | V77: 0 | W77: 0 | X77: 0 | Y77: 0 | Z77: 0 | AA77: 0 | AB77: 0 | AC77: 0 | AD77: 0 | AE77: 0 | AF77: 0 | AG77: 0 | AH77: 0 | AI77: 0 | AJ77: 0 | AK77: 0 | AL77: - -
B78: School Bus | C78: Transportation Energy Use: Bus: School Bus: High oil and gas supply | D78: 46-AEO2020.92.highogs-d112619a | E78: trillion Btu | F78: 105.19891 | G78: 105.64934 | H78: 106.1176 | I78: 106.56614 | J78: 106.9596 | K78: 107.41371 | L78: 108.03915 | M78: 108.65778 | N78: 109.27963 | O78: 109.95661 | P78: 110.63587 | Q78: 111.28769 | R78: 111.9245 | S78: 112.55617 | T78: 113.05969 | U78: 113.53259 | V78: 113.98013 | W78: 114.40887 | X78: 114.82594 | Y78: 115.2375 | Z78: 115.64941 | AA78: 116.06626 | AB78: 116.49187 | AC78: 116.92904 | AD78: 117.38118 | AE78: 117.85213 | AF78: 118.34538 | AG78: 118.86262 | AH78: 119.40527 | AI78: 119.97376 | AJ78: 120.56672 | AK78: 121.17171 | AL78: 0.005
A79: gasoline vehicle | B79: Motor Gasoline | C79: Transportation Energy Use: Bus: School Bus: Motor Gasoline: High oil and gas supply | D79: 46-AEO2020.93.highogs-d112619a | E79: trillion Btu | F79: 11.675825 | G79: 11.72582 | H79: 11.777789 | I79: 11.827572 | J79: 11.871243 | K79: 11.921642 | L79: 11.99106 | M79: 12.05972 | N79: 12.128736 | O79: 12.203874 | P79: 12.279263 | Q79: 12.351608 | R79: 12.422287 | S79: 12.492394 | T79: 12.548279 | U79: 12.600767 | V79: 12.650436 | W79: 12.698023 | X79: 12.744313 | Y79: 12.789989 | Z79: 12.835707 | AA79: 12.881972 | AB79: 12.92921 | AC79: 12.977732 | AD79: 13.027914 | AE79: 13.080184 | AF79: 13.134929 | AG79: 13.192336 | AH79: 13.252563 | AI79: 13.315661 | AJ79: 13.381471 | AK79: 13.448618 | AL79: 0.005
A80: gasoline vehicle | B80: E85 | C80: Transportation Energy Use: Bus: School Bus: E85: High oil and gas supply | D80: 46-AEO2020.94.highogs-d112619a | E80: trillion Btu | F80: 0 | G80: 0 | H80: 0 | I80: 0 | J80: 0 | K80: 0 | L80: 0 | M80: 0 | N80: 0 | O80: 0 | P80: 0 | Q80: 0 | R80: 0 | S80: 0 | T80: 0 | U80: 0 | V80: 0 | W80: 0 | X80: 0 | Y80: 0 | Z80: 0 | AA80: 0 | AB80: 0 | AC80: 0 | AD80: 0 | AE80: 0 | AF80: 0 | AG80: 0 | AH80: 0 | AI80: 0 | AJ80: 0 | AK80: 0 | AL80: - -
A81: diesel vehicle | B81: Distillate Fuel Oil (diesel) | C81: Transportation Energy Use: Bus: School Bus: Distillate Fuel Oil: High oil and gas supply | D81: 46-AEO2020.95.highogs-d112619a | E81: trillion Btu | F81: 92.537903 | G81: 92.918617 | H81: 93.315315 | I81: 93.692673 | J81: 94.02076 | K81: 94.400513 | L81: 94.930122 | M81: 95.453484 | N81: 95.97908 | O81: 96.552406 | P81: 97.126236 | Q81: 97.679932 | R81: 98.219223 | S81: 98.753113 | T81: 99.174217 | U81: 99.567772 | V81: 99.937981 | W81: 100.29074 | X81: 100.6322 | Y81: 100.96796 | Z81: 101.30301 | AA81: 101.64082 | AB81: 101.98547 | AC81: 102.33882 | AD81: 102.70414 | AE81: 103.08508 | AF81: 103.48481 | AG81: 103.90475 | AH81: 104.34637 | AI81: 104.80971 | AJ81: 105.29352 | AK81: 105.78712 | AL81: 0.004
A82: natural gas vehicle | B82: Compressed/Liquefied Natural Gas | C82: Transportation Energy Use: Bus: School Bus: Natural Gas: High oil and gas supply | D82: 46-AEO2020.96.highogs-d112619a | E82: trillion Btu | F82: 0.895065 | G82: 0.914413 | H82: 0.933599 | I82: 0.954611 | J82: 0.975991 | K82: 0.999553 | L82: 1.025436 | M82: 1.051499 | N82: 1.078207 | O82: 1.106151 | P82: 1.135606 | Q82: 1.160827 | R82: 1.187119 | S82: 1.214256 | T82: 1.240354 | U82: 1.266808 | V82: 1.294089 | W82: 1.322112 | X82: 1.351076 | Y82: 1.380845 | Z82: 1.411627 | AA82: 1.444049 | AB82: 1.477411 | AC82: 1.512335 | AD82: 1.548587 | AE82: 1.585911 | AF82: 1.624276 | AG82: 1.663713 | AH82: 1.704059 | AI82: 1.745638 | AJ82: 1.788462 | AK82: 1.832182 | AL82: 0.023
A83: LPG vehicle | B83: Propane | C83: Transportation Energy Use: Bus: School Bus: Propane: High oil and gas supply | D83: 46-AEO2020.97.highogs-d112619a | E83: trillion Btu | F83: 0.090107 | G83: 0.090493 | H83: 0.090894 | I83: 0.091279 | J83: 0.091616 | K83: 0.092004 | L83: 0.09254 | M83: 0.09307 | N83: 0.093603 | O83: 0.094183 | P83: 0.094764 | Q83: 0.095323 | R83: 0.095868 | S83: 0.096409 | T83: 0.096841 | U83: 0.097246 | V83: 0.097629 | W83: 0.097996 | X83: 0.098353 | Y83: 0.098706 | Z83: 0.099059 | AA83: 0.099416 | AB83: 0.09978 | AC83: 0.100155 | AD83: 0.100542 | AE83: 0.100945 | AF83: 0.101368 | AG83: 0.101811 | AH83: 0.102276 | AI83: 0.102763 | AJ83: 0.103271 | AK83: 0.103789 | AL83: 0.005
A84: battery electric vehicle | B84: Electricity | C84: Transportation Energy Use: Bus: School Bus: Electricity: High oil and gas supply | D84: 46-AEO2020.98.highogs-d112619a | E84: trillion Btu | F84: 0 | G84: 0 | H84: 0 | I84: 0 | J84: 0 | K84: 0 | L84: 0 | M84: 0 | N84: 0 | O84: 0 | P84: 0 | Q84: 0 | R84: 0 | S84: 0 | T84: 0 | U84: 0 | V84: 0 | W84: 0 | X84: 0 | Y84: 0 | Z84: 0 | AA84: 0 | AB84: 0 | AC84: 0 | AD84: 0 | AE84: 0 | AF84: 0 | AG84: 0 | AH84: 0 | AI84: 0 | AJ84: 0 | AK84: 0 | AL84: - -
A85: hydrogen vehicle | B85: Hydrogen | C85: Transportation Energy Use: Bus: School Bus: Hydrogen: High oil and gas supply | D85: 46-AEO2020.99.highogs-d112619a | E85: trillion Btu | F85: 0 | G85: 0 | H85: 0 | I85: 0 | J85: 0 | K85: 0 | L85: 0 | M85: 0 | N85: 0 | O85: 0 | P85: 0 | Q85: 0 | R85: 0 | S85: 0 | T85: 0 | U85: 0 | V85: 0 | W85: 0 | X85: 0 | Y85: 0 | Z85: 0 | AA85: 0 | AB85: 0 | AC85: 0 | AD85: 0 | AE85: 0 | AF85: 0 | AG85: 0 | AH85: 0 | AI85: 0 | AJ85: 0 | AK85: 0 | AL85: - -
B86: Rail Transportation | C86: Transportation Energy Use: Rail: High oil and gas supply | D86: 46-AEO2020.100.highogs-d112619a | E86: trillion Btu | F86: 49.124718 | G86: 50.002377 | H86: 50.829475 | I86: 51.513145 | J86: 52.17318 | K86: 52.82975 | L86: 53.460701 | M86: 54.088158 | N86: 54.687988 | O86: 55.315411 | P86: 55.939659 | Q86: 56.410965 | R86: 57.057266 | S86: 57.683121 | T86: 58.287663 | U86: 58.841217 | V86: 59.417301 | W86: 59.976952 | X86: 60.531982 | Y86: 61.099018 | Z86: 61.666862 | AA86: 62.233864 | AB86: 62.771835 | AC86: 63.311226 | AD86: 63.863609 | AE86: 64.421509 | AF86: 64.971481 | AG86: 65.567513 | AH86: 66.150879 | AI86: 66.765129 | AJ86: 67.348282 | AK86: 67.944778 | AL86: 0.011
B87: Intercity Rail | C87: Transportation Energy Use: Rail: Intercity Rail: High oil and gas supply | D87: 46-AEO2020.101.highogs-d112619a | E87: trillion Btu | F87: 10.422049 | G87: 10.531468 | H87: 10.640453 | I87: 10.74976 | J87: 10.859998 | K87: 10.968224 | L87: 11.071688 | M87: 11.174754 | N87: 11.276881 | O87: 11.376637 | P87: 11.475645 | Q87: 11.5741 | R87: 11.671005 | S87: 11.766532 | T87: 11.863631 | U87: 11.959969 | V87: 12.055451 | W87: 12.149978 | X87: 12.243448 | Y87: 12.335788 | Z87: 12.426949 | AA87: 12.516918 | AB87: 12.605728 | AC87: 12.693441 | AD87: 12.780126 | AE87: 12.865875 | AF87: 12.950798 | AG87: 13.035023 | AH87: 13.118643 | AI87: 13.201827 | AJ87: 13.284771 | AK87: 13.367389 | AL87: 0.008
B88: Electricity | C88: Transportation Energy Use: Rail: Intercity Rail: Electricity: High oil and gas supply | D88: 46-AEO2020.102.highogs-d112619a | E88: trillion Btu | F88: 1.718127 | G88: 1.736166 | H88: 1.754132 | I88: 1.772152 | J88: 1.790325 | K88: 1.808167 | L88: 1.825224 | M88: 1.842215 | N88: 1.859051 | O88: 1.875496 | P88: 1.891818 | Q88: 1.908049 | R88: 1.924025 | S88: 1.939773 | T88: 1.95578 | U88: 1.971662 | V88: 1.987402 | W88: 2.002985 | X88: 2.018394 | Y88: 2.033617 | Z88: 2.048645 | AA88: 2.063478 | AB88: 2.078118 | AC88: 2.092578 | AD88: 2.106869 | AE88: 2.121005 | AF88: 2.135005 | AG88: 2.14889 | AH88: 2.162675 | AI88: 2.176388 | AJ88: 2.190062 | AK88: 2.203682 | AL88: 0.008
B89: Diesel | C89: Transportation Energy Use: Rail: Intercity Rail: Diesel: High oil and gas supply | D89: 46-AEO2020.103.highogs-d112619a | E89: trillion Btu | F89: 8.703921 | G89: 8.795302 | H89: 8.886321 | I89: 8.977608 | J89: 9.069673 | K89: 9.160056 | L89: 9.246464 | M89: 9.33254 | N89: 9.41783 | O89: 9.501142 | P89: 9.583827 | Q89: 9.666051 | R89: 9.746981 | S89: 9.826759 | T89: 9.907851 | U89: 9.988307 | V89: 10.068049 | W89: 10.146993 | X89: 10.225054 | Y89: 10.302171 | Z89: 10.378304 | AA89: 10.453441 | AB89: 10.52761 | AC89: 10.600863 | AD89: 10.673257 | AE89: 10.74487 | AF89: 10.815793 | AG89: 10.886133 | AH89: 10.955968 | AI89: 11.025439 | AJ89: 11.094709 | AK89: 11.163707 | AL89: 0.008
B90: Compressed Natural Gas | C90: Transportation Energy Use: Rail: Intercity Rail: CNG: High oil and gas supply | D90: 46-AEO2020.104.highogs-d112619a | E90: trillion Btu | F90: 0 | G90: 0 | H90: 0 | I90: 0 | J90: 0 | K90: 0 | L90: 0 | M90: 0 | N90: 0 | O90: 0 | P90: 0 | Q90: 0 | R90: 0 | S90: 0 | T90: 0 | U90: 0 | V90: 0 | W90: 0 | X90: 0 | Y90: 0 | Z90: 0 | AA90: 0 | AB90: 0 | AC90: 0 | AD90: 0 | AE90: 0 | AF90: 0 | AG90: 0 | AH90: 0 | AI90: 0 | AJ90: 0 | AK90: 0 | AL90: - -
B91: Liquefied Natural Gas | C91: Transportation Energy Use: Rail: Intercity Rail: LNG: High oil and gas supply | D91: 46-AEO2020.105.highogs-d112619a | E91: trillion Btu | F91: 0 | G91: 0 | H91: 0 | I91: 0 | J91: 0 | K91: 0 | L91: 0 | M91: 0 | N91: 0 | O91: 0 | P91: 0 | Q91: 0 | R91: 0 | S91: 0 | T91: 0 | U91: 0 | V91: 0 | W91: 0 | X91: 0 | Y91: 0 | Z91: 0 | AA91: 0 | AB91: 0 | AC91: 0 | AD91: 0 | AE91: 0 | AF91: 0 | AG91: 0 | AH91: 0 | AI91: 0 | AJ91: 0 | AK91: 0 | AL91: - -
B92: Transit Rail | C92: Transportation Energy Use: Rail: Transit Rail: High oil and gas supply | D92: 46-AEO2020.106.highogs-d112619a | E92: trillion Btu | F92: 17.189331 | G92: 17.388334 | H92: 17.585045 | I92: 17.759405 | J92: 17.923174 | K92: 18.088472 | L92: 18.245422 | M92: 18.398161 | N92: 18.547804 | O92: 18.698662 | P92: 18.8507 | Q92: 18.974638 | R92: 19.112001 | S92: 19.245508 | T92: 19.375572 | U92: 19.495077 | V92: 19.609205 | W92: 19.717878 | X92: 19.822212 | Y92: 19.920149 | Z92: 20.010719 | AA92: 20.095358 | AB92: 20.166985 | AC92: 20.231947 | AD92: 20.293125 | AE92: 20.351675 | AF92: 20.412086 | AG92: 20.483519 | AH92: 20.565197 | AI92: 20.663223 | AJ92: 20.777836 | AK92: 20.911673 | AL92: 0.006
B93: Electricity | C93: Transportation Energy Use: Rail: Transit Rail: Electricity: High oil and gas supply | D93: 46-AEO2020.107.highogs-d112619a | E93: trillion Btu | F93: 17.189331 | G93: 17.388334 | H93: 17.585045 | I93: 17.759405 | J93: 17.923174 | K93: 18.088472 | L93: 18.245422 | M93: 18.398161 | N93: 18.547804 | O93: 18.698662 | P93: 18.8507 | Q93: 18.974638 | R93: 19.112001 | S93: 19.245508 | T93: 19.375572 | U93: 19.495077 | V93: 19.609205 | W93: 19.717878 | X93: 19.822212 | Y93: 19.920149 | Z93: 20.010719 | AA93: 20.095358 | AB93: 20.166985 | AC93: 20.231947 | AD93: 20.293125 | AE93: 20.351675 | AF93: 20.412086 | AG93: 20.483519 | AH93: 20.565197 | AI93: 20.663223 | AJ93: 20.777836 | AK93: 20.911673 | AL93: 0.006
B94: Commuter Rail | C94: Transportation Energy Use: Rail: Commuter Rail: High oil and gas supply | D94: 46-AEO2020.108.highogs-d112619a | E94: trillion Btu | F94: 21.513336 | G94: 22.082573 | H94: 22.603981 | I94: 23.003981 | J94: 23.390005 | K94: 23.773052 | L94: 24.143589 | M94: 24.515247 | N94: 24.8633 | O94: 25.240112 | P94: 25.613314 | Q94: 25.862228 | R94: 26.274261 | S94: 26.671078 | T94: 27.048458 | U94: 27.386173 | V94: 27.752644 | W94: 28.109095 | X94: 28.466328 | Y94: 28.843084 | Z94: 29.229195 | AA94: 29.62159 | AB94: 29.999123 | AC94: 30.385841 | AD94: 30.790356 | AE94: 31.203959 | AF94: 31.608601 | AG94: 32.048973 | AH94: 32.467041 | AI94: 32.900078 | AJ94: 33.285671 | AK94: 33.665718 | AL94: 0.015
B95: Electricity | C95: Transportation Energy Use: Rail: Commuter Rail: Electricity: High oil and gas supply | D95: 46-AEO2020.109.highogs-d112619a | E95: trillion Btu | F95: 6.116357 | G95: 6.22413 | H95: 6.33061 | I95: 6.413865 | J95: 6.488579 | K95: 6.566199 | L95: 6.643357 | M95: 6.720106 | N95: 6.794744 | O95: 6.873001 | P95: 6.95286 | Q95: 7.031975 | R95: 7.116939 | S95: 7.201175 | T95: 7.284187 | U95: 7.356703 | V95: 7.43011 | W95: 7.504315 | X95: 7.579061 | Y95: 7.657236 | Z95: 7.73758 | AA95: 7.819145 | AB95: 7.897911 | AC95: 7.978196 | AD95: 8.058715 | AE95: 8.140158 | AF95: 8.221079 | AG95: 8.305956 | AH95: 8.388528 | AI95: 8.47293 | AJ95: 8.548101 | AK95: 8.618113 | AL95: 0.011
B96: Diesel | C96: Transportation Energy Use: Rail: Commuter Rail: Diesel: High oil and gas supply | D96: 46-AEO2020.110.highogs-d112619a | E96: trillion Btu | F96: 15.39698 | G96: 15.858444 | H96: 16.273371 | I96: 16.590117 | J96: 16.901426 | K96: 17.206854 | L96: 17.500231 | M96: 17.795141 | N96: 18.068556 | O96: 18.367111 | P96: 18.660454 | Q96: 18.830254 | R96: 19.157322 | S96: 19.469904 | T96: 19.764271 | U96: 20.02947 | V96: 20.322533 | W96: 20.60478 | X96: 20.887266 | Y96: 21.185848 | Z96: 21.491615 | AA96: 21.802444 | AB96: 22.101212 | AC96: 22.407644 | AD96: 22.731642 | AE96: 23.063801 | AF96: 23.387522 | AG96: 23.743019 | AH96: 24.078514 | AI96: 24.427147 | AJ96: 24.73757 | AK96: 25.047604 | AL96: 0.016
B97: Compressed Natural Gas | C97: Transportation Energy Use: Rail: Commuter Rail: CNG: High oil and gas supply | D97: 46-AEO2020.111.highogs-d112619a | E97: trillion Btu | F97: 0 | G97: 0 | H97: 0 | I97: 0 | J97: 0 | K97: 0 | L97: 0 | M97: 0 | N97: 0 | O97: 0 | P97: 0 | Q97: 0 | R97: 0 | S97: 0 | T97: 0 | U97: 0 | V97: 0 | W97: 0 | X97: 0 | Y97: 0 | Z97: 0 | AA97: 0 | AB97: 0 | AC97: 0 | AD97: 0 | AE97: 0 | AF97: 0 | AG97: 0 | AH97: 0 | AI97: 0 | AJ97: 0 | AK97: 0 | AL97: - -
B98: Liquefied Natural Gas | C98: Transportation Energy Use: Rail: Commuter Rail: LNG: High oil and gas supply | D98: 46-AEO2020.112.highogs-d112619a | E98: trillion Btu | F98: 0 | G98: 0 | H98: 0 | I98: 0 | J98: 0 | K98: 0 | L98: 0 | M98: 0 | N98: 0 | O98: 0 | P98: 0 | Q98: 0 | R98: 0 | S98: 0 | T98: 0 | U98: 0 | V98: 0 | W98: 0 | X98: 0 | Y98: 0 | Z98: 0 | AA98: 0 | AB98: 0 | AC98: 0 | AD98: 0 | AE98: 0 | AF98: 0 | AG98: 0 | AH98: 0 | AI98: 0 | AJ98: 0 | AK98: 0 | AL98: - -
B99: Recreational Boats | C99: Transportation Energy Use: Recreation Boats: High oil and gas supply | D99: 46-AEO2020.114.highogs-d112619a | E99: trillion Btu | F99: 245.48737 | G99: 246.24731 | H99: 246.89113 | I99: 247.22803 | J99: 247.40088 | K99: 247.561 | L99: 247.74658 | M99: 247.87222 | N99: 247.94768 | O99: 248.03426 | P99: 248.11905 | Q99: 248.12834 | R99: 248.11883 | S99: 248.07858 | T99: 247.94284 | U99: 247.70436 | V99: 247.38197 | W99: 247.05051 | X99: 246.67229 | Y99: 246.27057 | Z99: 245.84454 | AA99: 245.36371 | AB99: 244.83713 | AC99: 244.24297 | AD99: 243.63638 | AE99: 243.03659 | AF99: 242.46649 | AG99: 241.926 | AH99: 241.38654 | AI99: 240.85849 | AJ99: 240.31628 | AK99: 239.76006 | AL99: -0.001
A100: gasoline vehicle | B100: Gasoline | C100: Transportation Energy Use: Recreation Boats: Motor Gasoline: High oil and gas supply | D100: 46-AEO2020.115.highogs-d112619a | E100: trillion Btu | F100: 190.41097 | G100: 189.7621 | H100: 189.07871 | I100: 188.3589 | J100: 187.59949 | K100: 186.79903 | L100: 185.95711 | M100: 185.07472 | N100: 184.14857 | O100: 183.17694 | P100: 182.16502 | Q100: 181.1068 | R100: 179.99432 | S100: 178.83392 | T100: 177.62646 | U100: 176.37314 | V100: 175.07529 | W100: 173.73459 | X100: 172.35272 | Y100: 170.93141 | Z100: 169.47247 | AA100: 167.97778 | AB100: 166.44934 | AC100: 164.88917 | AD100: 163.29942 | AE100: 161.68245 | AF100: 160.04063 | AG100: 158.37592 | AH100: 156.68977 | AI100: 154.98407 | AJ100: 153.26039 | AK100: 151.51515 | AL100: -0.007
A101: diesel vehicle | B101: Distillate Fuel Oil (diesel) | C101: Transportation Energy Use: Recreation Boats: Distillate Fuel Oil: High oil and gas supply | D101: 46-AEO2020.116.highogs-d112619a | E101: trillion Btu | F101: 55.076408 | G101: 56.485214 | H101: 57.812428 | I101: 58.869122 | J101: 59.801392 | K101: 60.761978 | L101: 61.789467 | M101: 62.797501 | N101: 63.799099 | O101: 64.857315 | P101: 65.954018 | Q101: 67.021545 | R101: 68.124504 | S101: 69.244659 | T101: 70.316368 | U101: 71.331223 | V101: 72.306686 | W101: 73.31591 | X101: 74.319565 | Y101: 75.339149 | Z101: 76.372078 | AA101: 77.385933 | AB101: 78.387779 | AC101: 79.35379 | AD101: 80.336967 | AE101: 81.354149 | AF101: 82.425865 | AG101: 83.550072 | AH101: 84.696762 | AI101: 85.874428 | AJ101: 87.055901 | AK101: 88.244904 | AL101: 0.015
B102: Lubricants | C102: Transportation Energy Use: Lubricants: High oil and gas supply | D102: 46-AEO2020.118.highogs-d112619a | E102: trillion Btu | F102: 131.4688 | G102: 130.9978 | H102: 130.61691 | I102: 130.16556 | J102: 129.71597 | K102: 129.23587 | L102: 128.71664 | M102: 128.21002 | N102: 127.73817 | O102: 127.32877 | P102: 126.99723 | Q102: 126.67632 | R102: 126.39497 | S102: 126.14228 | T102: 125.89642 | U102: 125.70426 | V102: 125.55006 | W102: 125.49034 | X102: 125.46355 | Y102: 125.46944 | Z102: 125.51205 | AA102: 125.52898 | AB102: 125.53334 | AC102: 125.61249 | AD102: 125.6669 | AE102: 125.76542 | AF102: 125.93991 | AG102: 126.14378 | AH102: 126.36053 | AI102: 126.62708 | AJ102: 126.86329 | AK102: 127.07791 | AL102: -0.001
B103: Pipeline Fuel Natural Gas | C103: Transportation Energy Use: Pipeline Fuel Natural Gas: High oil and gas supply | D103: 46-AEO2020.119.highogs-d112619a | E103: trillion Btu | F103: 671.92114 | G103: 667.21631 | H103: 701.37659 | I103: 713.80554 | J103: 720.88531 | K103: 735.13074 | L103: 751.8468 | M103: 760.75671 | N103: 755.91388 | O103: 756.47766 | P103: 763.30188 | Q103: 765.38464 | R103: 772.58118 | S103: 775.92578 | T103: 776.05963 | U103: 777.57422 | V103: 780.55438 | W103: 791.487 | X103: 796.76007 | Y103: 804.71332 | Z103: 815.8562 | AA103: 823.09863 | AB103: 829.39862 | AC103: 844.2193 | AD103: 853.06616 | AE103: 861.44495 | AF103: 869.52753 | AG103: 879.44995 | AH103: 887.93481 | AI103: 897.92761 | AJ103: 905.13617 | AK103: 912.4433 | AL103: 0.01
B104: Total Consumption | C104: Transportation Energy Use: Total Use: High oil and gas supply | D104: 46-AEO2020.121.highogs-d112619a | E104: trillion Btu | F104: 28112.633 | G104: 28230.043 | H104: 28207.84 | I104: 28010.221 | J104: 27786.57 | K104: 27464.219 | L104: 27153.484 | M104: 26879.91 | N104: 26657.34 | O104: 26447.17 | P104: 26242.152 | Q104: 26066.857 | R104: 25948.875 | S104: 25801.398 | T104: 25698.723 | U104: 25576.391 | V104: 25466.162 | W104: 25408.643 | X104: 25370.514 | Y104: 25336.406 | Z104: 25339.396 | AA104: 25369.297 | AB104: 25391.189 | AC104: 25453.395 | AD104: 25523.727 | AE104: 25622.963 | AF104: 25750.77 | AG104: 25928.531 | AH104: 26092.914 | AI104: 26299.697 | AJ104: 26523.189 | AK104: 26762.32 | AL104: -0.002

Sheet AEO 37
A1: Transportation Energy Use (Case High oil and gas supply)
A2: https://www.eia.gov/outlooks/aeo/data/browser/#/?id=47-AEO2020&region=0-0&cases=highogs&start=2018&end=2050&f=A&linechart=highogs-d112619a.4-47-AEO2020~highogs-d112619a.5-47-AEO2020~highogs-d112619a.6-47-AEO2020~highogs-d112619a.9-47-AEO2020~highogs-d112619a.10-47-AEO2020~highogs-d112619a.11-47-AEO2020~highogs-d112619a.12-47-AEO2020~highogs-d112619a.13-47-AEO2020~highogs-d112619a.14-47-AEO2020~highogs-d112619a.15-47-AEO2020~highogs-d112619a.16-47-AEO2020~highogs-d112619a.17-47-AEO2020~highogs-d112619a.18-47-AEO2020~highogs-d112619a.19-47-AEO2020~highogs-d112619a.20-47-AEO2020~highogs-d112619a.21-47-AEO2020~highogs-d112619a.22-47-AEO2020~highogs-d112619a.23-47-AEO2020~highogs-d112619a.28-47-AEO2020~highogs-d112619a.29-47-AEO2020~highogs-d112619a.30-47-AEO2020~highogs-d112619a.31-47-AEO2020~highogs-d112619a.32-47-AEO2020~highogs-d112619a.33-47-AEO2020~highogs-d112619a.34-47-AEO2020~highogs-d112619a.35-47-AEO2020~highogs-d112619a.25-47-AEO2020&ctype=linechart&sourcekey=0
A3: 12:40:30 GMT-0700 (Pacific Daylight Time)
A4: Source: U.S. Energy Information Administration
A5: Year | B5: Light-Duty Vehicles: Conventional: Gasoline trillion Btu | C5: Light-Duty Vehicles: Conventional: TDI Diesel trillion Btu | D5: Light-Duty Vehicles: Conventional: Total trillion Btu | E5: Light-Duty Vehicles: Alternative-Fuel: Ethanol Flex trillion Btu | F5: Light-Duty Vehicles: Alternative-Fuel: 100 Mile Electric Vehicle trillion Btu | G5: Light-Duty Vehicles: Alternative-Fuel: 200 Mile Electric Vehicle trillion Btu | H5: Light-Duty Vehicles: Alternative-Fuel: 300 Mile Electric Vehicle trillion Btu | I5: Light-Duty Vehicles: Alternative-Fuel: Plug-in 10 Gasoline Hybrid trillion Btu | J5: Light-Duty Vehicles: Alternative-Fuel: Plug-in 40 Gasoline Hybrid trillion Btu | K5: Light-Duty Vehicles: Alternative-Fuel: Electric-Diesel Hybrid trillion Btu | L5: Light-Duty Vehicles: Alternative-Fuel: Electric-Gasoline Hybrid trillion Btu | M5: Light-Duty Vehicles: Alternative-Fuel: Natural Gas ICE trillion Btu | N5: Light-Duty Vehicles: Alternative-Fuel: Natural Gas Bi-fuel trillion Btu | O5: Light-Duty Vehicles: Alternative-Fuel: Propane ICE trillion Btu | P5: Light-Duty Vehicles: Alternative-Fuel: Propane Bi-fuel trillion Btu | Q5: Light-Duty Vehicles: Alternative-Fuel: Fuel Cell Methanol trillion Btu | R5: Light-Duty Vehicles: Alternative-Fuel: Fuel Cell Hydrogen trillion Btu | S5: Light-Duty Vehicles: Alternative-Fuel: Total trillion Btu | T5: Light-Duty Vehicle: Motor Gasoline trillion Btu | U5: Light-Duty Vehicle: Distillate Fuel Oil trillion Btu | V5: Light-Duty Vehicle: Methanol trillion Btu | W5: Light-Duty Vehicle: Ethanol trillion Btu | X5: Light-Duty Vehicle: Natural Gas trillion Btu | Y5: Light-Duty Vehicle: Propane trillion Btu | Z5: Light-Duty Vehicle: Electricity trillion Btu | AA5: Light-Duty Vehicle: Hydrogen trillion Btu | AB5: Light-Duty Vehicles: Total trillion Btu
A6: 2050 | B6: 10746.833 | C6: 98.750359 | D6: 10845.583 | E6: 622.72241 | F6: 6.295012 | G6: 147.57886 | H6: 196.32095 | I6: 16.851854 | J6: 59.397636 | K6: 9.693973 | L6: 423.98621 | M6: 0.76933 | N6: 2.796045 | O6: 1.103926 | P6: 1.184343 | Q6: 0 | R6: 1.084782 | S6: 1489.7854 | T6: 11838.642 | U6: 108.44432 | V6: 0 | W6: 8.098272 | X6: 2.692575 | Y6: 1.589708 | Z6: 386.20929 | AA6: 1.084782 | AB6: 12335.368
A7: 2049 | B7: 10691.326 | C7: 98.087463 | D7: 10789.414 | E7: 623.21454 | F7: 6.176499 | G7: 141.028 | H7: 188.78819 | I7: 15.38822 | J7: 58.134945 | K7: 9.341089 | L7: 413.26028 | M7: 0.760676 | N7: 2.773635 | O7: 1.074083 | P7: 1.177784 | Q7: 0 | R7: 1.032795 | S7: 1462.1509 | T7: 11771.21 | U7: 107.42856 | V7: 0 | W7: 7.830171 | X7: 2.668769 | Y7: 1.562022 | Z7: 371.08896 | AA7: 1.032795 | AB7: 12251.564
A8: 2048 | B8: 10645.742 | C8: 97.468437 | D8: 10743.211 | E8: 624.57318 | F8: 6.056271 | G8: 134.48697 | H8: 181.34299 | I8: 14.146991 | J8: 56.804352 | K8: 8.960178 | L8: 402.84561 | M8: 0.752546 | N8: 2.752309 | O8: 1.045976 | P8: 1.171856 | Q8: 0 | R8: 0.982053 | S8: 1435.9214 | T8: 11714.549 | U8: 106.4286 | V8: 0 | W8: 8.051833 | X8: 2.646219 | Y8: 1.526954 | Z8: 356.05942 | AA8: 0.982053 | AB8: 12179.133
A9: 2047 | B9: 10610.202 | C9: 96.976067 | D9: 10707.178 | E9: 626.75409 | F9: 5.933622 | G9: 128.03531 | H9: 173.95609 | I9: 13.099334 | J9: 55.435894 | K9: 8.548295 | L9: 392.77753 | M9: 0.745002 | N9: 2.731582 | O9: 1.019843 | P9: 1.166222 | Q9: 0 | R9: 0.932552 | S9: 1411.1351 | T9: 11669.203 | U9: 105.52435 | V9: 0 | W9: 8.313334 | X9: 2.624655 | Y9: 1.499175 | Z9: 341.17658 | AA9: 0.932552 | AB9: 12118.312
A10: 2046 | B10: 10589.597 | C10: 96.61705 | D10: 10686.214 | E10: 630.1073 | F10: 5.814386 | G10: 121.65962 | H10: 166.76569 | I10: 12.219675 | J10: 54.02599 | K10: 8.112716 | L10: 383.18817 | M10: 0.738763 | N10: 2.714561 | O10: 0.996239 | P10: 1.162311 | Q10: 0 | R10: 0.884676 | S10: 1388.39 | T10: 11639.25 | U10: 104.72976 | V10: 0 | W10: 9.906834 | X10: 2.60693 | Y10: 1.468693 | Z10: 326.57141 | AA10: 0.884676 | AB10: 12074.604
A11: 2045 | B11: 10581.096 | C11: 96.467308 | D11: 10677.563 | E11: 634.43903 | F11: 5.303064 | G11: 115.34772 | H11: 159.66579 | I11: 11.461509 | J11: 52.58009 | K11: 7.652514 | L11: 373.95477 | M11: 0.733585 | N11: 2.699871 | O11: 0.974783 | P11: 1.159484 | Q11: 0 | R11: 0.837969 | S11: 1366.8102 | T11: 11623.285 | U11: 104.11983 | V11: 0 | W11: 11.035002 | X11: 2.591878 | Y11: 1.447421 | Z11: 311.72357 | AA11: 0.837969 | AB11: 12044.374
A12: 2044 | B12: 10589.736 | C12: 96.456848 | D12: 10686.193 | E12: 640.0766 | F12: 5.097292 | G12: 109.08507 | H12: 152.78989 | I12: 10.843517 | J12: 51.101543 | K12: 7.17487 | L12: 365.15018 | M12: 0.729554 | N12: 2.687979 | O12: 0.95551 | P12: 1.158005 | Q12: 0 | R12: 0.792258 | S12: 1347.6423 | T12: 11624.686 | U12: 103.63173 | V12: 0 | W12: 13.793528 | X12: 2.579886 | Y12: 1.420997 | Z12: 297.4516 | AA12: 0.792258 | AB12: 12033.836
A13: 2043 | B13: 10609.438 | C13: 96.589638 | D13: 10706.027 | E13: 646.67377 | F13: 4.93377 | G13: 102.84852 | H13: 145.88599 | I13: 9.528104 | J13: 49.590675 | K13: 6.679934 | L13: 356.5686 | M13: 0.726395 | N13: 2.679425 | O13: 0.938204 | P13: 1.158017 | Q13: 0 | R13: 0.746228 | S13: 1328.9576 | T13: 11640.296 | U13: 103.26958 | V13: 0 | W13: 13.99791 | X13: 2.571058 | Y13: 1.405051 | Z13: 283.08017 | AA13: 0.746228 | AB13: 12034.985
A14: 2042 | B14: 10639.227 | C14: 96.245705 | D14: 10735.473 | E14: 654.24524 | F14: 4.775503 | G14: 96.260986 | H14: 139.08374 | I14: 9.028165 | J14: 48.027321 | K14: 6.16527 | L14: 348.05255 | M14: 0.7237 | N14: 2.67291 | O14: 0.922127 | P14: 1.159069 | Q14: 0 | R14: 0.696295 | S14: 1311.8129 | T14: 11667.807 | U14: 102.41099 | V14: 0 | W14: 14.075607 | X14: 2.564096 | Y14: 1.393089 | Z14: 268.569 | AA14: 0.696295 | AB14: 12047.285
A15: 2041 | B15: 10679.16 | C15: 96.276489 | D15: 10775.437 | E15: 662.83624 | F15: 4.598731 | G15: 89.732094 | H15: 132.31709 | I15: 8.48032 | J15: 46.391159 | K15: 5.632419 | L15: 339.53033 | M15: 0.725503 | N15: 2.666555 | O15: 0.907049 | P15: 1.160482 | Q15: 0 | R15: 0.648974 | S15: 1295.6271 | T15: 11704.455 | U15: 101.90889 | V15: 0 | W15: 16.113234 | X15: 2.561738 | Y15: 1.377485 | Z15: 254.06908 | AA15: 0.648974 | AB15: 12071.063
A16: 2040 | B16: 10731.035 | C16: 96.203194 | D16: 10827.238 | E16: 672.70136 | F16: 4.405731 | G16: 83.209732 | H16: 125.60748 | I16: 8.130892 | J16: 44.710686 | K16: 5.091609 | L16: 331.02701 | M16: 0.725222 | N16: 2.663973 | O16: 0.896397 | P16: 1.164861 | Q16: 0 | R16: 0.599215 | S16: 1280.9342 | T16: 11755.599 | U16: 101.29481 | V16: 0 | W16: 17.040964 | X16: 2.559894 | Y16: 1.363592 | Z16: 239.61594 | AA16: 0.599215 | AB16: 12108.173
A17: 2039 | B17: 10786.763 | C17: 95.282822 | D17: 10882.046 | E17: 683.50763 | F17: 4.164013 | G17: 76.702011 | H17: 118.8706 | I17: 7.852118 | J17: 42.951851 | K17: 4.546561 | L17: 322.35007 | M17: 0.730395 | N17: 2.671255 | O17: 0.88884 | P17: 1.187112 | Q17: 0 | R17: 0.56031 | S17: 1266.9828 | T17: 11810.42 | U17: 99.829384 | V17: 0 | W17: 18.944868 | X17: 2.570287 | Y17: 1.36307 | Z17: 225.06065 | AA17: 0.56031 | AB17: 12149.028
... A37: 2019 | B37: 13649.671 | C37: 63.969223 | D37: 13713.64 | E37: 1358.2336 | F37: 3.503986 | G37: 4.82556 | H37: 6.701128 | I37: 11.812346 | J37: 10.252526 | K37: 0 | L37: 181.25551 | M37: 2.190075 | N37: 5.231336 | O37: 1.301297 | P37: 5.284471 | Q37: 0 | R37: 0.244584 | S37: 1590.8365 | T37: 15199.481 | U37: 63.969234 | V37: 0 | W37: 17.035625 | X37: 5.73929 | Y37: 3.780961 | Z37: 22.194469 | AA37: 0.244584 | AB37: 15304.477
B39: gasoline vehicle | C39: diesel vehicle | E39: gasoline vehicle | F39: battery electric vehicle | G39: battery electric vehicle | H39: battery electric vehicle | I39: plugin hybrid vehicle | J39: plugin hybrid vehicle | K39: diesel vehicle | L39: gasoline vehicle | M39: natural gas vehicle | N39: natural gas vehicle | O39: LPG vehicle | P39: LPG vehicle | Q39: hydrogen vehicle | R39: hydrogen vehicle

Sheet AEO 38
A1: Light-Duty Vehicle Stock (Case High oil and gas supply)
A2: https://www.eia.gov/outlooks/aeo/data/browser/#/?id=49-AEO2020&region=0-0&cases=highogs&start=2018&end=2050&f=A&linechart=highogs-d112619a.4-49-AEO2020~highogs-d112619a.5-49-AEO2020~highogs-d112619a.6-49-AEO2020~highogs-d112619a.9-49-AEO2020~highogs-d112619a.10-49-AEO2020~highogs-d112619a.11-49-AEO2020~highogs-d112619a.12-49-AEO2020~highogs-d112619a.13-49-AEO2020~highogs-d112619a.14-49-AEO2020~highogs-d112619a.15-49-AEO2020~highogs-d112619a.16-49-AEO2020~highogs-d112619a.17-49-AEO2020~highogs-d112619a.18-49-AEO2020~highogs-d112619a.19-49-AEO2020~highogs-d112619a.20-49-AEO2020~highogs-d112619a.21-49-AEO2020~highogs-d112619a.22-49-AEO2020~highogs-d112619a.23-49-AEO2020~highogs-d112619a.25-49-AEO2020~highogs-d112619a.29-49-AEO2020~highogs-d112619a.30-49-AEO2020~highogs-d112619a.31-49-AEO2020~highogs-d112619a.34-49-AEO2020~highogs-d112619a.35-49-AEO2020~highogs-d112619a.36-49-AEO2020~highogs-d112619a.37-49-AEO2020~highogs-d112619a.38-49-AEO2020~highogs-d112619a.39-49-AEO2020~highogs-d112619a.40-49-AEO2020~highogs-d112619a.41-49-AEO2020~highogs-d112619a.42-49-AEO2020~highogs-d112619a.43-49-AEO2020~highogs-d112619a.44-49-AEO2020~highogs-d112619a.45-49-AEO2020~highogs-d112619a.46-49-AEO2020~highogs-d112619a.47-49-AEO2020~highogs-d112619a.48-49-AEO2020~highogs-d112619a.50-49-AEO2020~highogs-d112619a.52-49-AEO2020&ctype=linechart&sourcekey=0
A3: 15:25:04 GMT-0800 (Pacific Standard Time)
A4: Light-Duty Vehicle Sales (Case High oil and gas supply Region United States)
A5: https://www.eia.gov/outlooks/aeo/data/browser/#/?id=48-AEO2020&region=1-0&cases=highogs&start=2018&end=2050&f=A&linechart=~~~highogs-d112619a.4-48-AEO2020.1-0~highogs-d112619a.5-48-AEO2020.1-0~highogs-d112619a.6-48-AEO2020.1-0~highogs-d112619a.9-48-AEO2020.1-0~highogs-d112619a.10-48-AEO2020.1-0~highogs-d112619a.11-48-AEO2020.1-0~highogs-d112619a.12-48-AEO2020.1-0~highogs-d112619a.13-48-AEO2020.1-0~highogs-d112619a.14-48-AEO2020.1-0~highogs-d112619a.15-48-AEO2020.1-0~highogs-d112619a.16-48-AEO2020.1-0~highogs-d112619a.17-48-AEO2020.1-0~highogs-d112619a.18-48-AEO2020.1-0~highogs-d112619a.19-48-AEO2020.1-0~highogs-d112619a.20-48-AEO2020.1-0~highogs-d112619a.21-48-AEO2020.1-0~highogs-d112619a.22-48-AEO2020.1-0~highogs-d112619a.23-48-AEO2020.1-0~highogs-d112619a.30-48-AEO2020.1-0~highogs-d112619a.31-48-AEO2020.1-0~highogs-d112619a.32-48-AEO2020.1-0~highogs-d112619a.35-48-AEO2020.1-0~highogs-d112619a.36-48-AEO2020.1-0~highogs-d112619a.37-48-AEO2020.1-0~highogs-d112619a.38-48-AEO2020.1-0~highogs-d112619a.39-48-AEO2020.1-0~highogs-d112619a.40-48-AEO2020.1-0~highogs-d112619a.41-48-AEO2020.1-0~highogs-d112619a.42-48-AEO2020.1-0~highogs-d112619a.43-48-AEO2020.1-0~highogs-d112619a.44-48-AEO2020.1-0~highogs-d112619a.45-48-AEO2020.1-0~highogs-d112619a.46-48-AEO2020.1-0~highogs-d112619a.47-48-AEO2020.1-0~highogs-d112619a.48-48-AEO2020.1-0~highogs-d112619a.49-48-AEO2020.1-0&sourcekey=0
A6: 10:42:29 GMT-0800 (Pacific Standard Time)
A7: Source: U.S. Energy Information Administration
A8: Year | B8: Conventional Cars: Gasoline thousands | C8: Conventional Cars: TDI Diesel thousands | D8: Conventional Cars: Total thousands | E8: Alternative-Fuel Cars: Ethanol-Flex Fuel ICE thousands | F8: Alternative-Fuel Cars: 100 Mile Electric Vehicle thousands | G8: Alternative-Fuel Cars: 200 Mile Electric Vehicle thousands | H8: Alternative-Fuel Cars: 300 Mile Electric Vehicle thousands | I8: Alternative-Fuel Cars: Plug-in 10 Gasoline Hybrid thousands | J8: Alternative-Fuel Cars: Plug-in 40 Gasoline Hybrid thousands | K8: Alternative-Fuel Cars: Electric-Diesel Hybrid thousands | L8: Alternative-Fuel Cars: Electric-Gasoline Hybrid thousands | M8: Alternative-Fuel Cars: Natural Gas ICE thousands | N8: Alternative-Fuel Cars: Natural Gas Bi-fuel thousands | O8: Alternative-Fuel Cars: Propane thousands | P8: Alternative-Fuel Cars: Fuel Cell Methanol thousands | Q8: Alternative-Fuel cars: Fuel Cell Hydrogen thousands | R8: Alternative-Fuel Cars: Total thousands | S8: Conventional Light Trucks: Gasoline thousands | T8: Conventional Light Trucks: TDI Diesel thousands | U8: Conventional Light Trucks: Total thousands | V8: Alternative-Fuel Light Trucks: Ethanol-Flex Fuel ICE thousands | W8: Alternative-Fuel Light Trucks: 100 Mile Electric Vehicle thousands | X8: Alternative-Fuel Light Trucks: 200 Mile Electric Vehicle thousands | Y8: Alternative-Fuel Light Trucks: 300 Mile Electric Vehicle thousands | Z8: Alternative-Fuel Light Trucks: Plug-in 10 Gasoline Hybrid thousands | AA8: Alternative-Fuel Light Trucks: Plug-in 40 Gasoline Hybrid thousands | AB8: Alternative-Fuel Light Trucks: Electric-Diesel Hybrid thousands | AC8: Alternative-Fuel Light Trucks: Electric-Gasoline Hybrid thousands | AD8: Alternative-Fuel Light Trucks: Natural Gas ICE thousands | AE8: Alternative-Fuel Light Trucks: Natural Gas Bi-fuel thousands | AF8: Alternative-Fuel Light Trucks: Propane ICE thousands | AG8: Alternative-Fuel Light Trucks: Propane Bi-fuel thousands | AH8: Alternative-Fuel Light Trucks: Fuel Cell Methanol thousands | AI8: Alternative-Fuel Light Trucks: Fuel Cell Hydrogen thousands | AJ8: Alternative-Fuel Light Trucks: Total thousands
A9: 2050 | B9: 7356.5649 | C9: 20.660522 | D9: 7377.2256 | E9: 145.37088 | F9: 7.407793 | G9: 604.6922 | H9: 1030.8519 | I9: 10.356289 | J9: 100.82558 | K9: 30.184778 | L9: 288.715 | M9: 1.090307 | N9: 4.468718 | O9: 1.074683 | P9: 0 | Q9: 2.344098 | R9: 2228.1936 | S9: 6124.3896 | T9: 109.43921 | U9: 6233.8291 | V9: 526.28052 | W9: 5.123567 | X9: 188.37894 | Y9: 15.889852 | Z9: 46.682095 | AA9: 65.127541 | AB9: 0.373823 | AC9: 575.94665 | AD9: 1.025713 | AE9: 4.9073 | AF9: 1.261964 | AG9: 3.160007 | AH9: 0 | AI9: 0.355968 | AJ9: 1434.5142
A10: 2049 | B10: 7327.9961 | C10: 20.488869 | D10: 7348.4849 | E10: 144.60481 | F10: 7.327712 | G10: 589.11469 | H10: 1003.5169 | I10: 10.277878 | J10: 99.893257 | K10: 30.02804 | L10: 287.26334 | M10: 1.078121 | N10: 4.430942 | O10: 1.066106 | P10: 0 | Q10: 2.259941 | R10: 2181.6565 | S10: 6104.6177 | T10: 109.70412 | U10: 6214.3218 | V10: 524.51038 | W10: 5.00571 | X10: 184.81308 | Y10: 15.771797 | Z10: 40.49041 | AA10: 65.721283 | AB10: 0.367604 | AC10: 562.44232 | AD10: 1.019462 | AE10: 4.878758 | AF10: 1.237593 | AG10: 3.141734 | AH10: 0 | AI10: 0.34209 | AJ10: 1409.7422
A11: 2048 | B11: 7282.6748 | C11: 20.265898 | D11: 7302.9409 | E11: 143.53613 | F11: 7.211104 | G11: 569.2898 | H11: 979.37488 | I11: 10.166741 | J11: 97.972275 | K11: 29.834106 | L11: 284.47516 | M11: 1.066203 | N11: 4.384568 | O11: 1.055446 | P11: 0 | Q11: 2.178296 | R11: 2131.3245 | S11: 6107.9751 | T11: 108.74126 | U11: 6216.7163 | V11: 524.53699 | W11: 4.91066 | X11: 181.00775 | Y11: 15.697524 | Z11: 35.226364 | AA11: 66.180252 | AB11: 0.36144 | AC11: 549.61841 | AD11: 1.014738 | AE11: 4.865566 | AF11: 1.211371 | AG11: 3.133702 | AH11: 0 | AI11: 0.327844 | AJ11: 1388.0927
A12: 2047 | B12: 7184.2969 | C12: 19.892609 | D12: 7204.1895 | E12: 141.4048 | F12: 7.059891 | G12: 548.73224 | H12: 945.42224 | I12: 9.988218 | J12: 95.97963 | K12: 29.242867 | L12: 280.095 | M12: 1.04499 | N12: 4.305882 | O12: 1.037036 | P12: 0 | Q12: 2.080944 | R12: 2067.1509 | S12: 6056.9277 | T12: 107.58795 | U12: 6164.5156 | V12: 520.02075 | W12: 4.786489 | X12: 176.5043 | Y12: 15.482485 | Z12: 30.543112 | AA12: 66.226349 | AB12: 0.350929 | AC12: 533.43066 | AD12: 1.003131 | AE12: 4.812302 | AF12: 1.180079 | AG12: 3.09964 | AH12: 0 | AI12: 0.311415 | AJ12: 1357.7516
A13: 2046 | B13: 7104.939 | C13: 19.564222 | D13: 7124.5034 | E13: 139.67212 | F13: 6.913047 | G13: 527.9762 | H13: 918.56195 | I13: 9.828765 | J13: 93.627274 | K13: 28.744875 | L13: 275.98517 | M13: 1.029484 | N13: 4.240761 | O13: 1.021866 | P13: 0 | Q13: 1.996761 | R13: 2010.3378 | S13: 6044.5513 | T13: 105.26802 | U13: 6149.8193 | V13: 518.66974 | W13: 4.694041 | X13: 172.42192 | Y13: 15.346577 | Z13: 26.68679 | AA13: 66.349426 | AB13: 0.340859 | AC13: 519.86072 | AD13: 0.996359 | AE13: 4.787296 | AF13: 1.153208 | AG13: 3.083992 | AH13: 0 | AI13: 0.296321 | AJ13: 1334.6871
A14: 2045 | B14: 7026.2593 | C14: 19.230032 | D14: 7045.4893 | E14: 137.93393 | F14: 6.781735 | G14: 510.26077 | H14: 888.5506 | I14: 9.675061 | J14: 91.881493 | K14: 28.216167 | L14: 272.27689 | M14: 1.011487 | N14: 4.175304 | O14: 1.006627 | P14: 0 | Q14: 1.913042 | R14: 1954.4028 | S14: 6023.5391 | T14: 104.58823 | U14: 6128.1274 | V14: 516.73285 | W14: 4.603438 | X14: 168.90213 | Y14: 15.182136 | Z14: 23.450542 | AA14: 66.553459 | AB14: 0.328607 | AC14: 507.05832 | AD14: 0.990286 | AE14: 4.759185 | AF14: 1.130848 | AG14: 3.066095 | AH14: 0 | AI14: 0.281599 | AJ14: 1313.0394
A15: 2044 | B15: 6924.4692 | C15: 18.824385 | D15: 6943.2935 | E15: 135.78299 | F15: 6.614907 | G15: 489.66321 | H15: 861.39777 | I15: 9.482103 | J15: 89.283882 | K15: 27.651794 | L15: 267.21106 | M15: 0.992847 | N15: 4.099095 | O15: 0.98871 | P15: 0 | Q15: 1.830352 | R15: 1895.7002 | S15: 6015.1265 | T15: 102.73732 | U15: 6117.8638 | V15: 515.71844 | W15: 4.519195 | X15: 165.11609 | Y15: 15.021276 | Z15: 20.713139 | AA15: 66.603821 | AB15: 0.314649 | AC15: 494.36957 | AD15: 0.984334 | AE15: 4.738503 | AF15: 1.106761 | AG15: 3.053322 | AH15: 0 | AI15: 0.267007 | AJ15: 1292.5261
A16: 2043 | B16: 6863.6636 | C16: 18.520103 | D16: 6882.1836 | E16: 134.44055 | F16: 6.499104 | G16: 474.84998 | H16: 838.4986 | I16: 9.348961 | J16: 87.675987 | K16: 27.319126 | L16: 264.08978 | M16: 0.979475 | N16: 4.048443 | O16: 0.976996 | P16: 0 | Q16: 1.760798 | R16: 1851.1753 | S16: 6018.5557 | T16: 102.66756 | U16: 6121.2231 | V16: 515.86377 | W16: 4.445229 | X16: 162.41859 | Y16: 14.870623 | Z16: 18.479574 | AA16: 66.941101 | AB16: 0.299012 | AC16: 484.12332 | AD16: 0.98198 | AE16: 4.730482 | AF16: 1.091763 | AG16: 3.048505 | AH16: 0 | AI16: 0.253956 | AJ16: 1277.5477
A17: 2042 | B17: 6851.8477 | C17: 18.317869 | D17: 6870.1655 | E17: 134.02594 | F17: 6.424996 | G17: 463.01178 | H17: 819.57947 | I17: 9.274627 | J17: 86.643677 | K17: 27.146671 | L17: 262.6423 | M17: 0.97122 | N17: 4.024579 | O17: 0.971932 | P17: 0 | Q17: 1.703923 | R17: 1817.0986 | S17: 6079.063 | T17: 104.69996 | U17: 6183.7632 | V17: 520.89856 | W17: 4.407474 | X17: 161.06705 | Y17: 14.824867 | Z17: 16.748579 | AA17: 67.809769 | AB17: 0.28343 | AC17: 478.4317 | AD17: 0.988781 | AE17: 4.767969 | AF17: 1.089037 | AG17: 3.073061 | AH17: 0 | AI17: 0.243046 | AJ17: 1274.6333
A18: 2041 | B18: 6801.0664 | C18: 17.973934 | D18: 6819.0405 | E18: 132.81928 | F18: 6.301369 | G18: 446.60461 | H18: 795.75781 | I18: 9.134626 | J18: 84.833649 | K18: 26.638241 | L18: 259.3204 | M18: 0.956116 | N18: 3.975807 | O18: 0.96086 | P18: 0 | Q18: 1.637853 | R18: 1769.6044 | S18: 6136.0479 | T18: 106.64137 | U18: 6242.6895 | V18: 525.5404 | W18: 4.355084 | X18: 158.97803 | Y18: 14.717456 | Z18: 15.270218 | AA18: 68.400749 | AB18: 0.264662 | AC18: 471.73715 | AD18: 0.993572 | AE18: 4.801469 | AF18: 1.082617 | AG18: 3.095162 | AH18: 0 | AI18: 0.231229 | AJ18: 1269.4678
A19: 2040 | B19: 6744.5195 | C19: 17.566254 | D19: 6762.0859 | E19: 131.48029 | F19: 6.169448 | G19: 426.77841 | H19: 773.48914 | I19: 8.972788 | J19: 82.635223 | K19: 25.950548 | L19: 254.3633 | M19: 0.94242 | N19: 3.923074 | O19: 0.948782 | P19: 0 | Q19: 1.571583 | R19: 1717.875 | S19: 6210.356 | T19: 107.03075 | U19: 6317.3867 | V19: 531.88226 | W19: 4.297756 | X19: 156.41399 | Y19: 14.581896 | Z19: 14.082215 | AA19: 68.8638 | AB19: 0.243761 | AC19: 465.71115 | AD19: 1.000494 | AE19: 4.846213 | AF19: 1.077163 | AG19: 3.124582 | AH19: 0 | AI19: 0.219554 | AJ19: 1266.345
A20: 2039 | B20: 6705.085 | C20: 17.143122 | D20: 6722.228 | E20: 130.41498 | F20: 6.019829 | G20: 398.5065 | H20: 755.29553 | I20: 8.808755 | J20: 79.765709 | K20: 25.548981 | L20: 250.04053 | M20: 0.930574 | N20: 3.876864 | O20: 0.938319 | P20: 0 | Q20: 1.507918 | R20: 1662.2931 | S20: 6291.7729 | T20: 109.25549 | U20: 6401.0283 | V20: 538.43994 | W20: 4.223468 | X20: 151.54091 | Y20: 14.378107 | Z20: 13.040431 | AA20: 68.856133 | AB20: 0.220777 | AC20: 458.59866 | AD20: 1.008109 | AE20: 4.894477 | AF20: 1.075325 | AG20: 3.156234 | AH20: 0 | AI20: 0.207676 | AJ20: 1259.6401
... A40: 2019 | B40: 6709.9771 | C40: 2.094034 | D40: 6712.0713 | E40: 124.26006 | F40: 9.894434 | G40: 5.797792 | H40: 223.9214 | I40: 29.030844 | J40: 78.612167 | K40: 0 | L40: 146.89015 | M40: 0.679313 | N40: 3.446354 | O40: 0.84987 | P40: 0 | Q40: 1.963742 | R40: 625.9433 | S40: 7254.7427 | T40: 74.945877 | U40: 7329.6885 | V40: 733.30768 | W40: 0.175663 | X40: 44.449253 | Y40: 5.425774 | Z40: 7.158337 | AA40: 21.759895 | AB40: 0 | AC40: 207.84482 | AD40: 0.981438 | AE40: 5.331606 | AF40: 1.064369 | AG40: 3.440948 | AH40: 0 | AI40: 0 | AJ40: 1030.9398
A42: EPS vehicle type | B42: gasoline vehicle | C42: diesel vehicle | E42: gasoline vehicle | F42: battery electric vehicle | G42: battery electric vehicle | H42: battery electric vehicle | I42: plugin hybrid vehicle | J42: plugin hybrid vehicle | K42: diesel vehicle | L42: gasoline vehicle | M42: natural gas vehicle | N42: natural gas vehicle | O42: LPG vehicle | P42: LPG vehicle | Q42: hydrogen vehicle | R42: hydrogen vehicle | S42: gasoline vehicle | T42: diesel vehicle | V42: gasoline vehicle | W42: battery electric vehicle | X42: battery electric vehicle | Y42: battery electric vehicle | Z42: plugin hybrid vehicle | AA42: plugin hybrid vehicle | AB42: diesel vehicle | AC42: gasoline vehicle | AD42: natural gas vehicle | AE42: natural gas vehicle | AF42: LPG vehicle | AG42: LPG vehicle | AH42: hydrogen vehicle | AI42: hydrogen vehicle

Sheet AEO 40
A1: Light-Duty Fuel Economy (Case High oil and gas supply)
A2: https://www.eia.gov/outlooks/aeo/data/browser/#/?id=50-AEO2020&region=0-0&cases=highogs&start=2018&end=2050&f=A&linechart=highogs-d112619a.4-50-AEO2020~highogs-d112619a.5-50-AEO2020~highogs-d112619a.8-50-AEO2020~highogs-d112619a.9-50-AEO2020~highogs-d112619a.10-50-AEO2020~highogs-d112619a.11-50-AEO2020~highogs-d112619a.12-50-AEO2020~highogs-d112619a.13-50-AEO2020~highogs-d112619a.14-50-AEO2020~highogs-d112619a.15-50-AEO2020~highogs-d112619a.16-50-AEO2020~highogs-d112619a.17-50-AEO2020~highogs-d112619a.18-50-AEO2020~highogs-d112619a.19-50-AEO2020~highogs-d112619a.20-50-AEO2020~highogs-d112619a.21-50-AEO2020~highogs-d112619a.23-50-AEO2020~highogs-d112619a.27-50-AEO2020~highogs-d112619a.28-50-AEO2020~highogs-d112619a.31-50-AEO2020~highogs-d112619a.32-50-AEO2020~highogs-d112619a.33-50-AEO2020~highogs-d112619a.34-50-AEO2020~highogs-d112619a.35-50-AEO2020~highogs-d112619a.36-50-AEO2020~highogs-d112619a.37-50-AEO2020~highogs-d112619a.38-50-AEO2020~highogs-d112619a.39-50-AEO2020~highogs-d112619a.40-50-AEO2020~highogs-d112619a.41-50-AEO2020~highogs-d112619a.42-50-AEO2020~highogs-d112619a.43-50-AEO2020~highogs-d112619a.44-50-AEO2020~highogs-d112619a.46-50-AEO2020&ctype=linechart&sourcekey=0
A3: 10:07:37 GMT-0800 (Pacific Standard Time)
A4: Source: U.S. Energy Information Administration
A5: Year | B5: Conventional Cars: Gasoline mpg gas equiv | C5: Conventional Cars: TDI Diesel mpg gas equiv | D5: Alternative-Fuel Cars: Ethanol-Flex Fuel ICE mpg gas equiv | E5: Alternative-Fuel Cars: 100 Mile Electric Vehicle mpg gas equiv | F5: Alternative-Fuel Cars: 200 Mile Electric Vehicle mpg gas equiv | G5: Alternative-Fuel Cars: 300 Mile Electric Vehicle mpg gas equiv | H5: Alternative-Fuel Cars: Plug-in 10 Gasoline Hybrid mpg gas equiv | I5: Alternative-Fuel Cars: Plug-in 40 Gasoline Hybrid mpg gas equiv | J5: Alternative-Fuel Cars: Electric-Diesel Hybrid mpg gas equiv | K5: Alternative-Fuel Cars: Electric-Gasoline Hybrid mpg gas equiv | L5: Alternative-Fuel Cars: Natural Gas ICE mpg gas equiv | M5: Alternative-Fuel Cars: Natural Gas Bi-fuel mpg gas equiv | N5: Alternative-Fuel Cars: Propane ICE mpg gas equiv | O5: Alternative-Fuel Cars: Propane Bi-fuel mpg gas equiv | P5: Alternative-Fuel Cars: Fuel Cell Methanol mpg gas equiv | Q5: Alternative-Fuel Cars: Fuel Cell Hydrogen mpg gas equiv | R5: Cars: Average New Car MPG mpg gas equiv | S5: Conventional Light Trucks: Gasoline mpg gas equiv | T5: Conventional Light Trucks: TDI Diesel mpg gas equiv | U5: Alternative-Fuel Light Trucks: Ethanol-Flex Fuel ICE mpg gas equiv | V5: Alternative-Fuel Light Trucks: 100 Mile Electric Vehicle mpg gas equiv | W5: Alternative-Fuel Light Trucks: 200 Mile Electric Vehicle mpg gas equiv | X5: Alternative-Fuel Light Trucks: 300 Mile Electric Vehicle mpg gas equiv | Y5: Alternative-Fuel Light Trucks: Plug-in 10 Gasoline Hybrid mpg gas equiv | Z5: Alternative-Fuel Light Trucks: Plug-in 40 Gasoline Hybrid mpg gas equiv | AA5: Alternative-Fuel Light Trucks: Electric-Diesel Hybrid mpg gas equiv | AB5: Alternative-Fuel Light Trucks: Electric-Gasoline Hybrid mpg gas equiv | AC5: Alternative-Fuel Light Trucks: Natural Gas ICE mpg gas equiv | AD5: Alternative-Fuel Light Trucks: Natural Gas Bi-fuel mpg gas equiv | AE5: Alternative-Fuel Light Trucks: Propane ICE mpg gas equiv | AF5: Alternative-Fuel Light Trucks: Propane Bi-fuel mpg gas equiv | AG5: Alternative-Fuel Light Trucks: Fuel Cell Methanol mpg gas equiv | AH5: Alternative-Fuel Light Trucks: Fuel Cell Hydrogen mpg gas equiv | AI5: Light Trucks: Average New Light Truck mpg gas equiv | AJ5: Conventional Cars: Gasoline mpg gas equiv | AK5: Light Trucks: Average New Light Truck mpg gas equiv | AL5: Average New Vehicle mpg gas equiv | AM5: Cars: Stock Average mpg gas equiv | AN5: Light Trucks: Stock Average mpg gas equiv | AO5: Stock Average mpg gas equiv | AP5: New: +2B: Plug-in Hybrid mpg gas equiv | AQ5: Stock: +2B: Plug-in Hybrid mpg gas equiv
A6: 2050 | B6: 47.681984 | C6: 55.305809 | D6: 48.98439 | E6: 125.53535 | F6: 133.62488 | G6: 131.03696 | H6: 73.128197 | I6: 85.117378 | J6: 82.645966 | K6: 69.887756 | L6: 52.553799 | M6: 48.794102 | N6: 50.449409 | O6: 48.849701 | P6: 0 | Q6: 59.002132 | R6: 58.987617 | S6: 37.267811 | T6: 42.230171 | U6: 37.656605 | V6: 89.901077 | W6: 112.8126 | X6: 100.27828 | Y6: 58.820457 | Z6: 76.532066 | AA6: 58.343231 | AB6: 55.293106 | AC6: 38.343075 | AD6: 35.944969 | AE6: 37.174129 | AF6: 36.034206 | AG6: 0 | AH6: 47.615364 | AI6: 39.929474 | AJ6: 47.681984 | AK6: 39.929474 | AL6: 48.674248 | AM6: 43.528164 | AN6: 31.529968 | AO6: 36.73679 | AP6: 43.10556 | AQ6: 35.116829
A7: 2049 | B7: 47.775478 | C7: 55.542683 | D7: 49.081425 | E7: 125.53081 | F7: 133.62981 | G7: 131.05167 | H7: 73.249634 | I7: 85.22049 | J7: 82.816322 | K7: 70.01857 | L7: 52.662815 | M7: 48.890476 | N7: 50.552155 | O7: 48.949348 | P7: 0 | Q7: 58.98064 | R7: 58.859608 | S7: 37.333641 | T7: 42.321018 | U7: 37.724857 | V7: 89.765511 | W7: 112.79211 | X7: 100.26277 | Y7: 58.737045 | Z7: 76.659653 | AA7: 58.381844 | AB7: 55.380505 | AC7: 38.494415 | AD7: 36.001274 | AE7: 37.261089 | AF7: 36.07851 | AG7: 0 | AH7: 47.542843 | AI7: 39.958122 | AJ7: 47.775478 | AK7: 39.958122 | AL7: 48.634819 | AM7: 43.437515 | AN7: 31.475521 | AO7: 36.625896 | AP7: 43.086754 | AQ7: 35.022881
A8: 2048 | B8: 47.867973 | C8: 55.770748 | D8: 49.171322 | E8: 125.52479 | F8: 133.60393 | G8: 131.05881 | H8: 73.351234 | I8: 85.299561 | J8: 82.979904 | K8: 70.154266 | L8: 52.755669 | M8: 48.974731 | N8: 50.641586 | O8: 49.035454 | P8: 0 | Q8: 58.958511 | R8: 58.738182 | S8: 37.39431 | T8: 42.401325 | U8: 37.786667 | V8: 89.644356 | W8: 112.7931 | X8: 100.2503 | Y8: 58.625381 | Z8: 76.764839 | AA8: 58.419243 | AB8: 55.466476 | AC8: 38.64814 | AD8: 36.050694 | AE8: 37.35075 | AF8: 36.117153 | AG8: 0 | AH8: 47.456802 | AI8: 39.972542 | AJ8: 47.867973 | AK8: 39.972542 | AL8: 48.562855 | AM8: 43.334728 | AN8: 31.412695 | AO8: 36.501759 | AP8: 43.047394 | AQ8: 34.918461
A9: 2047 | B9: 47.960953 | C9: 56.004269 | D9: 49.266571 | E9: 125.51791 | F9: 133.60239 | G9: 131.07202 | H9: 73.476677 | I9: 85.407013 | J9: 83.139709 | K9: 70.285324 | L9: 52.85976 | M9: 49.066986 | N9: 50.740536 | O9: 49.131325 | P9: 0 | Q9: 58.935284 | R9: 58.621887 | S9: 37.454441 | T9: 42.480221 | U9: 37.850887 | V9: 89.542732 | W9: 112.78212 | X9: 100.23846 | Y9: 58.515423 | Z9: 76.892105 | AA9: 58.453716 | AB9: 55.551521 | AC9: 38.799961 | AD9: 36.103249 | AE9: 37.437809 | AF9: 36.158527 | AG9: 0 | AH9: 47.363785 | AI9: 39.996075 | AJ9: 47.960953 | AK9: 39.996075 | AL9: 48.504185 | AM9: 43.218128 | AN9: 31.341038 | AO9: 36.364738 | AP9: 43.020195 | AQ9: 34.803288
A10: 2046 | B10: 48.051662 | C10: 56.229118 | D10: 49.354496 | E10: 125.51062 | F10: 133.57756 | G10: 131.07971 | H10: 73.566505 | I10: 85.480751 | J10: 83.291916 | K10: 70.41716 | L10: 52.946415 | M10: 49.146839 | N10: 50.825565 | O10: 49.21431 | P10: 0 | Q10: 58.912121 | R10: 58.51268 | S10: 37.510044 | T10: 42.548916 | U10: 37.908627 | V10: 89.45182 | W10: 112.78883 | X10: 100.22841 | Y10: 58.365711 | Z10: 76.970596 | AA10: 58.485748 | AB10: 55.632961 | AC10: 38.952374 | AD10: 36.153122 | AE10: 37.522564 | AF10: 36.194386 | AG10: 0 | AH10: 47.258968 | AI10: 40.008018 | AJ10: 48.051662 | AK10: 40.008018 | AL10: 48.425739 | AM10: 43.085407 | AN10: 31.259272 | AO10: 36.213295 | AP10: 42.980335 | AQ10: 34.675686
A11: 2045 | B11: 48.139225 | C11: 56.459312 | D11: 49.444305 | E11: 125.50528 | F11: 133.57927 | G11: 131.09442 | H11: 73.685089 | I11: 85.585106 | J11: 83.446106 | K11: 70.541443 | L11: 53.043022 | M11: 49.234436 | N11: 50.92009 | O11: 49.304844 | P11: 0 | Q11: 58.888008 | R11: 58.397022 | S11: 37.565617 | T11: 42.619778 | U11: 37.968128 | V11: 89.374008 | W11: 112.78085 | X11: 100.21758 | Y11: 58.223606 | Z11: 77.080421 | AA11: 58.519367 | AB11: 55.713669 | AC11: 39.102371 | AD11: 36.200306 | AE11: 37.603024 | AF11: 36.233231 | AG11: 0 | AH11: 47.146309 | AI11: 40.029408 | AJ11: 48.139225 | AK11: 40.029408 | AL11: 48.3549 | AM11: 42.936893 | AN11: 31.165998 | AO11: 36.047432 | AP11: 42.957817 | AQ11: 34.54261
A12: 2044 | B12: 48.227612 | C12: 56.673969 | D12: 49.528553 | E12: 125.4942 | F12: 133.55453 | G12: 131.10255 | H12: 73.769714 | I12: 85.659332 | J12: 83.557877 | K12: 70.663376 | L12: 53.118614 | M12: 49.307106 | N12: 50.998089 | O12: 49.38279 | P12: 0 | Q12: 58.864353 | R12: 58.303883 | S12: 37.615147 | T12: 42.670715 | U12: 38.019608 | V12: 89.304848 | W12: 112.79251 | X12: 100.20834 | Y12: 58.04454 | Z12: 77.152176 | AA12: 58.543549 | AB12: 55.785152 | AC12: 39.219242 | AD12: 36.239388 | AE12: 37.681709 | AF12: 36.265278 | AG12: 0 | AH12: 47.022507 | AI12: 40.038029 | AJ12: 48.227612 | AK12: 40.038029 | AL12: 48.262737 | AM12: 42.762932 | AN12: 31.058792 | AO12: 35.862267 | AP12: 42.911129 | AQ12: 34.387123
A13: 2043 | B13: 48.314518 | C13: 56.887218 | D13: 49.614708 | E13: 125.48174 | F13: 133.54778 | G13: 131.11371 | H13: 73.857285 | I13: 85.739227 | J13: 83.63343 | K13: 70.772858 | L13: 53.198021 | M13: 49.382515 | N13: 51.08147 | O13: 49.465981 | P13: 0 | Q13: 58.84087 | R13: 58.223202 | S13: 37.664356 | T13: 42.725712 | U13: 38.071659 | V13: 89.246002 | W13: 112.79703 | X13: 100.1991 | Y13: 57.864235 | Z13: 77.233986 | AA13: 58.560081 | AB13: 55.851875 | AC13: 39.3158 | AD13: 36.280529 | AE13: 37.751865 | AF13: 36.298912 | AG13: 0 | AH13: 46.897633 | AI13: 40.055481 | AJ13: 48.314518 | AK13: 40.055481 | AL13: 48.197189 | AM13: 42.569054 | AN13: 30.937075 | AO13: 35.660904 | AP13: 42.881802 | AQ13: 34.215942
A14: 2042 | B14: 48.397583 | C14: 57.080658 | D14: 49.696568 | E14: 125.46573 | F14: 133.54884 | G14: 131.12797 | H14: 73.944527 | I14: 85.822289 | J14: 83.711021 | K14: 70.872162 | L14: 53.27354 | M14: 49.454552 | N14: 51.162758 | O14: 49.547817 | P14: 0 | Q14: 58.818539 | R14: 58.118862 | S14: 37.7103 | T14: 42.806911 | U14: 38.120468 | V14: 89.196487 | W14: 112.80061 | X14: 100.19049 | Y14: 57.68362 | Z14: 77.315475 | AA14: 58.56852 | AB14: 55.912685 | AC14: 39.412125 | AD14: 36.320869 | AE14: 37.817795 | AF14: 36.331337 | AG14: 0 | AH14: 46.764076 | AI14: 40.069695 | AJ14: 48.397583 | AK14: 40.069695 | AL14: 48.108444 | AM14: 42.343189 | AN14: 30.797438 | AO14: 35.43647 | AP14: 42.837154 | AQ14: 34.021847
A15: 2041 | B15: 48.471909 | C15: 57.167458 | D15: 49.768448 | E15: 125.45152 | F15: 133.54575 | G15: 131.14293 | H15: 74.014366 | I15: 85.89241 | J15: 83.899872 | K15: 70.968933 | L15: 53.343094 | M15: 49.519623 | N15: 51.2356 | O15: 49.619392 | P15: 0 | Q15: 58.796474 | R15: 57.984364 | S15: 37.752281 | T15: 42.882729 | U15: 38.164776 | V15: 89.154701 | W15: 112.8114 | X15: 100.18356 | Y15: 57.506477 | Z15: 77.380188 | AA15: 58.582638 | AB15: 55.975739 | AC15: 39.464005 | AD15: 36.357506 | AE15: 37.884384 | AF15: 36.360786 | AG15: 0 | AH15: 46.621426 | AI15: 40.075615 | AJ15: 48.471909 | AK15: 40.075615 | AL15: 47.980515 | AM15: 42.072693 | AN15: 30.63913 | AO15: 35.185284 | AP15: 42.765274 | AQ15: 33.801395
A16: 2040 | B16: 48.546909 | C16: 57.248001 | D16: 49.840054 | E16: 125.44669 | F16: 133.53145 | G16: 131.15465 | H16: 74.070938 | I16: 85.946907 | J16: 84.118568 | K16: 71.13028 | L16: 53.406418 | M16: 49.580273 | N16: 51.3032 | O16: 49.68821 | P16: 0 | Q16: 58.775497 | R16: 57.841148 | S16: 37.794556 | T16: 42.954197 | U16: 38.209316 | V16: 89.12027 | W16: 112.8348 | X16: 100.17802 | Y16: 57.359261 | Z16: 77.424965 | AA16: 58.590565 | AB16: 56.037132 | AC16: 39.50618 | AD16: 36.392696 | AE16: 37.952087 | AF16: 36.38921 | AG16: 0 | AH16: 46.476608 | AI16: 40.075218 | AJ16: 48.546909 | AK16: 40.075218 | AL16: 47.83065 | AM16: 41.759014 | AN16: 30.458717 | AO16: 34.907772 | AP16: 42.678761 | AQ16: 33.557755
A17: 2039 | B17: 48.630318 | C17: 57.335922 | D17: 49.917961 | E17: 125.42291 | F17: 133.51578 | G17: 131.16907 | H17: 74.139076 | I17: 86.01104 | J17: 84.275307 | K17: 71.24118 | L17: 53.475388 | M17: 49.646889 | N17: 51.377106 | O17: 49.765415 | P17: 0 | Q17: 58.755146 | R17: 57.643833 | S17: 37.843178 | T17: 43.0383 | U17: 38.260303 | V17: 89.095558 | W17: 112.86436 | X17: 100.17328 | Y17: 57.216026 | Z17: 77.476807 | AA17: 58.599102 | AB17: 56.102123 | AC17: 39.552105 | AD17: 36.433945 | AE17: 38.023338 | AF17: 36.423233 | AG17: 0 | AH17: 46.33744 | AI17: 40.064693 | AJ17: 48.630318 | AK17: 40.064693 | AL17: 47.659729 | AM17: 41.402107 | AN17: 30.25383 | AO17: 34.603638 | AP17: 42.585392 | AQ17: 33.288147
... A37: 2019 | B37: 40.156864 | C37: 50.414795 | D37: 40.841618 | E37: 111.428 | F37: 121.63172 | G37: 120.73607 | H37: 61.002525 | I37: 74.516876 | J37: 0 | K37: 57.716972 | L37: 42.766304 | M37: 40.074883 | N37: 41.242378 | O37: 40.46909 | P37: 0 | Q37: 54.463524 | R37: 42.356316 | S37: 29.754852 | T37: 37.037449 | U37: 29.940485 | V37: 0 | W37: 103.56575 | X37: 90.40731 | Y37: 46.257996 | Z37: 54.129944 | AA37: 0 | AB37: 43.222702 | AC37: 30.83477 | AD37: 28.579258 | AE37: 29.503197 | AF37: 28.53409 | AG37: 0 | AH37: 41.850655 | AI37: 30.865908 | AJ37: 40.156864 | AK37: 30.865908 | AL37: 35.348213 | AM37: 28.291594 | AN37: 20.426172 | AO37: 23.821983 | AP37: 32.759342 | AQ37: 23.278784
A39: EPS vehicle type | B39: gasoline vehicle | C39: diesel vehicle | D39: gasoline vehicle | E39: battery electric vehicle | F39: battery electric vehicle | G39: battery electric vehicle | H39: plugin hybrid vehicle | I39: plugin hybrid vehicle | J39: diesel vehicle | K39: gasoline vehicle | L39: natural gas vehicle | M39: natural gas vehicle | N39: LPG vehicle | O39: LPG vehicle | P39: hydrogen vehicle | Q39: hydrogen vehicle | S39: gasoline vehicle | T39: diesel vehicle | U39: gasoline vehicle | V39: battery electric vehicle | W39: battery electric vehicle | X39: battery electric vehicle | Y39: plugin hybrid vehicle | Z39: plugin hybrid vehicle | AA39: diesel vehicle | AB39: gasoline vehicle | AC39: natural gas vehicle | AD39: natural gas vehicle | AE39: LPG vehicle | AF39: LPG vehicle | AG39: hydrogen vehicle | AH39: hydrogen vehicle

Sheet AEO 41
A1: Light-Duty Vehicle Miles Traveled (Case High oil and gas supply)
A2: https://www.eia.gov/outlooks/aeo/data/browser/#/?id=51-AEO2020&region=0-0&cases=highogs&start=2018&end=2050&f=A&linechart=highogs-d112619a.2-51-AEO2020~highogs-d112619a.3-51-AEO2020~highogs-d112619a.6-51-AEO2020~highogs-d112619a.7-51-AEO2020~highogs-d112619a.8-51-AEO2020~highogs-d112619a.9-51-AEO2020~highogs-d112619a.10-51-AEO2020~highogs-d112619a.11-51-AEO2020~highogs-d112619a.12-51-AEO2020~highogs-d112619a.13-51-AEO2020~highogs-d112619a.14-51-AEO2020~highogs-d112619a.15-51-AEO2020~highogs-d112619a.16-51-AEO2020~highogs-d112619a.17-51-AEO2020~highogs-d112619a.18-51-AEO2020~highogs-d112619a.19-51-AEO2020&sourcekey=0
A3: 12:42:05 GMT-0700 (Pacific Daylight Time)
A4: Source: U.S. Energy Information Administration
A5: Year | B5: Conventional Vehicles: Gasoline billion miles | C5: Conventional Vehicles: TDI Diesel billion miles | D5: Alternative-Fuel Vehicles: Ethanol-Flex Fuel ICE billion miles | E5: Alternative-Fuel Vehicles: 100 Mile Electric Vehicle billion miles | F5: Alternative-Fuel Vehicles: 200 Mile Electric Vehicle billion miles | G5: Alternative-Fuel Vehicles: 300 Mile Electric Vehicle billion miles | H5: Alternative-Fuel Vehicles: Plug-in 10 Gasoline Hybrid billion miles | I5: Alternative-Fuel Vehicles: Plug-in 40 Gasoline Hybrid billion miles | J5: Alternative-Fuel Vehicles: Electric-Diesel Hybrid billion miles | K5: Alternative-Fuel Vehicles: Electric-Gasoline Hybrid billion miles | L5: Alternative-Fuel Vehicles: Natural Gas ICE billion miles | M5: Alternative-Fuel Vehicles: Natural Gas Bi-fuel billion miles | N5: Alternative-Fuel Vehicles: Propane ICE billion miles | O5: Alternative-Fuel Vehicles: Propane Bi-fuel billion miles | P5: Alternative-Fuel Vehicles: Fuel Cell Methanol billion miles | Q5: Alternative-Fuel Vehicles: Fuel Cell Hydrogen billion miles
A6: 2050 | B6: 2927.7937 | C6: 28.310617 | D6: 157.90778 | E6: 2.148816 | F6: 126.12958 | G6: 171.08795 | H6: 6.62871 | I6: 31.760241 | J6: 5.274114 | K6: 165.34073 | L6: 0.228105 | M6: 0.777238 | N6: 0.296341 | O6: 0.31541 | P6: 0 | Q6: 0.403933
A7: 2049 | B7: 2910.1577 | C7: 28.112772 | D7: 157.79211 | E7: 2.088993 | F7: 120.51414 | G7: 164.59456 | H7: 6.037531 | I7: 31.081373 | J7: 5.089775 | K7: 161.37906 | L7: 0.225985 | M7: 0.771208 | N7: 0.289011 | O7: 0.313748 | P7: 0 | Q7: 0.384196
A8: 2048 | B8: 2894.3398 | C8: 27.919748 | D8: 157.84199 | E8: 2.028488 | F8: 114.89677 | G8: 158.17912 | H8: 5.530824 | I8: 30.362911 | J8: 4.889179 | K8: 157.49901 | L8: 0.223979 | M8: 0.765323 | N8: 0.282106 | O8: 0.312206 | P8: 0 | Q8: 0.364819
A9: 2047 | B9: 2880.3875 | C9: 27.754131 | D9: 158.04329 | E9: 1.967612 | F9: 109.34819 | G9: 151.80158 | H9: 5.095844 | I9: 29.621361 | J9: 4.670751 | K9: 153.71468 | L9: 0.222062 | M9: 0.759491 | N9: 0.275655 | O9: 0.310712 | P9: 0 | Q9: 0.345787
A10: 2046 | B10: 2869.4912 | C10: 27.616241 | D10: 158.47647 | E10: 1.90674 | F10: 103.86221 | G10: 145.58363 | H10: 4.724231 | I10: 28.852882 | J10: 4.438396 | K10: 150.07205 | L10: 0.220414 | M10: 0.754543 | N10: 0.269837 | O10: 0.309627 | P10: 0 | Q10: 0.327308
A11: 2045 | B11: 2860.7444 | C11: 27.525841 | D11: 159.08285 | E11: 1.845636 | F11: 98.436264 | G11: 139.43074 | H11: 4.404008 | I11: 28.061007 | J11: 4.191662 | K11: 146.51802 | L11: 0.218927 | M11: 0.750121 | N11: 0.264534 | O11: 0.308801 | P11: 0 | Q11: 0.309214
A12: 2044 | B12: 2855.2769 | C12: 27.462532 | D12: 159.93063 | E12: 1.784575 | F12: 93.044441 | G12: 133.45471 | H12: 4.127164 | I12: 27.245073 | J12: 3.934509 | K12: 143.07369 | L12: 0.217638 | M12: 0.746326 | N12: 0.259773 | O12: 0.30829 | P12: 0 | Q12: 0.291593
A13: 2043 | B13: 2851.3394 | C13: 27.427101 | D13: 160.9241 | E13: 1.723708 | F13: 87.674911 | G13: 127.52292 | H13: 3.887988 | I13: 26.405495 | J13: 3.66723 | K13: 139.65912 | L13: 0.216509 | M13: 0.743376 | N13: 0.255499 | O13: 0.308155 | P13: 0 | Q13: 0.27441
A14: 2042 | B14: 2848.3391 | C14: 27.384569 | D14: 162.04746 | E14: 1.663189 | F14: 82.233749 | G14: 121.5945 | H14: 3.680046 | I14: 25.529198 | J14: 3.388695 | K14: 136.2067 | L14: 0.215447 | M14: 0.740909 | N14: 0.251543 | O14: 0.308284 | P14: 0 | Q14: 0.257718
A15: 2041 | B15: 2846.0322 | C15: 27.307106 | D15: 163.29001 | E15: 1.603104 | F15: 76.702881 | G15: 115.67545 | H15: 3.499056 | I15: 24.611828 | J15: 3.099742 | K15: 132.68387 | L15: 0.215708 | M15: 0.738397 | N15: 0.247843 | O15: 0.308516 | P15: 0 | Q15: 0.241515
A16: 2040 | B16: 2844.741 | C16: 27.187225 | D16: 164.69875 | E16: 1.546541 | F16: 71.132812 | G16: 109.79195 | H16: 3.350828 | I16: 23.66251 | J16: 2.805427 | K16: 129.10451 | L16: 0.215207 | M16: 0.73677 | N16: 0.244949 | O16: 0.30965 | P16: 0 | Q16: 0.226105
A17: 2039 | B17: 2841.959 | C17: 27.036894 | D17: 166.16921 | E17: 1.49586 | F17: 65.538063 | G17: 103.84312 | H17: 3.22569 | I17: 22.662228 | J17: 2.507652 | K17: 125.38679 | L17: 0.215927 | M17: 0.737118 | N17: 0.242234 | O17: 0.314467 | P17: 0 | Q17: 0.211309
... A37: 2019 | B37: 2576.9045 | C37: 15.066283 | D37: 244.83624 | E37: 2.42997 | F37: 3.706803 | G37: 5.594828 | H37: 4.282115 | I37: 4.629926 | J37: 0 | K37: 57.174438 | L37: 0.446715 | M37: 1.005513 | N37: 0.233891 | O37: 0.856037 | P37: 0 | Q37: 0.086018
B39: gasoline vehicle | C39: diesel vehicle | D39: gasoline vehicle | E39: battery electric vehicle | F39: battery electric vehicle | G39: battery electric vehicle | H39: plugin hybrid vehicle | I39: plugin hybrid vehicle | J39: diesel vehicle | K39: gasoline vehicle | L39: natural gas vehicle | M39: natural gas vehicle | N39: LPG vehicle | O39: LPG vehicle | P39: hydrogen vehicle | Q39: hydrogen vehicle

Sheet AEO 43
F1: 2019 | G1: 2020 | H1: 2021 | I1: 2022 | J1: 2023 | K1: 2024 | L1: 2025 | M1: 2026 | N1: 2027 | O1: 2028 | P1: 2029 | Q1: 2030 | R1: 2031 | S1: 2032 | T1: 2033 | U1: 2034 | V1: 2035 | W1: 2036 | X1: 2037 | Y1: 2038 | Z1: 2039 | AA1: 2040 | AB1: 2041 | AC1: 2042 | AD1: 2043 | AE1: 2044 | AF1: 2045 | AG1: 2046 | AH1: 2047 | AI1: 2048 | AJ1: 2049 | AK1: 2050 | AL1: Growth (2019-2050)
B10: Table 43. Transportation Fleet Car and Truck Fuel Consumption by Type and Technology
B11: https://www.eia.gov/outlooks/aeo/data/browser/#/?id=53-AEO2020&cases=highogs&sourcekey=0
B12: Tue Mar 09 2021 09:46:31 GMT-0800 (Pacific Standard Time)
B13: Source: U.S. Energy Information Administration
C14: full name | D14: api key | E14: units | F14: 2019 | G14: 2020 | H14: 2021 | I14: 2022 | J14: 2023 | K14: 2024 | L14: 2025 | M14: 2026 | N14: 2027 | O14: 2028 | P14: 2029 | Q14: 2030 | R14: 2031 | S14: 2032 | T14: 2033 | U14: 2034 | V14: 2035 | W14: 2036 | X14: 2037 | Y14: 2038 | Z14: 2039 | AA14: 2040 | AB14: 2041 | AC14: 2042 | AD14: 2043 | AE14: 2044 | AF14: 2045 | AG14: 2046 | AH14: 2047 | AI14: 2048 | AJ14: 2049 | AK14: 2050 | AL14: Growth (2019-2050)
B15: Cars | D15: 53-AEO2020.2.
B16: Conventional Cars | D16: 53-AEO2020.3.
B17: Gasoline ICE Vehicles | C17: Fleet Vehicle Energy Use: Conventional Cars: Gasoline: High oil and gas supply | D17: 53-AEO2020.4.highogs-d112619a | E17: trillion Btu | F17: 448.92712 | G17: 432.19784 | H17: 415.09604 | I17: 393.16638 | J17: 367.80301 | K17: 346.03827 | L17: 324.03223 | M17: 306.49155 | N17: 293.41574 | O17: 283.71787 | P17: 277.09833 | Q17: 272.97482 | R17: 270.21954 | S17: 268.33899 | T17: 267.01495 | U17: 266.36908 | V17: 266.23724 | W17: 267.04242 | X17: 268.28925 | Y17: 270.04135 | Z17: 272.33768 | AA17: 274.50345 | AB17: 276.63928 | AC17: 279.73721 | AD17: 282.5495 | AE17: 285.81635 | AF17: 290.04019 | AG17: 294.57245 | AH17: 299.23071 | AI17: 304.37787 | AJ17: 309.14917 | AK17: 313.46106 | AL17: -0.012
B18: TDI Diesel ICE | C18: Fleet Vehicle Energy Use: Conventional Cars: TDI Diesel: High oil and gas supply | D18: 53-AEO2020.5.highogs-d112619a | E18: trillion Btu | F18: 1.56414 | G18: 1.4964 | H18: 1.430923 | I18: 1.366693 | J18: 1.319986 | K18: 1.284571 | L18: 1.250678 | M18: 1.231132 | N18: 1.229022 | O18: 1.246591 | P18: 1.283301 | Q18: 1.325149 | R18: 1.387195 | S18: 1.48893 | T18: 1.595926 | U18: 1.701736 | V18: 1.809246 | W18: 1.922208 | X18: 2.032461 | Y18: 2.140187 | Z18: 2.239645 | AA18: 2.338476 | AB18: 2.447548 | AC18: 2.551064 | AD18: 2.64542 | AE18: 2.738792 | AF18: 2.836366 | AG18: 2.931751 | AH18: 3.02346 | AI18: 3.115211 | AJ18: 3.199116 | AK18: 3.274838 | AL18: 0.024
B19: Total Conventional Cars | C19: Fleet Vehicle Energy Use: Conventional Cars: Total: High oil and gas supply | D19: 53-AEO2020.6.highogs-d112619a | E19: trillion Btu | F19: 450.49127 | G19: 433.69424 | H19: 416.52695 | I19: 394.53308 | J19: 369.12299 | K19: 347.32284 | L19: 325.2829 | M19: 307.72269 | N19: 294.64477 | O19: 284.96445 | P19: 278.38162 | Q19: 274.29996 | R19: 271.60675 | S19: 269.82791 | T19: 268.61087 | U19: 268.0708 | V19: 268.04648 | W19: 268.96463 | X19: 270.32172 | Y19: 272.18155 | Z19: 274.57733 | AA19: 276.84192 | AB19: 279.08682 | AC19: 282.28827 | AD19: 285.19492 | AE19: 288.55514 | AF19: 292.87656 | AG19: 297.50421 | AH19: 302.25418 | AI19: 307.49307 | AJ19: 312.3483 | AK19: 316.7359 | AL19: -0.011
B20: Alternative-Fuel Cars | D20: 53-AEO2020.8.
B21: Ethanol-Flex Fuel ICE | C21: Fleet Vehicle Energy Use: Alternative-Fuel Cars: Ethanol-Flex Fuel ICE: High oil and gas supply | D21: 53-AEO2020.9.highogs-d112619a | E21: trillion Btu | F21: 27.82748 | G21: 25.598982 | H21: 23.585793 | I21: 21.501091 | J21: 19.642786 | K21: 18.154333 | L21: 16.689133 | M21: 15.517682 | N21: 14.619654 | O21: 13.913252 | P21: 13.38958 | Q21: 13.006542 | R21: 12.677776 | S21: 12.437954 | T21: 12.121868 | U21: 11.936569 | V21: 11.811363 | W21: 11.688669 | X21: 11.69699 | Y21: 11.792857 | Z21: 11.885321 | AA21: 11.969833 | AB21: 12.127377 | AC21: 12.303209 | AD21: 12.454608 | AE21: 12.623462 | AF21: 12.837446 | AG21: 13.061507 | AH21: 13.286102 | AI21: 13.530311 | AJ21: 13.750583 | AK21: 13.944055 | AL21: -0.022
B22: 100 Mile Electric Vehicle | C22: Fleet Vehicle Energy Use: Alternative-Fuel Cars: 100 Mile Electric Vehicle: High oil and gas supply | D22: 53-AEO2020.10.highogs-d112619a | E22: trillion Btu | F22: 0.251801 | G22: 0.260844 | H22: 0.268711 | I22: 0.275627 | J22: 0.281793 | K22: 0.287428 | L22: 0.292391 | M22: 0.297624 | N22: 0.298632 | O22: 0.306016 | P22: 0.314573 | Q22: 0.331236 | R22: 0.345754 | S22: 0.362978 | T22: 0.381988 | U22: 0.402779 | V22: 0.424703 | W22: 0.446527 | X22: 0.469013 | Y22: 0.490684 | Z22: 0.513364 | AA22: 0.534204 | AB22: 0.555838 | AC22: 0.577312 | AD22: 0.597408 | AE22: 0.616646 | AF22: 0.635455 | AG22: 0.653509 | AH22: 0.670839 | AI22: 0.687732 | AJ22: 0.703579 | AK22: 0.718327 | AL22: 0.034
B23: 200 Mile Electric Vehicle | C23: Fleet Vehicle Energy Use: Alternative-Fuel Cars: 200 Mile Electric Vehicle: High oil and gas supply | D23: 53-AEO2020.11.highogs-d112619a | E23: trillion Btu | F23: 0.297188 | G23: 0.327627 | H23: 0.361247 | I23: 0.3971 | J23: 0.436255 | K23: 0.480423 | L23: 0.529673 | M23: 0.586209 | N23: 0.652533 | O23: 0.729498 | P23: 0.817466 | Q23: 0.916947 | R23: 1.024467 | S23: 1.1361 | T23: 1.249296 | U23: 1.362126 | V23: 1.473495 | W23: 1.584351 | X23: 1.692211 | Y23: 1.795687 | Z23: 1.895204 | AA23: 1.986895 | AB23: 2.072537 | AC23: 2.154911 | AD23: 2.229373 | AE23: 2.300156 | AF23: 2.37065 | AG23: 2.438423 | AH23: 2.503453 | AI23: 2.567792 | AJ23: 2.627487 | AK23: 2.682046 | AL23: 0.074
B24: 300 Mile Electric Vehicle | C24: Fleet Vehicle Energy Use: Alternative-Fuel Cars: 300 Mile Electric Vehicle: High oil and gas supply | D24: 53-AEO2020.12.highogs-d112619a | E24: trillion Btu | F24: 0.220589 | G24: 0.161104 | H24: 0.127104 | I24: 0.14792 | J24: 0.18328 | K24: 0.225922 | L24: 0.276365 | M24: 0.337114 | N24: 0.410683 | O24: 0.497403 | P24: 0.597194 | Q24: 0.71061 | R24: 0.833232 | S24: 0.961389 | T24: 1.092259 | U24: 1.223399 | V24: 1.352669 | W24: 1.481129 | X24: 1.606135 | Y24: 1.727845 | Z24: 1.844747 | AA24: 1.95321 | AB24: 2.054923 | AC24: 2.149669 | AD24: 2.234975 | AE24: 2.315397 | AF24: 2.395256 | AG24: 2.4716 | AH24: 2.544435 | AI24: 2.61591 | AJ24: 2.681997 | AK24: 2.742225 | AL24: 0.085
B25: Plug-in 10 Gasoline Hybrid | C25: Fleet Vehicle Energy Use: Alternative-Fuel Cars: Plug-in 10 Gasoline Hybrid: High oil and gas supply | D25: 53-AEO2020.13.highogs-d112619a | E25: trillion Btu | F25: 2.850964 | G25: 1.862119 | H25: 1.268327 | I25: 1.193479 | J25: 1.192451 | K25: 1.180799 | L25: 1.160745 | M25: 1.144941 | N25: 1.139436 | O25: 1.140677 | P25: 1.145736 | Q25: 1.157257 | R25: 1.173982 | S25: 1.189607 | T25: 1.213484 | U25: 1.238913 | V25: 1.270611 | W25: 1.312606 | X25: 1.355393 | Y25: 1.3993 | Z25: 1.445656 | AA25: 1.492399 | AB25: 1.534848 | AC25: 1.580987 | AD25: 1.622495 | AE25: 1.66347 | AF25: 1.710069 | AG25: 1.755632 | AH25: 1.799961 | AI25: 1.84389 | AJ25: 1.885671 | AK25: 1.925179 | AL25: -0.013
B26: Plug-in 40 Gasoline Hybrid | C26: Fleet Vehicle Energy Use: Alternative-Fuel Cars: Plug-in 40 Gasoline Hybrid: High oil and gas supply | D26: 53-AEO2020.14.highogs-d112619a | E26: trillion Btu | F26: 1.363942 | G26: 0.874623 | H26: 0.578821 | I26: 0.540849 | J26: 0.542672 | K26: 0.541645 | L26: 0.539264 | M26: 0.541933 | N26: 0.551888 | O26: 0.567788 | P26: 0.591194 | Q26: 0.622719 | R26: 0.661326 | S26: 0.703309 | T26: 0.749494 | U26: 0.797724 | V26: 0.849703 | W26: 0.906011 | X26: 0.962579 | Y26: 1.019362 | Z26: 1.077659 | AA26: 1.135478 | AB26: 1.190455 | AC26: 1.243828 | AD26: 1.292459 | AE26: 1.339265 | AF26: 1.387991 | AG26: 1.43479 | AH26: 1.479566 | AI26: 1.523062 | AJ26: 1.563861 | AK26: 1.601922 | AL26: 0.005
B27: Electric-Diesel Hybrid | C27: Fleet Vehicle Energy Use: Alternative-Fuel Cars: Electric-Diesel Hybrid: High oil and gas supply | D27: 53-AEO2020.15.highogs-d112619a | E27: trillion Btu | F27: 0 | G27: 0 | H27: 0 | I27: 0 | J27: 0 | K27: 0 | L27: 0 | M27: 0 | N27: 0 | O27: 0 | P27: 0 | Q27: 0.000145 | R27: 0.000315 | S27: 0.000524 | T27: 0.000788 | U27: 0.001127 | V27: 0.001563 | W27: 0.002122 | X27: 0.002825 | Y27: 0.0037 | Z27: 0.004773 | AA27: 0.006051 | AB27: 0.007548 | AC27: 0.009265 | AD27: 0.011171 | AE27: 0.013266 | AF27: 0.01554 | AG27: 0.017946 | AH27: 0.020444 | AI27: 0.023008 | AJ27: 0.025568 | AK27: 0.028085 | AL27: - -
B28: Electric-Gasoline Hybrid | C28: Fleet Vehicle Energy Use: Alternative-Fuel Cars: Electric-Gasoline Hybrid: High oil and gas supply | D28: 53-AEO2020.16.highogs-d112619a | E28: trillion Btu | F28: 13.613784 | G28: 13.607199 | H28: 13.564078 | I28: 13.436025 | J28: 13.228998 | K28: 13.027976 | L28: 12.725214 | M28: 12.47506 | N28: 12.376129 | O28: 12.392044 | P28: 12.523299 | Q28: 12.779699 | R28: 13.169247 | S28: 13.636745 | T28: 14.20727 | U28: 14.835912 | V28: 15.460705 | W28: 16.119484 | X28: 16.770466 | Y28: 17.423298 | Z28: 18.078686 | AA28: 18.69565 | AB28: 19.302435 | AC28: 19.8997 | AD28: 20.443192 | AE28: 20.971584 | AF28: 21.516411 | AG28: 22.05571 | AH28: 22.587219 | AI28: 23.130789 | AJ28: 23.646286 | AK28: 24.127712 | AL28: 0.019
B29: Natural Gas ICE | C29: Fleet Vehicle Energy Use: Alternative-Fuel Cars: Natural Gas ICE: High oil and gas supply | D29: 53-AEO2020.17.highogs-d112619a | E29: trillion Btu | F29: 0.830366 | G29: 0.706063 | H29: 0.641138 | I29: 0.579731 | J29: 0.519612 | K29: 0.462968 | L29: 0.411885 | M29: 0.369805 | N29: 0.333902 | O29: 0.300844 | P29: 0.272522 | Q29: 0.246651 | R29: 0.224524 | S29: 0.207331 | T29: 0.191111 | U29: 0.181795 | V29: 0.174735 | W29: 0.169508 | X29: 0.164165 | Y29: 0.160584 | Z29: 0.158224 | AA29: 0.15672 | AB29: 0.157729 | AC29: 0.157465 | AD29: 0.15956 | AE29: 0.161776 | AF29: 0.164169 | AG29: 0.166653 | AH29: 0.169214 | AI29: 0.171909 | AJ29: 0.174568 | AK29: 0.177167 | AL29: -0.049
B30: Natural Gas Bi-fuel | C30: Fleet Vehicle Energy Use: Alternative-Fuel Cars: Natural Gas Bi-fuel: High oil and gas supply | D30: 53-AEO2020.18.highogs-d112619a | E30: trillion Btu | F30: 2.367834 | G30: 2.232389 | H30: 2.110601 | I30: 1.993939 | J30: 1.881701 | K30: 1.773208 | L30: 1.662481 | M30: 1.558 | N30: 1.460288 | O30: 1.369818 | P30: 1.292019 | Q30: 1.223412 | R30: 1.166809 | S30: 1.125737 | T30: 1.099217 | U30: 1.082884 | V30: 1.073476 | W30: 1.069697 | X30: 1.067678 | Y30: 1.069523 | Z30: 1.075121 | AA30: 1.082521 | AB30: 1.095845 | AC30: 1.111167 | AD30: 1.126279 | AE30: 1.142025 | AF30: 1.158969 | AG30: 1.176465 | AH30: 1.194424 | AI30: 1.213315 | AJ30: 1.231878 | AK30: 1.249962 | AL30: -0.02
B31: Propane ICE | C31: Fleet Vehicle Energy Use: Alternative-Fuel Cars: Propane ICE: High oil and gas supply | D31: 53-AEO2020.19.highogs-d112619a | E31: trillion Btu | F31: 0.224959 | G31: 0.216045 | H31: 0.208701 | I31: 0.200902 | J31: 0.193619 | K31: 0.187155 | L31: 0.180948 | M31: 0.175562 | N31: 0.170806 | O31: 0.166397 | P31: 0.162446 | Q31: 0.158846 | R31: 0.155697 | S31: 0.151112 | T31: 0.148718 | U31: 0.147321 | V31: 0.146506 | W31: 0.146207 | X31: 0.146334 | Y31: 0.146935 | Z31: 0.148031 | AA31: 0.149437 | AB31: 0.149794 | AC31: 0.15152 | AD31: 0.153466 | AE31: 0.155577 | AF31: 0.157869 | AG31: 0.160271 | AH31: 0.162761 | AI31: 0.165382 | AJ31: 0.16798 | AK31: 0.170528 | AL31: -0.009
B32: Propane Bi-fuel | C32: Fleet Vehicle Energy Use: Alternative-Fuel Cars: Propane Bi-fuel: High oil and gas supply | D32: 53-AEO2020.20.highogs-d112619a | E32: trillion Btu | F32: 0.474689 | G32: 0.458102 | H32: 0.4446 | I32: 0.430259 | J32: 0.416391 | K32: 0.403722 | L32: 0.391227 | M32: 0.380094 | N32: 0.36996 | O32: 0.360607 | P32: 0.352275 | Q32: 0.344722 | R32: 0.338306 | S32: 0.329129 | T32: 0.324391 | U32: 0.321766 | V32: 0.320458 | W32: 0.320241 | X32: 0.320934 | Y32: 0.322601 | Z32: 0.325255 | AA32: 0.328552 | AB32: 0.329739 | AC32: 0.333635 | AD32: 0.337944 | AE32: 0.342594 | AF32: 0.347641 | AG32: 0.352919 | AH32: 0.358389 | AI32: 0.364145 | AJ32: 0.369846 | AK32: 0.375431 | AL32: -0.008
B33: Fuel Cell Methanol | C33: Fleet Vehicle Energy Use: Alternative-Fuel Cars: Fuel Cell Methanol: High oil and gas supply | D33: 53-AEO2020.21.highogs-d112619a | E33: trillion Btu | F33: 0 | G33: 0 | H33: 0 | I33: 0 | J33: 0 | K33: 0 | L33: 0 | M33: 0 | N33: 0 | O33: 0 | P33: 0 | Q33: 0 | R33: 0 | S33: 0 | T33: 0 | U33: 0 | V33: 0 | W33: 0 | X33: 0 | Y33: 0 | Z33: 0 | AA33: 0 | AB33: 0 | AC33: 0 | AD33: 0 | AE33: 0 | AF33: 0 | AG33: 0 | AH33: 0 | AI33: 0 | AJ33: 0 | AK33: 0 | AL33: - -
B34: Fuel Cell Hydrogen | C34: Fleet Vehicle Energy Use: Alternative-Fuel Cars: Fuel Cell Hydrogen: High oil and gas supply | D34: 53-AEO2020.22.highogs-d112619a | E34: trillion Btu | F34: 0.028264 | G34: 0.0337 | H34: 0.03948 | I34: 0.045533 | J34: 0.051886 | K34: 0.058715 | L34: 0.066101 | M34: 0.074338 | N34: 0.083821 | O34: 0.094795 | P34: 0.107395 | Q34: 0.121811 | R34: 0.137729 | S34: 0.154776 | T34: 0.172828 | U34: 0.19162 | V34: 0.210968 | W34: 0.230875 | X34: 0.250988 | Y34: 0.271217 | Z34: 0.291344 | AA34: 0.310874 | AB34: 0.329531 | AC34: 0.347539 | AD34: 0.364525 | AE34: 0.380788 | AF34: 0.39657 | AG34: 0.411653 | AH34: 0.42603 | AI34: 0.43985 | AJ34: 0.452739 | AK34: 0.464655 | AL34: 0.095
B35: Total Alternative Cars | C35: Fleet Vehicle Energy Use: Alternative-Fuel Cars: Total Alternative: High oil and gas supply | D35: 53-AEO2020.23.highogs-d112619a | E35: trillion Btu | F35: 50.35186 | G35: 46.338802 | H35: 43.198601 | I35: 40.742455 | J35: 38.571445 | K35: 36.784294 | L35: 34.925426 | M35: 33.458355 | N35: 32.467735 | O35: 31.83914 | P35: 31.565701 | Q35: 31.620596 | R35: 31.909164 | S35: 32.39669 | T35: 32.952713 | U35: 33.723938 | V35: 34.570953 | W35: 35.477428 | X35: 36.505714 | Y35: 37.623592 | Z35: 38.743382 | AA35: 39.801823 | AB35: 40.9086 | AC35: 42.020203 | AD35: 43.027454 | AE35: 44.026005 | AF35: 45.094044 | AG35: 46.157078 | AH35: 47.202835 | AI35: 48.277092 | AJ35: 49.282043 | AK35: 50.207294 | AL35: 0
B36: Total Car Consumption | C36: Fleet Vehicle Energy Use: Total Cars: High oil and gas supply | D36: 53-AEO2020.25.highogs-d112619a | E36: trillion Btu | F36: 500.84314 | G36: 480.03305 | H36: 459.72555 | I36: 435.27554 | J36: 407.69443 | K36: 384.10715 | L36: 360.20831 | M36: 341.18103 | N36: 327.11252 | O36: 316.80359 | P36: 309.94733 | Q36: 305.92056 | R36: 303.51593 | S36: 302.22461 | T36: 301.5636 | U36: 301.79474 | V36: 302.61743 | W36: 304.44205 | X36: 306.82742 | Y36: 309.80514 | Z36: 313.32071 | AA36: 316.64374 | AB36: 319.99542 | AC36: 324.30847 | AD36: 328.22238 | AE36: 332.58115 | AF36: 337.97061 | AG36: 343.66129 | AH36: 349.45703 | AI36: 355.77017 | AJ36: 361.63034 | AK36: 366.94321 | AL36: -0.01
B37: Light Trucks | D37: 53-AEO2020.27.
B38: Conventional Light Trucks | D38: 53-AEO2020.28.
B39: Gasoline ICE Vehicles | C39: Fleet Vehicle Energy Use: Conventional Light Trucks: Gasoline: High oil and gas supply | D39: 53-AEO2020.29.highogs-d112619a | E39: trillion Btu | F39: 568.10016 | G39: 552.91077 | H39: 535.64282 | I39: 510.24988 | J39: 485.37579 | K39: 461.44977 | L39: 438.13614 | M39: 420.59256 | N39: 406.8963 | O39: 396.17798 | P39: 387.51999 | Q39: 379.19855 | R39: 372.75098 | S39: 366.86487 | T39: 360.47592 | U39: 354.38202 | V39: 348.40802 | W39: 343.42184 | X39: 338.79135 | Y39: 334.78912 | Z39: 331.11493 | AA39: 327.0817 | AB39: 322.94009 | AC39: 319.72043 | AD39: 316.6925 | AE39: 314.37909 | AF39: 312.80878 | AG39: 311.83142 | AH39: 311.25205 | AI39: 311.45258 | AJ39: 311.66006 | AK39: 312.15604 | AL39: -0.019
B40: TDI Diesel ICE | C40: Fleet Vehicle Energy Use: Conventional Light Trucks: TDI Diesel: High oil and gas supply | D40: 53-AEO2020.30.highogs-d112619a | E40: trillion Btu | F40: 2.565835 | G40: 2.699009 | H40: 2.850016 | I40: 3.003111 | J40: 3.165716 | K40: 3.325781 | L40: 3.486581 | M40: 3.666677 | N40: 3.862921 | O40: 4.070833 | P40: 4.292942 | Q40: 4.492619 | R40: 4.690886 | S40: 4.897075 | T40: 5.09718 | U40: 5.283131 | V40: 5.463271 | W40: 5.64104 | X40: 5.80747 | Y40: 5.970589 | Z40: 6.116902 | AA40: 6.241805 | AB40: 6.361677 | AC40: 6.474978 | AD40: 6.57415 | AE40: 6.669425 | AF40: 6.762223 | AG40: 6.851614 | AH40: 6.935315 | AI40: 7.020811 | AJ40: 7.096075 | AK40: 7.167341 | AL40: 0.034
B41: Total Conventional Light Trucks | C41: Fleet Vehicle Energy Use: Conventional Light Trucks: Total: High oil and gas supply | D41: 53-AEO2020.31.highogs-d112619a | E41: trillion Btu | F41: 570.66602 | G41: 555.6098 | H41: 538.49286 | I41: 513.25299 | J41: 488.5415 | K41: 464.77554 | L41: 441.62271 | M41: 424.25925 | N41: 410.75922 | O41: 400.24881 | P41: 391.81293 | Q41: 383.69116 | R41: 377.44186 | S41: 371.76193 | T41: 365.57309 | U41: 359.66516 | V41: 353.87128 | W41: 349.0629 | X41: 344.59882 | Y41: 340.7597 | Z41: 337.23184 | AA41: 333.32349 | AB41: 329.30176 | AC41: 326.1954 | AD41: 323.26666 | AE41: 321.04852 | AF41: 319.57101 | AG41: 318.68304 | AH41: 318.18735 | AI41: 318.47339 | AJ41: 318.75613 | AK41: 319.32336 | AL41: -0.019
B42: Alternative-Fuel Light Trucks | D42: 53-AEO2020.33.
B43: Ethanol-Flex Fuel ICE | C43: Fleet Vehicle Energy Use: Alternative-Fuel Light Trucks: Ethanol-Flex Fuel ICE: High oil and gas supply | D43: 53-AEO2020.34.highogs-d112619a | E43: trillion Btu | F43: 142.73833 | G43: 135.48135 | H43: 128.89867 | I43: 121.53393 | J43: 114.69969 | K43: 108.09987 | L43: 101.45573 | M43: 96.336731 | N43: 92.071152 | O43: 88.464745 | P43: 85.461548 | Q43: 82.537796 | R43: 80.105515 | S43: 77.806274 | T43: 75.616379 | U43: 73.568245 | V43: 71.726913 | W43: 70.179329 | X43: 68.891838 | Y43: 67.673958 | Z43: 66.768082 | AA43: 66.188698 | AB43: 65.617134 | AC43: 65.187965 | AD43: 64.778198 | AE43: 64.540184 | AF43: 64.468712 | AG43: 64.51342 | AH43: 64.615822 | AI43: 64.881531 | AJ43: 65.100204 | AK43: 65.352081 | AL43: -0.025
B44: 100 Mile Electric Vehicle | C44: Fleet Vehicle Energy Use: Alternative-Fuel Light Trucks: 100 Mile Electric Vehicle: High oil and gas supply | D44: 53-AEO2020.35.highogs-d112619a | E44: trillion Btu | F44: 0.002446 | G44: 0.00512 | H44: 0.008881 | I44: 0.014477 | J44: 0.021189 | K44: 0.029221 | L44: 0.038921 | M44: 0.050948 | N44: 0.06536 | O44: 0.082411 | P44: 0.102251 | Q44: 0.124219 | R44: 0.148524 | S44: 0.174862 | T44: 0.202392 | U44: 0.230392 | V44: 0.258861 | W44: 0.287585 | X44: 0.315683 | Y44: 0.342944 | Z44: 0.369229 | AA44: 0.393798 | AB44: 0.416556 | AC44: 0.437547 | AD44: 0.456662 | AE44: 0.474464 | AF44: 0.491118 | AG44: 0.506661 | AH44: 0.520992 | AI44: 0.534549 | AJ44: 0.546666 | AK44: 0.557698 | AL44: 0.191
B45: 200 Mile Electric Vehicle | C45: Fleet Vehicle Energy Use: Alternative-Fuel Light Trucks: 200 Mile Electric Vehicle: High oil and gas supply | D45: 53-AEO2020.36.highogs-d112619a | E45: trillion Btu | F45: 0.01332 | G45: 0.025869 | H45: 0.040931 | I45: 0.058205 | J45: 0.079255 | K45: 0.104505 | L45: 0.134581 | M45: 0.172117 | N45: 0.216873 | O45: 0.269346 | P45: 0.329965 | Q45: 0.395331 | R45: 0.466747 | S45: 0.543452 | T45: 0.621518 | U45: 0.698231 | V45: 0.77465 | W45: 0.851024 | X45: 0.923898 | Y45: 0.993812 | Z45: 1.060044 | AA45: 1.119341 | AB45: 1.172349 | AC45: 1.220581 | AD45: 1.263737 | AE45: 1.305345 | AF45: 1.345677 | AG45: 1.38411 | AH45: 1.419993 | AI45: 1.455551 | AJ45: 1.48701 | AK45: 1.515976 | AL45: 0.165
B46: 300 Mile Electric Vehicle | C46: Fleet Vehicle Energy Use: Alternative-Fuel Light Trucks: 300 Mile Electric Vehicle: High oil and gas supply | D46: 53-AEO2020.37.highogs-d112619a | E46: trillion Btu | F46: 0.275163 | G46: 0.16385 | H46: 0.086896 | I46: 0.090712 | J46: 0.112366 | K46: 0.138865 | L46: 0.171462 | M46: 0.213585 | N46: 0.264766 | O46: 0.325142 | P46: 0.394692 | Q46: 0.46919 | R46: 0.549756 | S46: 0.635241 | T46: 0.721115 | U46: 0.804163 | V46: 0.885429 | W46: 0.965632 | X46: 1.041002 | Y46: 1.112164 | Z46: 1.178551 | AA46: 1.236939 | AB46: 1.288163 | AC46: 1.333923 | AD46: 1.373882 | AE46: 1.411623 | AF46: 1.448245 | AG46: 1.482881 | AH46: 1.514825 | AI46: 1.546445 | AJ46: 1.573922 | AK46: 1.598975 | AL46: 0.058
B47: Plug-in 10 Gasoline Hybrid | C47: Fleet Vehicle Energy Use: Alternative-Fuel Light Trucks: Plug-in 10 Gasoline Hybrid: High oil and gas supply | D47: 53-AEO2020.38.highogs-d112619a | E47: trillion Btu | F47: 0.384475 | G47: 0.331324 | H47: 0.318928 | I47: 0.358486 | J47: 0.406734 | K47: 0.456413 | L47: 0.502876 | M47: 0.556003 | N47: 0.615366 | O47: 0.68075 | P47: 0.75111 | Q47: 0.822478 | R47: 0.895609 | S47: 0.965091 | T47: 1.034486 | U47: 1.100963 | V47: 1.165596 | W47: 1.227844 | X47: 1.286582 | Y47: 1.342551 | Z47: 1.395766 | AA47: 1.444394 | AB47: 1.487176 | AC47: 1.527116 | AD47: 1.562601 | AE47: 1.595467 | AF47: 1.625794 | AG47: 1.654213 | AH47: 1.680378 | AI47: 1.705727 | AJ47: 1.728303 | AK47: 1.749209 | AL47: 0.05
B48: Plug-in 40 Gasoline Hybrid | C48: Fleet Vehicle Energy Use: Alternative-Fuel Light Trucks: Plug-in 40 Gasoline Hybrid: High oil and gas supply | D48: 53-AEO2020.39.highogs-d112619a | E48: trillion Btu | F48: 0.899185 | G48: 0.473342 | H48: 0.219304 | I48: 0.192021 | J48: 0.204038 | K48: 0.219625 | L48: 0.238968 | M48: 0.268793 | N48: 0.309807 | O48: 0.360464 | P48: 0.418627 | Q48: 0.480481 | R48: 0.546234 | S48: 0.614612 | T48: 0.68197 | U48: 0.74655 | V48: 0.810626 | W48: 0.875395 | X48: 0.937216 | Y48: 0.99647 | Z48: 1.052811 | AA48: 1.104652 | AB48: 1.152623 | AC48: 1.195828 | AD48: 1.233707 | AE48: 1.268777 | AF48: 1.302687 | AG48: 1.334044 | AH48: 1.362586 | AI48: 1.389534 | AJ48: 1.413311 | AK48: 1.434876 | AL48: 0.015
B49: Electric-Diesel Hybrid | C49: Fleet Vehicle Energy Use: Alternative-Fuel Light Trucks: Electric-Diesel Hybrid: High oil and gas supply | D49: 53-AEO2020.40.highogs-d112619a | E49: trillion Btu | F49: 0 | G49: 0 | H49: 0 | I49: 0 | J49: 0 | K49: 0 | L49: 0 | M49: 0.000415 | N49: 0.000876 | O49: 0.001417 | P49: 0.002076 | Q49: 0.002871 | R49: 0.00385 | S49: 0.005056 | T49: 0.006512 | U49: 0.008241 | V49: 0.010293 | W49: 0.012704 | X49: 0.015458 | Y49: 0.018559 | Z49: 0.021969 | AA49: 0.025586 | AB49: 0.029344 | AC49: 0.033187 | AD49: 0.037033 | AE49: 0.040897 | AF49: 0.044738 | AG49: 0.04852 | AH49: 0.052192 | AI49: 0.05578 | AJ49: 0.059174 | AK49: 0.062401 | AL49: - -
B50: Electric-Gasoline Hybrid | C50: Fleet Vehicle Energy Use: Alternative-Fuel Light Trucks: Electric-Gasoline Hybrid: High oil and gas supply | D50: 53-AEO2020.41.highogs-d112619a | E50: trillion Btu | F50: 2.858212 | G50: 2.90564 | H50: 3.053677 | I50: 3.214275 | J50: 3.400567 | K50: 3.569194 | L50: 3.739361 | M50: 3.974805 | N50: 4.325826 | O50: 4.74618 | P50: 5.226252 | Q50: 5.726843 | R50: 6.237164 | S50: 6.762164 | T50: 7.25229 | U50: 7.711092 | V50: 8.136974 | W50: 8.541106 | X50: 8.904173 | Y50: 9.240955 | Z50: 9.548384 | AA50: 9.806446 | AB50: 10.024403 | AC50: 10.213916 | AD50: 10.374847 | AE50: 10.531025 | AF50: 10.68647 | AG50: 10.840936 | AH50: 10.990467 | AI50: 11.1508 | AJ50: 11.296684 | AK50: 11.43774 | AL50: 0.046
B51: Natural Gas ICE | C51: Fleet Vehicle Energy Use: Alternative-Fuel Light Trucks: Natural Gas ICE: High oil and gas supply | D51: 53-AEO2020.42.highogs-d112619a | E51: trillion Btu | F51: 1.073714 | G51: 0.906476 | H51: 0.835966 | I51: 0.76888 | J51: 0.704021 | K51: 0.640557 | L51: 0.587279 | M51: 0.541229 | N51: 0.505911 | O51: 0.475379 | P51: 0.446372 | Q51: 0.420539 | R51: 0.396258 | S51: 0.377402 | T51: 0.356891 | U51: 0.344442 | V51: 0.333208 | W51: 0.323929 | X51: 0.315957 | Y51: 0.309439 | Z51: 0.303644 | AA51: 0.297963 | AB51: 0.294904 | AC51: 0.290706 | AD51: 0.288503 | AE51: 0.286551 | AF51: 0.285 | AG51: 0.283872 | AH51: 0.283113 | AI51: 0.282888 | AJ51: 0.282873 | AK51: 0.283197 | AL51: -0.042
B52: Natural Gas Bi-fuel | C52: Fleet Vehicle Energy Use: Alternative-Fuel Light Trucks: Natural Gas Bi-fuel: High oil and gas supply | D52: 53-AEO2020.43.highogs-d112619a | E52: trillion Btu | F52: 2.53685 | G52: 2.435248 | H52: 2.339967 | I52: 2.245935 | J52: 2.158377 | K52: 2.069012 | L52: 1.992855 | M52: 1.917711 | N52: 1.857766 | O52: 1.805031 | P52: 1.756099 | Q52: 1.706785 | R52: 1.65922 | S52: 1.618849 | T52: 1.581748 | U52: 1.551523 | V52: 1.52388 | W52: 1.500988 | X52: 1.480864 | Y52: 1.464526 | Z52: 1.45015 | AA52: 1.435666 | AB52: 1.424317 | AC52: 1.413909 | AD52: 1.403476 | AE52: 1.394192 | AF52: 1.386728 | AG52: 1.381082 | AH52: 1.376982 | AI52: 1.375303 | AJ52: 1.374285 | AK52: 1.374623 | AL52: -0.02
B53: Propane ICE | C53: Fleet Vehicle Energy Use: Alternative-Fuel Light Trucks: Propane ICE: High oil and gas supply | D53: 53-AEO2020.44.highogs-d112619a | E53: trillion Btu | F53: 0.981018 | G53: 0.901186 | H53: 0.828676 | I53: 0.763348 | J53: 0.705488 | K53: 0.650533 | L53: 0.605833 | M53: 0.561972 | N53: 0.526143 | O53: 0.494508 | P53: 0.466006 | Q53: 0.438376 | R53: 0.4125 | S53: 0.393176 | T53: 0.376721 | U53: 0.364424 | V53: 0.353368 | W53: 0.344344 | X53: 0.336594 | Y53: 0.330222 | Z53: 0.324425 | AA53: 0.318594 | AB53: 0.315458 | AC53: 0.312983 | AD53: 0.310564 | AE53: 0.308349 | AF53: 0.306479 | AG53: 0.304959 | AH53: 0.303751 | AI53: 0.303031 | AJ53: 0.302497 | AK53: 0.302286 | AL53: -0.037
B54: Propane Bi-fuel | C54: Fleet Vehicle Energy Use: Alternative-Fuel Light Trucks: Propane Bi-fuel: High oil and gas supply | D54: 53-AEO2020.45.highogs-d112619a | E54: trillion Btu | F54: 4.798648 | G54: 4.327915 | H54: 3.891844 | I54: 3.495167 | J54: 3.138191 | K54: 2.798132 | L54: 2.516139 | M54: 2.236 | N54: 2.003124 | O54: 1.796148 | P54: 1.610109 | Q54: 1.432494 | R54: 1.260293 | S54: 1.158262 | T54: 1.071969 | U54: 1.010499 | V54: 0.95696 | W54: 0.915705 | X54: 0.881985 | Y54: 0.854996 | Z54: 0.830583 | AA54: 0.804865 | AB54: 0.798908 | AC54: 0.793135 | AD54: 0.787277 | AE54: 0.782113 | AF54: 0.77803 | AG54: 0.775014 | AH54: 0.772869 | AI54: 0.77212 | AJ54: 0.771701 | AK54: 0.77201 | AL54: -0.057
B55: Fuel Cell Methanol | C55: Fleet Vehicle Energy Use: Alternative-Fuel Light Trucks: Fuel Cell Methanol: High oil and gas supply | D55: 53-AEO2020.46.highogs-d112619a | E55: trillion Btu | F55: 0 | G55: 0 | H55: 0 | I55: 0 | J55: 0 | K55: 0 | L55: 0 | M55: 0 | N55: 0 | O55: 0 | P55: 0 | Q55: 0 | R55: 0 | S55: 0 | T55: 0 | U55: 0 | V55: 0 | W55: 0 | X55: 0 | Y55: 0 | Z55: 0 | AA55: 0 | AB55: 0 | AC55: 0 | AD55: 0 | AE55: 0 | AF55: 0 | AG55: 0 | AH55: 0 | AI55: 0 | AJ55: 0 | AK55: 0 | AL55: - -
